Workbook

Sheet COVERAGE
A1: Reconnaissance | B1: {=SUM(IF(B2:B200<>"",B2:B200,0))/SUM(IF(A2:A200<>"",1,0))} -> 0.033333333 | C1: Resource Development | D1: {=SUM(IF(D2:D200<>"",D2:D200,0))/SUM(IF(C2:C200<>"",1,0))} -> 0 | E1: Initial Access | F1: {=SUM(IF(F2:F200<>"",F2:F200,0))/SUM(IF(E2:E200<>"",1,0))} -> 0 | G1: Execution | H1: {=SUM(IF(H2:H200<>"",H2:H200,0))/SUM(IF(G2:G200<>"",1,0))} -> 0.0064935065 | I1: Persistence | J1: {=SUM(IF(J2:J200<>"",J2:J200,0))/SUM(IF(I2:I200<>"",1,0))} -> 0 | K1: Privilege Escalation | L1: {=SUM(IF(L2:L200<>"",L2:L200,0))/SUM(IF(K2:K200<>"",1,0))} -> 0 | M1: Defense Evasion | N1: {=SUM(IF(N2:N200<>"",N2:N200,0))/SUM(IF(M2:M200<>"",1,0))} -> 0.026623377 | O1: Credential Access | P1: {=SUM(IF(P2:P200<>"",P2:P200,0))/SUM(IF(O2:O200<>"",1,0))} -> 0.014705882 | Q1: Discovery | R1: {=SUM(IF(R2:R200<>"",R2:R200,0))/SUM(IF(Q2:Q200<>"",1,0))} -> 0.046875 | S1: Lateral Movement | T1: {=SUM(IF(T2:T200<>"",T2:T200,0))/SUM(IF(S2:S200<>"",1,0))} -> 0 | U1: Collection | V1: {=SUM(IF(V2:V200<>"",V2:V200,0))/SUM(IF(U2:U200<>"",1,0))} -> 0 | W1: Command and Control | X1: {=SUM(IF(X2:X200<>"",X2:X200,0))/SUM(IF(W2:W200<>"",1,0))} -> 0 | Y1: Exfiltration | Z1: {=SUM(IF(Z2:Z200<>"",Z2:Z200,0))/SUM(IF(Y2:Y200<>"",1,0))} -> 0.11111111 | AA1: Impact | AB1: {=SUM(IF(AB2:AB200<>"",AB2:AB200,0))/SUM(IF(AA2:AA200<>"",1,0))} -> 0
A2: Active Scanning (T1595) | B2: =IF(A2<>"",IF(INDEX(Techniques[Coverage],MATCH(A2,Techniques[Name],0))>0,INDEX(Techniques[Coverage],MATCH(A2,Techniques[Name],0)),""),"") -> 0.33333333 | C2: Acquire Access (T1650) | D2: =IF(C2<>"",IF(INDEX(Techniques[Coverage],MATCH(C2,Techniques[Name],0))>0,INDEX(Techniques[Coverage],MATCH(C2,Techniques[Name],0)),""),"") | E2: Content Injection (T1659) | F2: =IF(E2<>"",IF(INDEX(Techniques[Coverage],MATCH(E2,Techniques[Name],0))>0,INDEX(Techniques[Coverage],MATCH(E2,Techniques[Name],0)),""),"") | G2: Cloud Administration Command (T1651) | H2: =IF(G2<>"",IF(INDEX(Techniques[Coverage],MATCH(G2,Techniques[Name],0))>0,INDEX(Techniques[Coverage],MATCH(G2,Techniques[Name],0)),""),"") | I2: Account Manipulation (T1098) | J2: =IF(I2<>"",IF(INDEX(Techniques[Coverage],MATCH(I2,Techniques[Name],0))>0,INDEX(Techniques[Coverage],MATCH(I2,Techniques[Name],0)),""),"") | K2: Abuse Elevation Control Mechanism (T1548) | L2: =IF(K2<>"",IF(INDEX(Techniques[Coverage],MATCH(K2,Techniques[Name],0))>0,INDEX(Techniques[Coverage],MATCH(K2,Techniques[Name],0)),""),"") | M2: Abuse Elevation Control Mechanism (T1548) | N2: =IF(M2<>"",IF(INDEX(Techniques[Coverage],MATCH(M2,Techniques[Name],0))>0,INDEX(Techniques[Coverage],MATCH(M2,Techniques[Name],0)),""),"") | O2: Adversary-in-the-Middle (T1557) | P2: =IF(O2<>"",IF(INDEX(Techniques[Coverage],MATCH(O2,Techniques[Name],0))>0,INDEX(Techniques[Coverage],MATCH(O2,Techniques[Name],0)),""),"") | Q2: Account Discovery (T1087) | R2: =IF(Q2<>"",IF(INDEX(Techniques[Coverage],MATCH(Q2,Techniques[Name],0))>0,INDEX(Techniques[Coverage],MATCH(Q2,Techniques[Name],0)),""),"") | S2: Exploitation of Remote Services (T1210) | T2: =IF(S2<>"",IF(INDEX(Techniques[Coverage],MATCH(S2,Techniques[Name],0))>0,INDEX(Techniques[Coverage],MATCH(S2,Techniques[Name],0)),""),"") | U2: Adversary-in-the-Middle (T1557) | V2: =IF(U2<>"",IF(INDEX(Techniques[Coverage],MATCH(U2,Techniques[Name],0))>0,INDEX(Techniques[Coverage],MATCH(U2,Techniques[Name],0)),""),"") | W2: Application Layer Protocol (T1071) | X2: =IF(W2<>"",IF(INDEX(Techniques[Coverage],MATCH(W2,Techniques[Name],0))>0,INDEX(Techniques[Coverage],MATCH(W2,Techniques[Name],0)),""),"") | Y2: Automated Exfiltration (T1020) | Z2: =IF(Y2<>"",IF(INDEX(Techniques[Coverage],MATCH(Y2,Techniques[Name],0))>0,INDEX(Techniques[Coverage],MATCH(Y2,Techniques[Name],0)),""),"") -> 1 | AA2: Account Access Removal (T1531) | AB2: =IF(AA2<>"",IF(INDEX(Techniques[Coverage],MATCH(AA2,Techniques[Name],0))>0,INDEX(Techniques[Coverage],MATCH(AA2,Techniques[Name],0)),""),"")
A3: Gather Victim Host Information (T1592) | B3: =IF(A3<>"",IF(INDEX(Techniques[Coverage],MATCH(A3,Techniques[Name],0))>0,INDEX(Techniques[Coverage],MATCH(A3,Techniques[Name],0)),""),"") | C3: Acquire Infrastructure (T1583) | D3: =IF(C3<>"",IF(INDEX(Techniques[Coverage],MATCH(C3,Techniques[Name],0))>0,INDEX(Techniques[Coverage],MATCH(C3,Techniques[Name],0)),""),"") | E3: Drive-by Compromise (T1189) | F3: =IF(E3<>"",IF(INDEX(Techniques[Coverage],MATCH(E3,Techniques[Name],0))>0,INDEX(Techniques[Coverage],MATCH(E3,Techniques[Name],0)),""),"") | G3: Command and Scripting Interpreter (T1059) | H3: =IF(G3<>"",IF(INDEX(Techniques[Coverage],MATCH(G3,Techniques[Name],0))>0,INDEX(Techniques[Coverage],MATCH(G3,Techniques[Name],0)),""),"") -> 0.090909091 | I3: BITS Jobs (T1197) | J3: =IF(I3<>"",IF(INDEX(Techniques[Coverage],MATCH(I3,Techniques[Name],0))>0,INDEX(Techniques[Coverage],MATCH(I3,Techniques[Name],0)),""),"") | K3: Access Token Manipulation (T1134) | L3: =IF(K3<>"",IF(INDEX(Techniques[Coverage],MATCH(K3,Techniques[Name],0))>0,INDEX(Techniques[Coverage],MATCH(K3,Techniques[Name],0)),""),"") | M3: Access Token Manipulation (T1134) | N3: =IF(M3<>"",IF(INDEX(Techniques[Coverage],MATCH(M3,Techniques[Name],0))>0,INDEX(Techniques[Coverage],MATCH(M3,Techniques[Name],0)),""),"") | O3: Brute Force (T1110) | P3: =IF(O3<>"",IF(INDEX(Techniques[Coverage],MATCH(O3,Techniques[Name],0))>0,INDEX(Techniques[Coverage],MATCH(O3,Techniques[Name],0)),""),"") | Q3: Application Window Discovery (T1010) | R3: =IF(Q3<>"",IF(INDEX(Techniques[Coverage],MATCH(Q3,Techniques[Name],0))>0,INDEX(Techniques[Coverage],MATCH(Q3,Techniques[Name],0)),""),"") -> 1 | S3: Internal Spearphishing (T1534) | T3: =IF(S3<>"",IF(INDEX(Techniques[Coverage],MATCH(S3,Techniques[Name],0))>0,INDEX(Techniques[Coverage],MATCH(S3,Techniques[Name],0)),""),"") | U3: Archive Collected Data (T1560) | V3: =IF(U3<>"",IF(INDEX(Techniques[Coverage],MATCH(U3,Techniques[Name],0))>0,INDEX(Techniques[Coverage],MATCH(U3,Techniques[Name],0)),""),"") | W3: Communication Through Removable Media (T1092) | X3: =IF(W3<>"",IF(INDEX(Techniques[Coverage],MATCH(W3,Techniques[Name],0))>0,INDEX(Techniques[Coverage],MATCH(W3,Techniques[Name],0)),""),"") | Y3: Data Transfer Size Limits (T1030) | Z3: =IF(Y3<>"",IF(INDEX(Techniques[Coverage],MATCH(Y3,Techniques[Name],0))>0,INDEX(Techniques[Coverage],MATCH(Y3,Techniques[Name],0)),""),"") | AA3: Data Destruction (T1485) | AB3: =IF(AA3<>"",IF(INDEX(Techniques[Coverage],MATCH(AA3,Techniques[Name],0))>0,INDEX(Techniques[Coverage],MATCH(AA3,Techniques[Name],0)),""),"")
A4: Gather Victim Identity Information (T1589) | B4: =IF(A4<>"",IF(INDEX(Techniques[Coverage],MATCH(A4,Techniques[Name],0))>0,INDEX(Techniques[Coverage],MATCH(A4,Techniques[Name],0)),""),"") | C4: Compromise Accounts (T1586) | D4: =IF(C4<>"",IF(INDEX(Techniques[Coverage],MATCH(C4,Techniques[Name],0))>0,INDEX(Techniques[Coverage],MATCH(C4,Techniques[Name],0)),""),"") | E4: Exploit Public-Facing Application (T1190) | F4: =IF(E4<>"",IF(INDEX(Techniques[Coverage],MATCH(E4,Techniques[Name],0))>0,INDEX(Techniques[Coverage],MATCH(E4,Techniques[Name],0)),""),"") | G4: Container Administration Command (T1609) | H4: =IF(G4<>"",IF(INDEX(Techniques[Coverage],MATCH(G4,Techniques[Name],0))>0,INDEX(Techniques[Coverage],MATCH(G4,Techniques[Name],0)),""),"") | I4: Boot or Logon Autostart Execution (T1547) | J4: =IF(I4<>"",IF(INDEX(Techniques[Coverage],MATCH(I4,Techniques[Name],0))>0,INDEX(Techniques[Coverage],MATCH(I4,Techniques[Name],0)),""),"") | K4: Account Manipulation (T1098) | L4: =IF(K4<>"",IF(INDEX(Techniques[Coverage],MATCH(K4,Techniques[Name],0))>0,INDEX(Techniques[Coverage],MATCH(K4,Techniques[Name],0)),""),"") | M4: BITS Jobs (T1197) | N4: =IF(M4<>"",IF(INDEX(Techniques[Coverage],MATCH(M4,Techniques[Name],0))>0,INDEX(Techniques[Coverage],MATCH(M4,Techniques[Name],0)),""),"") | O4: Credentials from Password Stores (T1555) | P4: =IF(O4<>"",IF(INDEX(Techniques[Coverage],MATCH(O4,Techniques[Name],0))>0,INDEX(Techniques[Coverage],MATCH(O4,Techniques[Name],0)),""),"") | Q4: Browser Information Discovery (T1217) | R4: =IF(Q4<>"",IF(INDEX(Techniques[Coverage],MATCH(Q4,Techniques[Name],0))>0,INDEX(Techniques[Coverage],MATCH(Q4,Techniques[Name],0)),""),"") | S4: Lateral Tool Transfer (T1570) | T4: =IF(S4<>"",IF(INDEX(Techniques[Coverage],MATCH(S4,Techniques[Name],0))>0,INDEX(Techniques[Coverage],MATCH(S4,Techniques[Name],0)),""),"") | U4: Audio Capture (T1123) | V4: =IF(U4<>"",IF(INDEX(Techniques[Coverage],MATCH(U4,Techniques[Name],0))>0,INDEX(Techniques[Coverage],MATCH(U4,Techniques[Name],0)),""),"") | W4: Content Injection (T1659) | X4: =IF(W4<>"",IF(INDEX(Techniques[Coverage],MATCH(W4,Techniques[Name],0))>0,INDEX(Techniques[Coverage],MATCH(W4,Techniques[Name],0)),""),"") | Y4: Exfiltration Over Alternative Protocol (T1048) | Z4: =IF(Y4<>"",IF(INDEX(Techniques[Coverage],MATCH(Y4,Techniques[Name],0))>0,INDEX(Techniques[Coverage],MATCH(Y4,Techniques[Name],0)),""),"") | AA4: Data Encrypted for Impact (T1486) | AB4: =IF(AA4<>"",IF(INDEX(Techniques[Coverage],MATCH(AA4,Techniques[Name],0))>0,INDEX(Techniques[Coverage],MATCH(AA4,Techniques[Name],0)),""),"")
A5: Gather Victim Network Information (T1590) | B5: =IF(A5<>"",IF(INDEX(Techniques[Coverage],MATCH(A5,Techniques[Name],0))>0,INDEX(Techniques[Coverage],MATCH(A5,Techniques[Name],0)),""),"") | C5: Compromise Infrastructure (T1584) | D5: =IF(C5<>"",IF(INDEX(Techniques[Coverage],MATCH(C5,Techniques[Name],0))>0,INDEX(Techniques[Coverage],MATCH(C5,Techniques[Name],0)),""),"") | E5: External Remote Services (T1133) | F5: =IF(E5<>"",IF(INDEX(Techniques[Coverage],MATCH(E5,Techniques[Name],0))>0,INDEX(Techniques[Coverage],MATCH(E5,Techniques[Name],0)),""),"") | G5: Deploy Container (T1610) | H5: =IF(G5<>"",IF(INDEX(Techniques[Coverage],MATCH(G5,Techniques[Name],0))>0,INDEX(Techniques[Coverage],MATCH(G5,Techniques[Name],0)),""),"") | I5: Boot or Logon Initialization Scripts (T1037) | J5: =IF(I5<>"",IF(INDEX(Techniques[Coverage],MATCH(I5,Techniques[Name],0))>0,INDEX(Techniques[Coverage],MATCH(I5,Techniques[Name],0)),""),"") | K5: Boot or Logon Autostart Execution (T1547) | L5: =IF(K5<>"",IF(INDEX(Techniques[Coverage],MATCH(K5,Techniques[Name],0))>0,INDEX(Techniques[Coverage],MATCH(K5,Techniques[Name],0)),""),"") | M5: Build Image on Host (T1612) | N5: =IF(M5<>"",IF(INDEX(Techniques[Coverage],MATCH(M5,Techniques[Name],0))>0,INDEX(Techniques[Coverage],MATCH(M5,Techniques[Name],0)),""),"") | O5: Exploitation for Credential Access (T1212) | P5: =IF(O5<>"",IF(INDEX(Techniques[Coverage],MATCH(O5,Techniques[Name],0))>0,INDEX(Techniques[Coverage],MATCH(O5,Techniques[Name],0)),""),"") | Q5: Cloud Infrastructure Discovery (T1580) | R5: =IF(Q5<>"",IF(INDEX(Techniques[Coverage],MATCH(Q5,Techniques[Name],0))>0,INDEX(Techniques[Coverage],MATCH(Q5,Techniques[Name],0)),""),"") | S5: Remote Service Session Hijacking (T1563) | T5: =IF(S5<>"",IF(INDEX(Techniques[Coverage],MATCH(S5,Techniques[Name],0))>0,INDEX(Techniques[Coverage],MATCH(S5,Techniques[Name],0)),""),"") | U5: Automated Collection (T1119) | V5: =IF(U5<>"",IF(INDEX(Techniques[Coverage],MATCH(U5,Techniques[Name],0))>0,INDEX(Techniques[Coverage],MATCH(U5,Techniques[Name],0)),""),"") | W5: Data Encoding (T1132) | X5: =IF(W5<>"",IF(INDEX(Techniques[Coverage],MATCH(W5,Techniques[Name],0))>0,INDEX(Techniques[Coverage],MATCH(W5,Techniques[Name],0)),""),"") | Y5: Exfiltration Over C2 Channel (T1041) | Z5: =IF(Y5<>"",IF(INDEX(Techniques[Coverage],MATCH(Y5,Techniques[Name],0))>0,INDEX(Techniques[Coverage],MATCH(Y5,Techniques[Name],0)),""),"") | AA5: Data Manipulation (T1565) | AB5: =IF(AA5<>"",IF(INDEX(Techniques[Coverage],MATCH(AA5,Techniques[Name],0))>0,INDEX(Techniques[Coverage],MATCH(AA5,Techniques[Name],0)),""),"")
A6: Gather Victim Org Information (T1591) | B6: =IF(A6<>"",IF(INDEX(Techniques[Coverage],MATCH(A6,Techniques[Name],0))>0,INDEX(Techniques[Coverage],MATCH(A6,Techniques[Name],0)),""),"") | C6: Develop Capabilities (T1587) | D6: =IF(C6<>"",IF(INDEX(Techniques[Coverage],MATCH(C6,Techniques[Name],0))>0,INDEX(Techniques[Coverage],MATCH(C6,Techniques[Name],0)),""),"") | E6: Hardware Additions (T1200) | F6: =IF(E6<>"",IF(INDEX(Techniques[Coverage],MATCH(E6,Techniques[Name],0))>0,INDEX(Techniques[Coverage],MATCH(E6,Techniques[Name],0)),""),"") | G6: Exploitation for Client Execution (T1203) | H6: =IF(G6<>"",IF(INDEX(Techniques[Coverage],MATCH(G6,Techniques[Name],0))>0,INDEX(Techniques[Coverage],MATCH(G6,Techniques[Name],0)),""),"") | I6: Browser Extensions (T1176) | J6: =IF(I6<>"",IF(INDEX(Techniques[Coverage],MATCH(I6,Techniques[Name],0))>0,INDEX(Techniques[Coverage],MATCH(I6,Techniques[Name],0)),""),"") | K6: Boot or Logon Initialization Scripts (T1037) | L6: =IF(K6<>"",IF(INDEX(Techniques[Coverage],MATCH(K6,Techniques[Name],0))>0,INDEX(Techniques[Coverage],MATCH(K6,Techniques[Name],0)),""),"") | M6: Debugger Evasion (T1622) | N6: =IF(M6<>"",IF(INDEX(Techniques[Coverage],MATCH(M6,Techniques[Name],0))>0,INDEX(Techniques[Coverage],MATCH(M6,Techniques[Name],0)),""),"") | O6: Forced Authentication (T1187) | P6: =IF(O6<>"",IF(INDEX(Techniques[Coverage],MATCH(O6,Techniques[Name],0))>0,INDEX(Techniques[Coverage],MATCH(O6,Techniques[Name],0)),""),"") | Q6: Cloud Service Dashboard (T1538) | R6: =IF(Q6<>"",IF(INDEX(Techniques[Coverage],MATCH(Q6,Techniques[Name],0))>0,INDEX(Techniques[Coverage],MATCH(Q6,Techniques[Name],0)),""),"") | S6: Remote Services (T1021) | T6: =IF(S6<>"",IF(INDEX(Techniques[Coverage],MATCH(S6,Techniques[Name],0))>0,INDEX(Techniques[Coverage],MATCH(S6,Techniques[Name],0)),""),"") | U6: Browser Session Hijacking (T1185) | V6: =IF(U6<>"",IF(INDEX(Techniques[Coverage],MATCH(U6,Techniques[Name],0))>0,INDEX(Techniques[Coverage],MATCH(U6,Techniques[Name],0)),""),"") | W6: Data Obfuscation (T1001) | X6: =IF(W6<>"",IF(INDEX(Techniques[Coverage],MATCH(W6,Techniques[Name],0))>0,INDEX(Techniques[Coverage],MATCH(W6,Techniques[Name],0)),""),"") | Y6: Exfiltration Over Other Network Medium (T1011) | Z6: =IF(Y6<>"",IF(INDEX(Techniques[Coverage],MATCH(Y6,Techniques[Name],0))>0,INDEX(Techniques[Coverage],MATCH(Y6,Techniques[Name],0)),""),"") | AA6: Defacement (T1491) | AB6: =IF(AA6<>"",IF(INDEX(Techniques[Coverage],MATCH(AA6,Techniques[Name],0))>0,INDEX(Techniques[Coverage],MATCH(AA6,Techniques[Name],0)),""),"")
A7: Phishing for Information (T1598) | B7: =IF(A7<>"",IF(INDEX(Techniques[Coverage],MATCH(A7,Techniques[Name],0))>0,INDEX(Techniques[Coverage],MATCH(A7,Techniques[Name],0)),""),"") | C7: Establish Accounts (T1585) | D7: =IF(C7<>"",IF(INDEX(Techniques[Coverage],MATCH(C7,Techniques[Name],0))>0,INDEX(Techniques[Coverage],MATCH(C7,Techniques[Name],0)),""),"") | E7: Phishing (T1566) | F7: =IF(E7<>"",IF(INDEX(Techniques[Coverage],MATCH(E7,Techniques[Name],0))>0,INDEX(Techniques[Coverage],MATCH(E7,Techniques[Name],0)),""),"") | G7: Inter-Process Communication (T1559) | H7: =IF(G7<>"",IF(INDEX(Techniques[Coverage],MATCH(G7,Techniques[Name],0))>0,INDEX(Techniques[Coverage],MATCH(G7,Techniques[Name],0)),""),"") | I7: Compromise Host Software Binary (T1554) | J7: =IF(I7<>"",IF(INDEX(Techniques[Coverage],MATCH(I7,Techniques[Name],0))>0,INDEX(Techniques[Coverage],MATCH(I7,Techniques[Name],0)),""),"") | K7: Create or Modify System Process (T1543) | L7: =IF(K7<>"",IF(INDEX(Techniques[Coverage],MATCH(K7,Techniques[Name],0))>0,INDEX(Techniques[Coverage],MATCH(K7,Techniques[Name],0)),""),"") | M7: Deobfuscate/Decode Files or Information (T1140) | N7: =IF(M7<>"",IF(INDEX(Techniques[Coverage],MATCH(M7,Techniques[Name],0))>0,INDEX(Techniques[Coverage],MATCH(M7,Techniques[Name],0)),""),"") | O7: Forge Web Credentials (T1606) | P7: =IF(O7<>"",IF(INDEX(Techniques[Coverage],MATCH(O7,Techniques[Name],0))>0,INDEX(Techniques[Coverage],MATCH(O7,Techniques[Name],0)),""),"") | Q7: Cloud Service Discovery (T1526) | R7: =IF(Q7<>"",IF(INDEX(Techniques[Coverage],MATCH(Q7,Techniques[Name],0))>0,INDEX(Techniques[Coverage],MATCH(Q7,Techniques[Name],0)),""),"") | S7: Replication Through Removable Media (T1091) | T7: =IF(S7<>"",IF(INDEX(Techniques[Coverage],MATCH(S7,Techniques[Name],0))>0,INDEX(Techniques[Coverage],MATCH(S7,Techniques[Name],0)),""),"") | U7: Clipboard Data (T1115) | V7: =IF(U7<>"",IF(INDEX(Techniques[Coverage],MATCH(U7,Techniques[Name],0))>0,INDEX(Techniques[Coverage],MATCH(U7,Techniques[Name],0)),""),"") | W7: Dynamic Resolution (T1568) | X7: =IF(W7<>"",IF(INDEX(Techniques[Coverage],MATCH(W7,Techniques[Name],0))>0,INDEX(Techniques[Coverage],MATCH(W7,Techniques[Name],0)),""),"") | Y7: Exfiltration Over Physical Medium (T1052) | Z7: =IF(Y7<>"",IF(INDEX(Techniques[Coverage],MATCH(Y7,Techniques[Name],0))>0,INDEX(Techniques[Coverage],MATCH(Y7,Techniques[Name],0)),""),"") | AA7: Disk Wipe (T1561) | AB7: =IF(AA7<>"",IF(INDEX(Techniques[Coverage],MATCH(AA7,Techniques[Name],0))>0,INDEX(Techniques[Coverage],MATCH(AA7,Techniques[Name],0)),""),"")
A8: Search Closed Sources (T1597) | B8: =IF(A8<>"",IF(INDEX(Techniques[Coverage],MATCH(A8,Techniques[Name],0))>0,INDEX(Techniques[Coverage],MATCH(A8,Techniques[Name],0)),""),"") | C8: Obtain Capabilities (T1588) | D8: =IF(C8<>"",IF(INDEX(Techniques[Coverage],MATCH(C8,Techniques[Name],0))>0,INDEX(Techniques[Coverage],MATCH(C8,Techniques[Name],0)),""),"") | E8: Replication Through Removable Media (T1091) | F8: =IF(E8<>"",IF(INDEX(Techniques[Coverage],MATCH(E8,Techniques[Name],0))>0,INDEX(Techniques[Coverage],MATCH(E8,Techniques[Name],0)),""),"") | G8: Native API (T1106) | H8: =IF(G8<>"",IF(INDEX(Techniques[Coverage],MATCH(G8,Techniques[Name],0))>0,INDEX(Techniques[Coverage],MATCH(G8,Techniques[Name],0)),""),"") | I8: Create Account (T1136) | J8: =IF(I8<>"",IF(INDEX(Techniques[Coverage],MATCH(I8,Techniques[Name],0))>0,INDEX(Techniques[Coverage],MATCH(I8,Techniques[Name],0)),""),"") | K8: Domain or Tenant Policy Modification (T1484) | L8: =IF(K8<>"",IF(INDEX(Techniques[Coverage],MATCH(K8,Techniques[Name],0))>0,INDEX(Techniques[Coverage],MATCH(K8,Techniques[Name],0)),""),"") | M8: Deploy Container (T1610) | N8: =IF(M8<>"",IF(INDEX(Techniques[Coverage],MATCH(M8,Techniques[Name],0))>0,INDEX(Techniques[Coverage],MATCH(M8,Techniques[Name],0)),""),"") | O8: Input Capture (T1056) | P8: =IF(O8<>"",IF(INDEX(Techniques[Coverage],MATCH(O8,Techniques[Name],0))>0,INDEX(Techniques[Coverage],MATCH(O8,Techniques[Name],0)),""),"") | Q8: Cloud Storage Object Discovery (T1619) | R8: =IF(Q8<>"",IF(INDEX(Techniques[Coverage],MATCH(Q8,Techniques[Name],0))>0,INDEX(Techniques[Coverage],MATCH(Q8,Techniques[Name],0)),""),"") | S8: Software Deployment Tools (T1072) | T8: =IF(S8<>"",IF(INDEX(Techniques[Coverage],MATCH(S8,Techniques[Name],0))>0,INDEX(Techniques[Coverage],MATCH(S8,Techniques[Name],0)),""),"") | U8: Data Staged (T1074) | V8: =IF(U8<>"",IF(INDEX(Techniques[Coverage],MATCH(U8,Techniques[Name],0))>0,INDEX(Techniques[Coverage],MATCH(U8,Techniques[Name],0)),""),"") | W8: Encrypted Channel (T1573) | X8: =IF(W8<>"",IF(INDEX(Techniques[Coverage],MATCH(W8,Techniques[Name],0))>0,INDEX(Techniques[Coverage],MATCH(W8,Techniques[Name],0)),""),"") | Y8: Exfiltration Over Web Service (T1567) | Z8: =IF(Y8<>"",IF(INDEX(Techniques[Coverage],MATCH(Y8,Techniques[Name],0))>0,INDEX(Techniques[Coverage],MATCH(Y8,Techniques[Name],0)),""),"") | AA8: Endpoint Denial of Service (T1499) | AB8: =IF(AA8<>"",IF(INDEX(Techniques[Coverage],MATCH(AA8,Techniques[Name],0))>0,INDEX(Techniques[Coverage],MATCH(AA8,Techniques[Name],0)),""),"")
A9: Search Open Technical Databases (T1596) | B9: =IF(A9<>"",IF(INDEX(Techniques[Coverage],MATCH(A9,Techniques[Name],0))>0,INDEX(Techniques[Coverage],MATCH(A9,Techniques[Name],0)),""),"") | C9: Stage Capabilities (T1608) | D9: =IF(C9<>"",IF(INDEX(Techniques[Coverage],MATCH(C9,Techniques[Name],0))>0,INDEX(Techniques[Coverage],MATCH(C9,Techniques[Name],0)),""),"") | E9: Supply Chain Compromise (T1195) | F9: =IF(E9<>"",IF(INDEX(Techniques[Coverage],MATCH(E9,Techniques[Name],0))>0,INDEX(Techniques[Coverage],MATCH(E9,Techniques[Name],0)),""),"") | G9: Scheduled Task/Job (T1053) | H9: =IF(G9<>"",IF(INDEX(Techniques[Coverage],MATCH(G9,Techniques[Name],0))>0,INDEX(Techniques[Coverage],MATCH(G9,Techniques[Name],0)),""),"") | I9: Create or Modify System Process (T1543) | J9: =IF(I9<>"",IF(INDEX(Techniques[Coverage],MATCH(I9,Techniques[Name],0))>0,INDEX(Techniques[Coverage],MATCH(I9,Techniques[Name],0)),""),"") | K9: Escape to Host (T1611) | L9: =IF(K9<>"",IF(INDEX(Techniques[Coverage],MATCH(K9,Techniques[Name],0))>0,INDEX(Techniques[Coverage],MATCH(K9,Techniques[Name],0)),""),"") | M9: Direct Volume Access (T1006) | N9: =IF(M9<>"",IF(INDEX(Techniques[Coverage],MATCH(M9,Techniques[Name],0))>0,INDEX(Techniques[Coverage],MATCH(M9,Techniques[Name],0)),""),"") | O9: Modify Authentication Process (T1556) | P9: =IF(O9<>"",IF(INDEX(Techniques[Coverage],MATCH(O9,Techniques[Name],0))>0,INDEX(Techniques[Coverage],MATCH(O9,Techniques[Name],0)),""),"") | Q9: Container and Resource Discovery (T1613) | R9: =IF(Q9<>"",IF(INDEX(Techniques[Coverage],MATCH(Q9,Techniques[Name],0))>0,INDEX(Techniques[Coverage],MATCH(Q9,Techniques[Name],0)),""),"") | S9: Taint Shared Content (T1080) | T9: =IF(S9<>"",IF(INDEX(Techniques[Coverage],MATCH(S9,Techniques[Name],0))>0,INDEX(Techniques[Coverage],MATCH(S9,Techniques[Name],0)),""),"") | U9: Data from Cloud Storage (T1530) | V9: =IF(U9<>"",IF(INDEX(Techniques[Coverage],MATCH(U9,Techniques[Name],0))>0,INDEX(Techniques[Coverage],MATCH(U9,Techniques[Name],0)),""),"") | W9: Fallback Channels (T1008) | X9: =IF(W9<>"",IF(INDEX(Techniques[Coverage],MATCH(W9,Techniques[Name],0))>0,INDEX(Techniques[Coverage],MATCH(W9,Techniques[Name],0)),""),"") | Y9: Scheduled Transfer (T1029) | Z9: =IF(Y9<>"",IF(INDEX(Techniques[Coverage],MATCH(Y9,Techniques[Name],0))>0,INDEX(Techniques[Coverage],MATCH(Y9,Techniques[Name],0)),""),"") | AA9: Financial Theft (T1657) | AB9: =IF(AA9<>"",IF(INDEX(Techniques[Coverage],MATCH(AA9,Techniques[Name],0))>0,INDEX(Techniques[Coverage],MATCH(AA9,Techniques[Name],0)),""),"")
A10: Search Open Websites/Domains (T1593) | B10: =IF(A10<>"",IF(INDEX(Techniques[Coverage],MATCH(A10,Techniques[Name],0))>0,INDEX(Techniques[Coverage],MATCH(A10,Techniques[Name],0)),""),"") | E10: Trusted Relationship (T1199) | F10: =IF(E10<>"",IF(INDEX(Techniques[Coverage],MATCH(E10,Techniques[Name],0))>0,INDEX(Techniques[Coverage],MATCH(E10,Techniques[Name],0)),""),"") | G10: Serverless Execution (T1648) | H10: =IF(G10<>"",IF(INDEX(Techniques[Coverage],MATCH(G10,Techniques[Name],0))>0,INDEX(Techniques[Coverage],MATCH(G10,Techniques[Name],0)),""),"") | I10: Event Triggered Execution (T1546) | J10: =IF(I10<>"",IF(INDEX(Techniques[Coverage],MATCH(I10,Techniques[Name],0))>0,INDEX(Techniques[Coverage],MATCH(I10,Techniques[Name],0)),""),"") | K10: Event Triggered Execution (T1546) | L10: =IF(K10<>"",IF(INDEX(Techniques[Coverage],MATCH(K10,Techniques[Name],0))>0,INDEX(Techniques[Coverage],MATCH(K10,Techniques[Name],0)),""),"") | M10: Domain or Tenant Policy Modification (T1484) | N10: =IF(M10<>"",IF(INDEX(Techniques[Coverage],MATCH(M10,Techniques[Name],0))>0,INDEX(Techniques[Coverage],MATCH(M10,Techniques[Name],0)),""),"") | O10: Multi-Factor Authentication Interception (T1111) | P10: =IF(O10<>"",IF(INDEX(Techniques[Coverage],MATCH(O10,Techniques[Name],0))>0,INDEX(Techniques[Coverage],MATCH(O10,Techniques[Name],0)),""),"") | Q10: Debugger Evasion (T1622) | R10: =IF(Q10<>"",IF(INDEX(Techniques[Coverage],MATCH(Q10,Techniques[Name],0))>0,INDEX(Techniques[Coverage],MATCH(Q10,Techniques[Name],0)),""),"") | S10: Use Alternate Authentication Material (T1550) | T10: =IF(S10<>"",IF(INDEX(Techniques[Coverage],MATCH(S10,Techniques[Name],0))>0,INDEX(Techniques[Coverage],MATCH(S10,Techniques[Name],0)),""),"") | U10: Data from Configuration Repository (T1602) | V10: =IF(U10<>"",IF(INDEX(Techniques[Coverage],MATCH(U10,Techniques[Name],0))>0,INDEX(Techniques[Coverage],MATCH(U10,Techniques[Name],0)),""),"") | W10: Hide Infrastructure (T1665) | X10: =IF(W10<>"",IF(INDEX(Techniques[Coverage],MATCH(W10,Techniques[Name],0))>0,INDEX(Techniques[Coverage],MATCH(W10,Techniques[Name],0)),""),"") | Y10: Transfer Data to Cloud Account (T1537) | Z10: =IF(Y10<>"",IF(INDEX(Techniques[Coverage],MATCH(Y10,Techniques[Name],0))>0,INDEX(Techniques[Coverage],MATCH(Y10,Techniques[Name],0)),""),"") | AA10: Firmware Corruption (T1495) | AB10: =IF(AA10<>"",IF(INDEX(Techniques[Coverage],MATCH(AA10,Techniques[Name],0))>0,INDEX(Techniques[Coverage],MATCH(AA10,Techniques[Name],0)),""),"")
A11: Search Victim-Owned Websites (T1594) | B11: =IF(A11<>"",IF(INDEX(Techniques[Coverage],MATCH(A11,Techniques[Name],0))>0,INDEX(Techniques[Coverage],MATCH(A11,Techniques[Name],0)),""),"") | E11: Valid Accounts (T1078) | F11: =IF(E11<>"",IF(INDEX(Techniques[Coverage],MATCH(E11,Techniques[Name],0))>0,INDEX(Techniques[Coverage],MATCH(E11,Techniques[Name],0)),""),"") | G11: Shared Modules (T1129) | H11: =IF(G11<>"",IF(INDEX(Techniques[Coverage],MATCH(G11,Techniques[Name],0))>0,INDEX(Techniques[Coverage],MATCH(G11,Techniques[Name],0)),""),"") | I11: External Remote Services (T1133) | J11: =IF(I11<>"",IF(INDEX(Techniques[Coverage],MATCH(I11,Techniques[Name],0))>0,INDEX(Techniques[Coverage],MATCH(I11,Techniques[Name],0)),""),"") | K11: Exploitation for Privilege Escalation (T1068) | L11: =IF(K11<>"",IF(INDEX(Techniques[Coverage],MATCH(K11,Techniques[Name],0))>0,INDEX(Techniques[Coverage],MATCH(K11,Techniques[Name],0)),""),"") | M11: Execution Guardrails (T1480) | N11: =IF(M11<>"",IF(INDEX(Techniques[Coverage],MATCH(M11,Techniques[Name],0))>0,INDEX(Techniques[Coverage],MATCH(M11,Techniques[Name],0)),""),"") | O11: Multi-Factor Authentication Request Generation (T1621) | P11: =IF(O11<>"",IF(INDEX(Techniques[Coverage],MATCH(O11,Techniques[Name],0))>0,INDEX(Techniques[Coverage],MATCH(O11,Techniques[Name],0)),""),"") | Q11: Device Driver Discovery (T1652) | R11: =IF(Q11<>"",IF(INDEX(Techniques[Coverage],MATCH(Q11,Techniques[Name],0))>0,INDEX(Techniques[Coverage],MATCH(Q11,Techniques[Name],0)),""),"") | U11: Data from Information Repositories (T1213) | V11: =IF(U11<>"",IF(INDEX(Techniques[Coverage],MATCH(U11,Techniques[Name],0))>0,INDEX(Techniques[Coverage],MATCH(U11,Techniques[Name],0)),""),"") | W11: Ingress Tool Transfer (T1105) | X11: =IF(W11<>"",IF(INDEX(Techniques[Coverage],MATCH(W11,Techniques[Name],0))>0,INDEX(Techniques[Coverage],MATCH(W11,Techniques[Name],0)),""),"") | AA11: Inhibit System Recovery (T1490) | AB11: =IF(AA11<>"",IF(INDEX(Techniques[Coverage],MATCH(AA11,Techniques[Name],0))>0,INDEX(Techniques[Coverage],MATCH(AA11,Techniques[Name],0)),""),"")
G12: Software Deployment Tools (T1072) | H12: =IF(G12<>"",IF(INDEX(Techniques[Coverage],MATCH(G12,Techniques[Name],0))>0,INDEX(Techniques[Coverage],MATCH(G12,Techniques[Name],0)),""),"") | I12: Hijack Execution Flow (T1574) | J12: =IF(I12<>"",IF(INDEX(Techniques[Coverage],MATCH(I12,Techniques[Name],0))>0,INDEX(Techniques[Coverage],MATCH(I12,Techniques[Name],0)),""),"") | K12: Hijack Execution Flow (T1574) | L12: =IF(K12<>"",IF(INDEX(Techniques[Coverage],MATCH(K12,Techniques[Name],0))>0,INDEX(Techniques[Coverage],MATCH(K12,Techniques[Name],0)),""),"") | M12: Exploitation for Defense Evasion (T1211) | N12: =IF(M12<>"",IF(INDEX(Techniques[Coverage],MATCH(M12,Techniques[Name],0))>0,INDEX(Techniques[Coverage],MATCH(M12,Techniques[Name],0)),""),"") | O12: Network Sniffing (T1040) | P12: =IF(O12<>"",IF(INDEX(Techniques[Coverage],MATCH(O12,Techniques[Name],0))>0,INDEX(Techniques[Coverage],MATCH(O12,Techniques[Name],0)),""),"") | Q12: Domain Trust Discovery (T1482) | R12: =IF(Q12<>"",IF(INDEX(Techniques[Coverage],MATCH(Q12,Techniques[Name],0))>0,INDEX(Techniques[Coverage],MATCH(Q12,Techniques[Name],0)),""),"") | U12: Data from Local System (T1005) | V12: =IF(U12<>"",IF(INDEX(Techniques[Coverage],MATCH(U12,Techniques[Name],0))>0,INDEX(Techniques[Coverage],MATCH(U12,Techniques[Name],0)),""),"") | W12: Multi-Stage Channels (T1104) | X12: =IF(W12<>"",IF(INDEX(Techniques[Coverage],MATCH(W12,Techniques[Name],0))>0,INDEX(Techniques[Coverage],MATCH(W12,Techniques[Name],0)),""),"") | AA12: Network Denial of Service (T1498) | AB12: =IF(AA12<>"",IF(INDEX(Techniques[Coverage],MATCH(AA12,Techniques[Name],0))>0,INDEX(Techniques[Coverage],MATCH(AA12,Techniques[Name],0)),""),"")
G13: System Services (T1569) | H13: =IF(G13<>"",IF(INDEX(Techniques[Coverage],MATCH(G13,Techniques[Name],0))>0,INDEX(Techniques[Coverage],MATCH(G13,Techniques[Name],0)),""),"") | I13: Implant Internal Image (T1525) | J13: =IF(I13<>"",IF(INDEX(Techniques[Coverage],MATCH(I13,Techniques[Name],0))>0,INDEX(Techniques[Coverage],MATCH(I13,Techniques[Name],0)),""),"") | K13: Process Injection (T1055) | L13: =IF(K13<>"",IF(INDEX(Techniques[Coverage],MATCH(K13,Techniques[Name],0))>0,INDEX(Techniques[Coverage],MATCH(K13,Techniques[Name],0)),""),"") | M13: File and Directory Permissions Modification (T1222) | N13: =IF(M13<>"",IF(INDEX(Techniques[Coverage],MATCH(M13,Techniques[Name],0))>0,INDEX(Techniques[Coverage],MATCH(M13,Techniques[Name],0)),""),"") | O13: OS Credential Dumping (T1003) | P13: =IF(O13<>"",IF(INDEX(Techniques[Coverage],MATCH(O13,Techniques[Name],0))>0,INDEX(Techniques[Coverage],MATCH(O13,Techniques[Name],0)),""),"") -> 0.25 | Q13: File and Directory Discovery (T1083) | R13: =IF(Q13<>"",IF(INDEX(Techniques[Coverage],MATCH(Q13,Techniques[Name],0))>0,INDEX(Techniques[Coverage],MATCH(Q13,Techniques[Name],0)),""),"") | U13: Data from Network Shared Drive (T1039) | V13: =IF(U13<>"",IF(INDEX(Techniques[Coverage],MATCH(U13,Techniques[Name],0))>0,INDEX(Techniques[Coverage],MATCH(U13,Techniques[Name],0)),""),"") | W13: Non-Application Layer Protocol (T1095) | X13: =IF(W13<>"",IF(INDEX(Techniques[Coverage],MATCH(W13,Techniques[Name],0))>0,INDEX(Techniques[Coverage],MATCH(W13,Techniques[Name],0)),""),"") | AA13: Resource Hijacking (T1496) | AB13: =IF(AA13<>"",IF(INDEX(Techniques[Coverage],MATCH(AA13,Techniques[Name],0))>0,INDEX(Techniques[Coverage],MATCH(AA13,Techniques[Name],0)),""),"")
G14: User Execution (T1204) | H14: =IF(G14<>"",IF(INDEX(Techniques[Coverage],MATCH(G14,Techniques[Name],0))>0,INDEX(Techniques[Coverage],MATCH(G14,Techniques[Name],0)),""),"") | I14: Modify Authentication Process (T1556) | J14: =IF(I14<>"",IF(INDEX(Techniques[Coverage],MATCH(I14,Techniques[Name],0))>0,INDEX(Techniques[Coverage],MATCH(I14,Techniques[Name],0)),""),"") | K14: Scheduled Task/Job (T1053) | L14: =IF(K14<>"",IF(INDEX(Techniques[Coverage],MATCH(K14,Techniques[Name],0))>0,INDEX(Techniques[Coverage],MATCH(K14,Techniques[Name],0)),""),"") | M14: Hide Artifacts (T1564) | N14: =IF(M14<>"",IF(INDEX(Techniques[Coverage],MATCH(M14,Techniques[Name],0))>0,INDEX(Techniques[Coverage],MATCH(M14,Techniques[Name],0)),""),"") | O14: Steal Application Access Token (T1528) | P14: =IF(O14<>"",IF(INDEX(Techniques[Coverage],MATCH(O14,Techniques[Name],0))>0,INDEX(Techniques[Coverage],MATCH(O14,Techniques[Name],0)),""),"") | Q14: Group Policy Discovery (T1615) | R14: =IF(Q14<>"",IF(INDEX(Techniques[Coverage],MATCH(Q14,Techniques[Name],0))>0,INDEX(Techniques[Coverage],MATCH(Q14,Techniques[Name],0)),""),"") | U14: Data from Removable Media (T1025) | V14: =IF(U14<>"",IF(INDEX(Techniques[Coverage],MATCH(U14,Techniques[Name],0))>0,INDEX(Techniques[Coverage],MATCH(U14,Techniques[Name],0)),""),"") | W14: Non-Standard Port (T1571) | X14: =IF(W14<>"",IF(INDEX(Techniques[Coverage],MATCH(W14,Techniques[Name],0))>0,INDEX(Techniques[Coverage],MATCH(W14,Techniques[Name],0)),""),"") | AA14: Service Stop (T1489) | AB14: =IF(AA14<>"",IF(INDEX(Techniques[Coverage],MATCH(AA14,Techniques[Name],0))>0,INDEX(Techniques[Coverage],MATCH(AA14,Techniques[Name],0)),""),"")
G15: Windows Management Instrumentation (T1047) | H15: =IF(G15<>"",IF(INDEX(Techniques[Coverage],MATCH(G15,Techniques[Name],0))>0,INDEX(Techniques[Coverage],MATCH(G15,Techniques[Name],0)),""),"") | I15: Office Application Startup (T1137) | J15: =IF(I15<>"",IF(INDEX(Techniques[Coverage],MATCH(I15,Techniques[Name],0))>0,INDEX(Techniques[Coverage],MATCH(I15,Techniques[Name],0)),""),"") | K15: Valid Accounts (T1078) | L15: =IF(K15<>"",IF(INDEX(Techniques[Coverage],MATCH(K15,Techniques[Name],0))>0,INDEX(Techniques[Coverage],MATCH(K15,Techniques[Name],0)),""),"") | M15: Hijack Execution Flow (T1574) | N15: =IF(M15<>"",IF(INDEX(Techniques[Coverage],MATCH(M15,Techniques[Name],0))>0,INDEX(Techniques[Coverage],MATCH(M15,Techniques[Name],0)),""),"") | O15: Steal Web Session Cookie (T1539) | P15: =IF(O15<>"",IF(INDEX(Techniques[Coverage],MATCH(O15,Techniques[Name],0))>0,INDEX(Techniques[Coverage],MATCH(O15,Techniques[Name],0)),""),"") | Q15: Log Enumeration (T1654) | R15: =IF(Q15<>"",IF(INDEX(Techniques[Coverage],MATCH(Q15,Techniques[Name],0))>0,INDEX(Techniques[Coverage],MATCH(Q15,Techniques[Name],0)),""),"") | U15: Email Collection (T1114) | V15: =IF(U15<>"",IF(INDEX(Techniques[Coverage],MATCH(U15,Techniques[Name],0))>0,INDEX(Techniques[Coverage],MATCH(U15,Techniques[Name],0)),""),"") | W15: Protocol Tunneling (T1572) | X15: =IF(W15<>"",IF(INDEX(Techniques[Coverage],MATCH(W15,Techniques[Name],0))>0,INDEX(Techniques[Coverage],MATCH(W15,Techniques[Name],0)),""),"") | AA15: System Shutdown/Reboot (T1529) | AB15: =IF(AA15<>"",IF(INDEX(Techniques[Coverage],MATCH(AA15,Techniques[Name],0))>0,INDEX(Techniques[Coverage],MATCH(AA15,Techniques[Name],0)),""),"")
I16: Power Settings (T1653) | J16: =IF(I16<>"",IF(INDEX(Techniques[Coverage],MATCH(I16,Techniques[Name],0))>0,INDEX(Techniques[Coverage],MATCH(I16,Techniques[Name],0)),""),"") | M16: Impair Defenses (T1562) | N16: =IF(M16<>"",IF(INDEX(Techniques[Coverage],MATCH(M16,Techniques[Name],0))>0,INDEX(Techniques[Coverage],MATCH(M16,Techniques[Name],0)),""),"") | O16: Steal or Forge Authentication Certificates (T1649) | P16: =IF(O16<>"",IF(INDEX(Techniques[Coverage],MATCH(O16,Techniques[Name],0))>0,INDEX(Techniques[Coverage],MATCH(O16,Techniques[Name],0)),""),"") | Q16: Network Service Discovery (T1046) | R16: =IF(Q16<>"",IF(INDEX(Techniques[Coverage],MATCH(Q16,Techniques[Name],0))>0,INDEX(Techniques[Coverage],MATCH(Q16,Techniques[Name],0)),""),"") | U16: Input Capture (T1056) | V16: =IF(U16<>"",IF(INDEX(Techniques[Coverage],MATCH(U16,Techniques[Name],0))>0,INDEX(Techniques[Coverage],MATCH(U16,Techniques[Name],0)),""),"") | W16: Proxy (T1090) | X16: =IF(W16<>"",IF(INDEX(Techniques[Coverage],MATCH(W16,Techniques[Name],0))>0,INDEX(Techniques[Coverage],MATCH(W16,Techniques[Name],0)),""),"")
I17: Pre-OS Boot (T1542) | J17: =IF(I17<>"",IF(INDEX(Techniques[Coverage],MATCH(I17,Techniques[Name],0))>0,INDEX(Techniques[Coverage],MATCH(I17,Techniques[Name],0)),""),"") | M17: Impersonation (T1656) | N17: =IF(M17<>"",IF(INDEX(Techniques[Coverage],MATCH(M17,Techniques[Name],0))>0,INDEX(Techniques[Coverage],MATCH(M17,Techniques[Name],0)),""),"") | O17: Steal or Forge Kerberos Tickets (T1558) | P17: =IF(O17<>"",IF(INDEX(Techniques[Coverage],MATCH(O17,Techniques[Name],0))>0,INDEX(Techniques[Coverage],MATCH(O17,Techniques[Name],0)),""),"") | Q17: Network Share Discovery (T1135) | R17: =IF(Q17<>"",IF(INDEX(Techniques[Coverage],MATCH(Q17,Techniques[Name],0))>0,INDEX(Techniques[Coverage],MATCH(Q17,Techniques[Name],0)),""),"") | U17: Screen Capture (T1113) | V17: =IF(U17<>"",IF(INDEX(Techniques[Coverage],MATCH(U17,Techniques[Name],0))>0,INDEX(Techniques[Coverage],MATCH(U17,Techniques[Name],0)),""),"") | W17: Remote Access Software (T1219) | X17: =IF(W17<>"",IF(INDEX(Techniques[Coverage],MATCH(W17,Techniques[Name],0))>0,INDEX(Techniques[Coverage],MATCH(W17,Techniques[Name],0)),""),"")
I18: Scheduled Task/Job (T1053) | J18: =IF(I18<>"",IF(INDEX(Techniques[Coverage],MATCH(I18,Techniques[Name],0))>0,INDEX(Techniques[Coverage],MATCH(I18,Techniques[Name],0)),""),"") | M18: Indicator Removal (T1070) | N18: =IF(M18<>"",IF(INDEX(Techniques[Coverage],MATCH(M18,Techniques[Name],0))>0,INDEX(Techniques[Coverage],MATCH(M18,Techniques[Name],0)),""),"") | O18: Unsecured Credentials (T1552) | P18: =IF(O18<>"",IF(INDEX(Techniques[Coverage],MATCH(O18,Techniques[Name],0))>0,INDEX(Techniques[Coverage],MATCH(O18,Techniques[Name],0)),""),"") | Q18: Network Sniffing (T1040) | R18: =IF(Q18<>"",IF(INDEX(Techniques[Coverage],MATCH(Q18,Techniques[Name],0))>0,INDEX(Techniques[Coverage],MATCH(Q18,Techniques[Name],0)),""),"") | U18: Video Capture (T1125) | V18: =IF(U18<>"",IF(INDEX(Techniques[Coverage],MATCH(U18,Techniques[Name],0))>0,INDEX(Techniques[Coverage],MATCH(U18,Techniques[Name],0)),""),"") | W18: Traffic Signaling (T1205) | X18: =IF(W18<>"",IF(INDEX(Techniques[Coverage],MATCH(W18,Techniques[Name],0))>0,INDEX(Techniques[Coverage],MATCH(W18,Techniques[Name],0)),""),"")
I19: Server Software Component (T1505) | J19: =IF(I19<>"",IF(INDEX(Techniques[Coverage],MATCH(I19,Techniques[Name],0))>0,INDEX(Techniques[Coverage],MATCH(I19,Techniques[Name],0)),""),"") | M19: Indirect Command Execution (T1202) | N19: =IF(M19<>"",IF(INDEX(Techniques[Coverage],MATCH(M19,Techniques[Name],0))>0,INDEX(Techniques[Coverage],MATCH(M19,Techniques[Name],0)),""),"") | Q19: Password Policy Discovery (T1201) | R19: =IF(Q19<>"",IF(INDEX(Techniques[Coverage],MATCH(Q19,Techniques[Name],0))>0,INDEX(Techniques[Coverage],MATCH(Q19,Techniques[Name],0)),""),"") | W19: Web Service (T1102) | X19: =IF(W19<>"",IF(INDEX(Techniques[Coverage],MATCH(W19,Techniques[Name],0))>0,INDEX(Techniques[Coverage],MATCH(W19,Techniques[Name],0)),""),"")
I20: Traffic Signaling (T1205) | J20: =IF(I20<>"",IF(INDEX(Techniques[Coverage],MATCH(I20,Techniques[Name],0))>0,INDEX(Techniques[Coverage],MATCH(I20,Techniques[Name],0)),""),"") | M20: Masquerading (T1036) | N20: =IF(M20<>"",IF(INDEX(Techniques[Coverage],MATCH(M20,Techniques[Name],0))>0,INDEX(Techniques[Coverage],MATCH(M20,Techniques[Name],0)),""),"") -> 0.1 | Q20: Peripheral Device Discovery (T1120) | R20: =IF(Q20<>"",IF(INDEX(Techniques[Coverage],MATCH(Q20,Techniques[Name],0))>0,INDEX(Techniques[Coverage],MATCH(Q20,Techniques[Name],0)),""),"")
I21: Valid Accounts (T1078) | J21: =IF(I21<>"",IF(INDEX(Techniques[Coverage],MATCH(I21,Techniques[Name],0))>0,INDEX(Techniques[Coverage],MATCH(I21,Techniques[Name],0)),""),"") | M21: Modify Authentication Process (T1556) | N21: =IF(M21<>"",IF(INDEX(Techniques[Coverage],MATCH(M21,Techniques[Name],0))>0,INDEX(Techniques[Coverage],MATCH(M21,Techniques[Name],0)),""),"") | Q21: Permission Groups Discovery (T1069) | R21: =IF(Q21<>"",IF(INDEX(Techniques[Coverage],MATCH(Q21,Techniques[Name],0))>0,INDEX(Techniques[Coverage],MATCH(Q21,Techniques[Name],0)),""),"")
M22: Modify Cloud Compute Infrastructure (T1578) | N22: =IF(M22<>"",IF(INDEX(Techniques[Coverage],MATCH(M22,Techniques[Name],0))>0,INDEX(Techniques[Coverage],MATCH(M22,Techniques[Name],0)),""),"") | Q22: Process Discovery (T1057) | R22: =IF(Q22<>"",IF(INDEX(Techniques[Coverage],MATCH(Q22,Techniques[Name],0))>0,INDEX(Techniques[Coverage],MATCH(Q22,Techniques[Name],0)),""),"")
M23: Modify Cloud Resource Hierarchy (T1666) | N23: =IF(M23<>"",IF(INDEX(Techniques[Coverage],MATCH(M23,Techniques[Name],0))>0,INDEX(Techniques[Coverage],MATCH(M23,Techniques[Name],0)),""),"") | Q23: Query Registry (T1012) | R23: =IF(Q23<>"",IF(INDEX(Techniques[Coverage],MATCH(Q23,Techniques[Name],0))>0,INDEX(Techniques[Coverage],MATCH(Q23,Techniques[Name],0)),""),"")
M24: Modify Registry (T1112) | N24: =IF(M24<>"",IF(INDEX(Techniques[Coverage],MATCH(M24,Techniques[Name],0))>0,INDEX(Techniques[Coverage],MATCH(M24,Techniques[Name],0)),""),"") | Q24: Remote System Discovery (T1018) | R24: =IF(Q24<>"",IF(INDEX(Techniques[Coverage],MATCH(Q24,Techniques[Name],0))>0,INDEX(Techniques[Coverage],MATCH(Q24,Techniques[Name],0)),""),"")
M25: Modify System Image (T1601) | N25: =IF(M25<>"",IF(INDEX(Techniques[Coverage],MATCH(M25,Techniques[Name],0))>0,INDEX(Techniques[Coverage],MATCH(M25,Techniques[Name],0)),""),"") | Q25: Software Discovery (T1518) | R25: =IF(Q25<>"",IF(INDEX(Techniques[Coverage],MATCH(Q25,Techniques[Name],0))>0,INDEX(Techniques[Coverage],MATCH(Q25,Techniques[Name],0)),""),"")
M26: Network Boundary Bridging (T1599) | N26: =IF(M26<>"",IF(INDEX(Techniques[Coverage],MATCH(M26,Techniques[Name],0))>0,INDEX(Techniques[Coverage],MATCH(M26,Techniques[Name],0)),""),"") | Q26: System Information Discovery (T1082) | R26: =IF(Q26<>"",IF(INDEX(Techniques[Coverage],MATCH(Q26,Techniques[Name],0))>0,INDEX(Techniques[Coverage],MATCH(Q26,Techniques[Name],0)),""),"")
M27: Obfuscated Files or Information (T1027) | N27: =IF(M27<>"",IF(INDEX(Techniques[Coverage],MATCH(M27,Techniques[Name],0))>0,INDEX(Techniques[Coverage],MATCH(M27,Techniques[Name],0)),""),"") -> 0.071428571 | Q27: System Location Discovery (T1614) | R27: =IF(Q27<>"",IF(INDEX(Techniques[Coverage],MATCH(Q27,Techniques[Name],0))>0,INDEX(Techniques[Coverage],MATCH(Q27,Techniques[Name],0)),""),"")
M28: Plist File Modification (T1647) | N28: =IF(M28<>"",IF(INDEX(Techniques[Coverage],MATCH(M28,Techniques[Name],0))>0,INDEX(Techniques[Coverage],MATCH(M28,Techniques[Name],0)),""),"") | Q28: System Network Configuration Discovery (T1016) | R28: =IF(Q28<>"",IF(INDEX(Techniques[Coverage],MATCH(Q28,Techniques[Name],0))>0,INDEX(Techniques[Coverage],MATCH(Q28,Techniques[Name],0)),""),"") -> 0.5
M29: Pre-OS Boot (T1542) | N29: =IF(M29<>"",IF(INDEX(Techniques[Coverage],MATCH(M29,Techniques[Name],0))>0,INDEX(Techniques[Coverage],MATCH(M29,Techniques[Name],0)),""),"") | Q29: System Network Connections Discovery (T1049) | R29: =IF(Q29<>"",IF(INDEX(Techniques[Coverage],MATCH(Q29,Techniques[Name],0))>0,INDEX(Techniques[Coverage],MATCH(Q29,Techniques[Name],0)),""),"")
M30: Process Injection (T1055) | N30: =IF(M30<>"",IF(INDEX(Techniques[Coverage],MATCH(M30,Techniques[Name],0))>0,INDEX(Techniques[Coverage],MATCH(M30,Techniques[Name],0)),""),"") | Q30: System Owner/User Discovery (T1033) | R30: =IF(Q30<>"",IF(INDEX(Techniques[Coverage],MATCH(Q30,Techniques[Name],0))>0,INDEX(Techniques[Coverage],MATCH(Q30,Techniques[Name],0)),""),"")
M31: Reflective Code Loading (T1620) | N31: =IF(M31<>"",IF(INDEX(Techniques[Coverage],MATCH(M31,Techniques[Name],0))>0,INDEX(Techniques[Coverage],MATCH(M31,Techniques[Name],0)),""),"") | Q31: System Service Discovery (T1007) | R31: =IF(Q31<>"",IF(INDEX(Techniques[Coverage],MATCH(Q31,Techniques[Name],0))>0,INDEX(Techniques[Coverage],MATCH(Q31,Techniques[Name],0)),""),"")
M32: Rogue Domain Controller (T1207) | N32: =IF(M32<>"",IF(INDEX(Techniques[Coverage],MATCH(M32,Techniques[Name],0))>0,INDEX(Techniques[Coverage],MATCH(M32,Techniques[Name],0)),""),"") | Q32: System Time Discovery (T1124) | R32: =IF(Q32<>"",IF(INDEX(Techniques[Coverage],MATCH(Q32,Techniques[Name],0))>0,INDEX(Techniques[Coverage],MATCH(Q32,Techniques[Name],0)),""),"")
M33: Rootkit (T1014) | N33: =IF(M33<>"",IF(INDEX(Techniques[Coverage],MATCH(M33,Techniques[Name],0))>0,INDEX(Techniques[Coverage],MATCH(M33,Techniques[Name],0)),""),"") -> 1 | Q33: Virtualization/Sandbox Evasion (T1497) | R33: =IF(Q33<>"",IF(INDEX(Techniques[Coverage],MATCH(Q33,Techniques[Name],0))>0,INDEX(Techniques[Coverage],MATCH(Q33,Techniques[Name],0)),""),"")
M34: Subvert Trust Controls (T1553) | N34: =IF(M34<>"",IF(INDEX(Techniques[Coverage],MATCH(M34,Techniques[Name],0))>0,INDEX(Techniques[Coverage],MATCH(M34,Techniques[Name],0)),""),"")
M35: System Binary Proxy Execution (T1218) | N35: =IF(M35<>"",IF(INDEX(Techniques[Coverage],MATCH(M35,Techniques[Name],0))>0,INDEX(Techniques[Coverage],MATCH(M35,Techniques[Name],0)),""),"")
M36: System Script Proxy Execution (T1216) | N36: =IF(M36<>"",IF(INDEX(Techniques[Coverage],MATCH(M36,Techniques[Name],0))>0,INDEX(Techniques[Coverage],MATCH(M36,Techniques[Name],0)),""),"")
M37: Template Injection (T1221) | N37: =IF(M37<>"",IF(INDEX(Techniques[Coverage],MATCH(M37,Techniques[Name],0))>0,INDEX(Techniques[Coverage],MATCH(M37,Techniques[Name],0)),""),"")
M38: Traffic Signaling (T1205) | N38: =IF(M38<>"",IF(INDEX(Techniques[Coverage],MATCH(M38,Techniques[Name],0))>0,INDEX(Techniques[Coverage],MATCH(M38,Techniques[Name],0)),""),"")
M39: Trusted Developer Utilities Proxy Execution (T1127) | N39: =IF(M39<>"",IF(INDEX(Techniques[Coverage],MATCH(M39,Techniques[Name],0))>0,INDEX(Techniques[Coverage],MATCH(M39,Techniques[Name],0)),""),"")
M40: Unused/Unsupported Cloud Regions (T1535) | N40: =IF(M40<>"",IF(INDEX(Techniques[Coverage],MATCH(M40,Techniques[Name],0))>0,INDEX(Techniques[Coverage],MATCH(M40,Techniques[Name],0)),""),"")
M41: Use Alternate Authentication Material (T1550) | N41: =IF(M41<>"",IF(INDEX(Techniques[Coverage],MATCH(M41,Techniques[Name],0))>0,INDEX(Techniques[Coverage],MATCH(M41,Techniques[Name],0)),""),"")
M42: Valid Accounts (T1078) | N42: =IF(M42<>"",IF(INDEX(Techniques[Coverage],MATCH(M42,Techniques[Name],0))>0,INDEX(Techniques[Coverage],MATCH(M42,Techniques[Name],0)),""),"")
M43: Virtualization/Sandbox Evasion (T1497) | N43: =IF(M43<>"",IF(INDEX(Techniques[Coverage],MATCH(M43,Techniques[Name],0))>0,INDEX(Techniques[Coverage],MATCH(M43,Techniques[Name],0)),""),"")
M44: Weaken Encryption (T1600) | N44: =IF(M44<>"",IF(INDEX(Techniques[Coverage],MATCH(M44,Techniques[Name],0))>0,INDEX(Techniques[Coverage],MATCH(M44,Techniques[Name],0)),""),"")
M45: XSL Script Processing (T1220)

Sheet Detection Rules
A1: Source | B1: Use Case | C1: Rule Description | D1: Is Active | E1: Attack1 | F1: Attack2 | G1: Attack3 | H1: Attack4 | I1: Attack5 | J1: Attack6 | K1: Attack7 | L1: Attack8 | M1: Attack9 | N1: Attack10
A2: IBM Qradar | B2: Detection Rule 1 | D2: yes | E2: Masquerading (T1036) | F2: Internet Connection Discovery (T1016.001) | G2: NTDS (T1003.003) | H2: Active Scanning (T1595)
A3: Microsoft Sentinel | B3: Detection Rule 2 | D3: yes | E3: Rootkit (T1014) | F3: Traffic Duplication (T1020.001) | G3: AppleScript (T1059.002)
A4: Microsoft Defender | B4: Detection Rule 3 | D4: yes | E4: OS Credential Dumping (T1003) | F4: Rootkit (T1014)
A5: Crowdstrike EDR | B5: EDR Rule 1 | D5: yes | E5: HTML Smuggling (T1027.006) | F5: Application Window Discovery (T1010)

Sheet Mitre Techniques
A1: Technique | B1: ID | C1: Name | D1: Tactics | E1: Data Sources | F1: Data Sources No. | G1: Data Sources Available | H1: No. of Sub Techniques | I1: Detection Rules for Technique | J1: Detection Rules for SubTech | K1: Min. Detection Rules | L1: Detection Rules Modifier | M1: Expected Detection Rules | N1: Detection Rules | O1: Coverage | P1: Technique Status | Q1: Notes | R1: ID Checks | S1: Error Checks | T1: platforms | U1: description | V1: detection | W1: is sub-technique | X1: sub-technique of
A2: T1001 | B2: T1001 | C2: Data Obfuscation (T1001) | D2: Command and Control | E2: Network Traffic: Network Traffic Content | F2: =LEN(E2)-LEN(SUBSTITUTE(E2,",",""))+1 -> 1 | G2: {=SUM(IF(ISERROR(FIND(Sources[Data Source],Techniques[[#This Row],[Data Sources]])),0,1)*IF(Sources[Available]="yes",1,0))} -> 1 | H2: {=IF(Techniques[[#This Row],[Technique]]=Techniques[[#This Row],[ID]],SUM(IF(Techniques[[#This Row],[ID]]=Techniques[Technique],1,0))-1,"")} -> 3 | I2: {=IF(SUM(IF($C2=Detections[],IF(Detections[Is Active]="yes",1,0),0))>0,SUM(IF($C2=Detections[],IF(Detections[Is Active]="yes",1,0),0)),"")} | J2: {=IF(IF(ISNUMBER(Techniques[[#This Row],[No. of Sub Techniques]]), Techniques[[#This Row],[No. of Sub Techniques]]>0,FALSE),SUM(IF(Techniques[[#This Row],[Technique]]=Techniques[Technique],Techniques[Detection Rules for Technique],0))-IF(ISNUMBER(Techniques[[#This Row],[Detection Rules for Technique]]),Techniques[[#This Row],[Detection Rules for Technique]],0),"")} -> 0 | K2: =IF(AND(ISNUMBER(Techniques[[#This Row],[No. of Sub Techniques]]),Techniques[[#This Row],[No. of Sub Techniques]]>1),Techniques[No. of Sub Techniques],1) -> 3 | M2: {=Techniques[[#This Row],[Min. Detection Rules]]+IF(IF(ISNUMBER(Techniques[[#This Row],[No. of Sub Techniques]]),Techniques[[#This Row],[No. of Sub Techniques]]>0,FALSE),SUM(IF(Techniques[[#This Row],[Technique]]=Techniques[Technique],Techniques[Detection Rules Modifier],0)),Techniques[[#This Row],[Detection Rules Modifier]])} -> 3 | N2: =IF(ISNUMBER(Techniques[[#This Row],[Detection Rules for Technique]]),Techniques[[#This Row],[Detection Rules for Technique]],0)+IF(ISNUMBER(Techniques[[#This Row],[Detection Rules for SubTech]]),Techniques[[#This Row],[Detection Rules for SubTech]],0) -> 0 | O2: =IF(Techniques[[#This Row],[Detection Rules]]>=Techniques[[#This Row],[Expected Detection Rules]],1,Techniques[[#This Row],[Detection Rules]]/Techniques[[#This Row],[Expected Detection Rules]]) -> 0 | P2: =IF(Techniques[[#This Row],[Expected Detection Rules]]<=0,"disabled",IF(Techniques[[#This Row],[Data Sources Available]]>0, IF(Techniques[[#This Row],[Detection Rules]]>0,"detect","no detect"),IF(Techniques[[#This Row],[Detection Rules]]>0,"inconsistent","no sources"))) -> no detect | S2: =IF(Techniques[[#This Row],[Expected Detection Rules]]<0,"expected detection rules negative!",IF(Techniques[[#This Row],[Detection Rules]]>Techniques[[#This Row],[Expected Detection Rules]],"more detection rules than expected!",IF(AND(IF(ISNUMBER(Techniques[[#This Row],[Detection Rules for Technique]]),Techniques[[#This Row],[Detection Rules for Technique]]>0,FALSE),IF(ISNUMBER(Techniques[[#This Row],[No. of Sub Techniques]]),Techniques[[#This Row],[No. of Sub Techniques]]>0,FALSE)),IF(Techniques[[#This Row],[Detection Rules for Technique]] > IF(ISNUMBER(Techniques[[#This Row],[Detection Rules Modifier]]),Techniques[[#This Row],[Detection Rules Modifier]],0), "modifier should be increased for the technique", ""),""))) | T2: Linux, Windows, macOS | U2: Adversaries may obfuscate command and control traffic to make it more difficult to detect.(Citation: Bitdefender FunnyDream Campaign November 2020) Command and control (C2) communications are hidden (but not necessarily encrypted) in an attempt to make the content more difficult to discover or decipher and to make the communication less conspicuous and hide commands from being seen. This encompasses many methods, such as adding junk data to protocol traffic, using steganography, or impersonating legitimate protocols. | V2: Analyze network data for uncommon data flows (e.g., a client sending significantly more data than it receives from a server). Processes utilizing the network that do not normally have network communication or have never been seen before are suspicious. Analyze packet contents to detect communications that do not follow the expected protocol behavior for the port that is being used. (Citation: University of Birmingham C2) | W2: FALSE
A3: T1001 | B3: T1001.001 | C3: Junk Data (T1001.001) | D3: Command and Control | E3: Network Traffic: Network Traffic Content | F3: =LEN(E3)-LEN(SUBSTITUTE(E3,",",""))+1 -> 1 | G3: {=SUM(IF(ISERROR(FIND(Sources[Data Source],Techniques[[#This Row],[Data Sources]])),0,1)*IF(Sources[Available]="yes",1,0))} -> 1 | H3: {=IF(Techniques[[#This Row],[Technique]]=Techniques[[#This Row],[ID]],SUM(IF(Techniques[[#This Row],[ID]]=Techniques[Technique],1,0))-1,"")} | I3: {=IF(SUM(IF($C3=Detections[],IF(Detections[Is Active]="yes",1,0),0))>0,SUM(IF($C3=Detections[],IF(Detections[Is Active]="yes",1,0),0)),"")} | J3: {=IF(IF(ISNUMBER(Techniques[[#This Row],[No. of Sub Techniques]]), Techniques[[#This Row],[No. of Sub Techniques]]>0,FALSE),SUM(IF(Techniques[[#This Row],[Technique]]=Techniques[Technique],Techniques[Detection Rules for Technique],0))-IF(ISNUMBER(Techniques[[#This Row],[Detection Rules for Technique]]),Techniques[[#This Row],[Detection Rules for Technique]],0),"")} | K3: =IF(AND(ISNUMBER(Techniques[[#This Row],[No. of Sub Techniques]]),Techniques[[#This Row],[No. of Sub Techniques]]>1),Techniques[No. of Sub Techniques],1) -> 1 | M3: {=Techniques[[#This Row],[Min. Detection Rules]]+IF(IF(ISNUMBER(Techniques[[#This Row],[No. of Sub Techniques]]),Techniques[[#This Row],[No. of Sub Techniques]]>0,FALSE),SUM(IF(Techniques[[#This Row],[Technique]]=Techniques[Technique],Techniques[Detection Rules Modifier],0)),Techniques[[#This Row],[Detection Rules Modifier]])} -> 1 | N3: =IF(ISNUMBER(Techniques[[#This Row],[Detection Rules for Technique]]),Techniques[[#This Row],[Detection Rules for Technique]],0)+IF(ISNUMBER(Techniques[[#This Row],[Detection Rules for SubTech]]),Techniques[[#This Row],[Detection Rules for SubTech]],0) -> 0 | O3: =IF(Techniques[[#This Row],[Detection Rules]]>=Techniques[[#This Row],[Expected Detection Rules]],1,Techniques[[#This Row],[Detection Rules]]/Techniques[[#This Row],[Expected Detection Rules]]) -> 0 | P3: =IF(Techniques[[#This Row],[Expected Detection Rules]]<=0,"disabled",IF(Techniques[[#This Row],[Data Sources Available]]>0, IF(Techniques[[#This Row],[Detection Rules]]>0,"detect","no detect"),IF(Techniques[[#This Row],[Detection Rules]]>0,"inconsistent","no sources"))) -> no detect | S3: =IF(Techniques[[#This Row],[Expected Detection Rules]]<0,"expected detection rules negative!",IF(Techniques[[#This Row],[Detection Rules]]>Techniques[[#This Row],[Expected Detection Rules]],"more detection rules than expected!",IF(AND(IF(ISNUMBER(Techniques[[#This Row],[Detection Rules for Technique]]),Techniques[[#This Row],[Detection Rules for Technique]]>0,FALSE),IF(ISNUMBER(Techniques[[#This Row],[No. of Sub Techniques]]),Techniques[[#This Row],[No. of Sub Techniques]]>0,FALSE)),IF(Techniques[[#This Row],[Detection Rules for Technique]] > IF(ISNUMBER(Techniques[[#This Row],[Detection Rules Modifier]]),Techniques[[#This Row],[Detection Rules Modifier]],0), "modifier should be increased for the technique", ""),""))) | T3: Linux, Windows, macOS | U3: Adversaries may add junk data to protocols used for command and control to make detection more difficult.(Citation: FireEye SUNBURST Backdoor December 2020) By adding random or meaningless data to the protocols used for command and control, adversaries can prevent trivial methods for decoding, deciphering, or otherwise analyzing the traffic. Examples may include appending/prepending data with junk characters or writing junk characters between significant characters. | V3: Analyze network data for uncommon data flows (e.g., a client sending significantly more data than it receives from a server). Processes utilizing the network that do not normally have network communication or have never been seen before are suspicious. Analyze packet contents to detect communications that do not follow the expected protocol behavior for the port that is being used.(Citation: University of Birmingham C2) | W3: TRUE | X3: T1001
A4: T1001 | B4: T1001.002 | C4: Steganography (T1001.002) | D4: Command and Control | E4: Network Traffic: Network Traffic Content | F4: =LEN(E4)-LEN(SUBSTITUTE(E4,",",""))+1 -> 1 | G4: {=SUM(IF(ISERROR(FIND(Sources[Data Source],Techniques[[#This Row],[Data Sources]])),0,1)*IF(Sources[Available]="yes",1,0))} -> 1 | H4: {=IF(Techniques[[#This Row],[Technique]]=Techniques[[#This Row],[ID]],SUM(IF(Techniques[[#This Row],[ID]]=Techniques[Technique],1,0))-1,"")} | I4: {=IF(SUM(IF($C4=Detections[],IF(Detections[Is Active]="yes",1,0),0))>0,SUM(IF($C4=Detections[],IF(Detections[Is Active]="yes",1,0),0)),"")} | J4: {=IF(IF(ISNUMBER(Techniques[[#This Row],[No. of Sub Techniques]]), Techniques[[#This Row],[No. of Sub Techniques]]>0,FALSE),SUM(IF(Techniques[[#This Row],[Technique]]=Techniques[Technique],Techniques[Detection Rules for Technique],0))-IF(ISNUMBER(Techniques[[#This Row],[Detection Rules for Technique]]),Techniques[[#This Row],[Detection Rules for Technique]],0),"")} | K4: =IF(AND(ISNUMBER(Techniques[[#This Row],[No. of Sub Techniques]]),Techniques[[#This Row],[No. of Sub Techniques]]>1),Techniques[No. of Sub Techniques],1) -> 1 | M4: {=Techniques[[#This Row],[Min. Detection Rules]]+IF(IF(ISNUMBER(Techniques[[#This Row],[No. of Sub Techniques]]),Techniques[[#This Row],[No. of Sub Techniques]]>0,FALSE),SUM(IF(Techniques[[#This Row],[Technique]]=Techniques[Technique],Techniques[Detection Rules Modifier],0)),Techniques[[#This Row],[Detection Rules Modifier]])} -> 1 | N4: =IF(ISNUMBER(Techniques[[#This Row],[Detection Rules for Technique]]),Techniques[[#This Row],[Detection Rules for Technique]],0)+IF(ISNUMBER(Techniques[[#This Row],[Detection Rules for SubTech]]),Techniques[[#This Row],[Detection Rules for SubTech]],0) -> 0 | O4: =IF(Techniques[[#This Row],[Detection Rules]]>=Techniques[[#This Row],[Expected Detection Rules]],1,Techniques[[#This Row],[Detection Rules]]/Techniques[[#This Row],[Expected Detection Rules]]) -> 0 | P4: =IF(Techniques[[#This Row],[Expected Detection Rules]]<=0,"disabled",IF(Techniques[[#This Row],[Data Sources Available]]>0, IF(Techniques[[#This Row],[Detection Rules]]>0,"detect","no detect"),IF(Techniques[[#This Row],[Detection Rules]]>0,"inconsistent","no sources"))) -> no detect | S4: =IF(Techniques[[#This Row],[Expected Detection Rules]]<0,"expected detection rules negative!",IF(Techniques[[#This Row],[Detection Rules]]>Techniques[[#This Row],[Expected Detection Rules]],"more detection rules than expected!",IF(AND(IF(ISNUMBER(Techniques[[#This Row],[Detection Rules for Technique]]),Techniques[[#This Row],[Detection Rules for Technique]]>0,FALSE),IF(ISNUMBER(Techniques[[#This Row],[No. of Sub Techniques]]),Techniques[[#This Row],[No. of Sub Techniques]]>0,FALSE)),IF(Techniques[[#This Row],[Detection Rules for Technique]] > IF(ISNUMBER(Techniques[[#This Row],[Detection Rules Modifier]]),Techniques[[#This Row],[Detection Rules Modifier]],0), "modifier should be increased for the technique", ""),""))) | T4: Linux, Windows, macOS | U4: Adversaries may use steganographic techniques to hide command and control traffic to make detection efforts more difficult. Steganographic techniques can be used to hide data in digital messages that are transferred between systems. This hidden information can be used for command and control of compromised systems. In some cases, the passing of files embedded using steganography, such as image or document files, can be used for command and control. | V4: Analyze network data for uncommon data flows (e.g., a client sending significantly more data than it receives from a server). Processes utilizing the network that do not normally have network communication or have never been seen before are suspicious. Analyze packet contents to detect communications that do not follow the expected protocol behavior for the port that is being used.(Citation: University of Birmingham C2) | W4: TRUE | X4: T1001
A5: T1001 | B5: T1001.003 | C5: Protocol or Service Impersonation (T1001.003) | D5: Command and Control | E5: Network Traffic: Network Traffic Content | F5: =LEN(E5)-LEN(SUBSTITUTE(E5,",",""))+1 -> 1 | G5: {=SUM(IF(ISERROR(FIND(Sources[Data Source],Techniques[[#This Row],[Data Sources]])),0,1)*IF(Sources[Available]="yes",1,0))} -> 1 | H5: {=IF(Techniques[[#This Row],[Technique]]=Techniques[[#This Row],[ID]],SUM(IF(Techniques[[#This Row],[ID]]=Techniques[Technique],1,0))-1,"")} | I5: {=IF(SUM(IF($C5=Detections[],IF(Detections[Is Active]="yes",1,0),0))>0,SUM(IF($C5=Detections[],IF(Detections[Is Active]="yes",1,0),0)),"")} | J5: {=IF(IF(ISNUMBER(Techniques[[#This Row],[No. of Sub Techniques]]), Techniques[[#This Row],[No. of Sub Techniques]]>0,FALSE),SUM(IF(Techniques[[#This Row],[Technique]]=Techniques[Technique],Techniques[Detection Rules for Technique],0))-IF(ISNUMBER(Techniques[[#This Row],[Detection Rules for Technique]]),Techniques[[#This Row],[Detection Rules for Technique]],0),"")} | K5: =IF(AND(ISNUMBER(Techniques[[#This Row],[No. of Sub Techniques]]),Techniques[[#This Row],[No. of Sub Techniques]]>1),Techniques[No. of Sub Techniques],1) -> 1 | M5: {=Techniques[[#This Row],[Min. Detection Rules]]+IF(IF(ISNUMBER(Techniques[[#This Row],[No. of Sub Techniques]]),Techniques[[#This Row],[No. of Sub Techniques]]>0,FALSE),SUM(IF(Techniques[[#This Row],[Technique]]=Techniques[Technique],Techniques[Detection Rules Modifier],0)),Techniques[[#This Row],[Detection Rules Modifier]])} -> 1 | N5: =IF(ISNUMBER(Techniques[[#This Row],[Detection Rules for Technique]]),Techniques[[#This Row],[Detection Rules for Technique]],0)+IF(ISNUMBER(Techniques[[#This Row],[Detection Rules for SubTech]]),Techniques[[#This Row],[Detection Rules for SubTech]],0) -> 0 | O5: =IF(Techniques[[#This Row],[Detection Rules]]>=Techniques[[#This Row],[Expected Detection Rules]],1,Techniques[[#This Row],[Detection Rules]]/Techniques[[#This Row],[Expected Detection Rules]]) -> 0 | P5: =IF(Techniques[[#This Row],[Expected Detection Rules]]<=0,"disabled",IF(Techniques[[#This Row],[Data Sources Available]]>0, IF(Techniques[[#This Row],[Detection Rules]]>0,"detect","no detect"),IF(Techniques[[#This Row],[Detection Rules]]>0,"inconsistent","no sources"))) -> no detect | S5: =IF(Techniques[[#This Row],[Expected Detection Rules]]<0,"expected detection rules negative!",IF(Techniques[[#This Row],[Detection Rules]]>Techniques[[#This Row],[Expected Detection Rules]],"more detection rules than expected!",IF(AND(IF(ISNUMBER(Techniques[[#This Row],[Detection Rules for Technique]]),Techniques[[#This Row],[Detection Rules for Technique]]>0,FALSE),IF(ISNUMBER(Techniques[[#This Row],[No. of Sub Techniques]]),Techniques[[#This Row],[No. of Sub Techniques]]>0,FALSE)),IF(Techniques[[#This Row],[Detection Rules for Technique]] > IF(ISNUMBER(Techniques[[#This Row],[Detection Rules Modifier]]),Techniques[[#This Row],[Detection Rules Modifier]],0), "modifier should be increased for the technique", ""),""))) | T5: Linux, Windows, macOS | U5: Adversaries may impersonate legitimate protocols or web service traffic to disguise command and control activity and thwart analysis efforts. By impersonating legitimate protocols or web services, adversaries can make their command and control traffic blend in with legitimate network traffic. Adversaries may impersonate a fake SSL/TLS handshake to make it look like subsequent traffic is SSL/TLS encrypted, potentially interfering with some security tooling, or to make the traffic look like it is related with a trusted entity. Adversaries may also leverage legitimate protocols to impersonate expected web traffic or trusted services. For example, adversaries may manipulate HTTP headers, URI endpoints, SSL certificates, and transmitted data to disguise C2 communications or mimic legitimate services such as Gmail, Google Drive, and Yahoo Messenger.(Citation: ESET Okrum July 2019)(Citation: Malleable-C2-U42) | V5: Analyze network data for uncommon data flows (e.g., a client sending significantly more data than it receives from a server). Processes utilizing the network that do not normally have network communication or have never been seen before are suspicious. Analyze packet contents to detect communications that do not follow the expected protocol behavior for the port that is being used.(Citation: University of Birmingham C2) | W5: TRUE | X5: T1001
A6: T1003 | B6: T1003 | C6: OS Credential Dumping (T1003) | D6: Credential Access | E6: Active Directory: Active Directory Object Access, Command: Command Execution, File: File Access, File: File Creation, Network Traffic: Network Traffic Content, Network Traffic: Network Traffic Flow, Process: OS API Execution, Process: Process Access, Process: Process Creation, Windows Registry: Windows Registry Key Access | F6: =LEN(E6)-LEN(SUBSTITUTE(E6,",",""))+1 -> 10 | G6: {=SUM(IF(ISERROR(FIND(Sources[Data Source],Techniques[[#This Row],[Data Sources]])),0,1)*IF(Sources[Available]="yes",1,0))} -> 4 | H6: {=IF(Techniques[[#This Row],[Technique]]=Techniques[[#This Row],[ID]],SUM(IF(Techniques[[#This Row],[ID]]=Techniques[Technique],1,0))-1,"")} -> 8 | I6: {=IF(SUM(IF($C6=Detections[],IF(Detections[Is Active]="yes",1,0),0))>0,SUM(IF($C6=Detections[],IF(Detections[Is Active]="yes",1,0),0)),"")} -> 1 | J6: {=IF(IF(ISNUMBER(Techniques[[#This Row],[No. of Sub Techniques]]), Techniques[[#This Row],[No. of Sub Techniques]]>0,FALSE),SUM(IF(Techniques[[#This Row],[Technique]]=Techniques[Technique],Techniques[Detection Rules for Technique],0))-IF(ISNUMBER(Techniques[[#This Row],[Detection Rules for Technique]]),Techniques[[#This Row],[Detection Rules for Technique]],0),"")} -> 1 | K6: =IF(AND(ISNUMBER(Techniques[[#This Row],[No. of Sub Techniques]]),Techniques[[#This Row],[No. of Sub Techniques]]>1),Techniques[No. of Sub Techniques],1) -> 8 | M6: {=Techniques[[#This Row],[Min. Detection Rules]]+IF(IF(ISNUMBER(Techniques[[#This Row],[No. of Sub Techniques]]),Techniques[[#This Row],[No. of Sub Techniques]]>0,FALSE),SUM(IF(Techniques[[#This Row],[Technique]]=Techniques[Technique],Techniques[Detection Rules Modifier],0)),Techniques[[#This Row],[Detection Rules Modifier]])} -> 8 | N6: =IF(ISNUMBER(Techniques[[#This Row],[Detection Rules for Technique]]),Techniques[[#This Row],[Detection Rules for Technique]],0)+IF(ISNUMBER(Techniques[[#This Row],[Detection Rules for SubTech]]),Techniques[[#This Row],[Detection Rules for SubTech]],0) -> 2 | O6: =IF(Techniques[[#This Row],[Detection Rules]]>=Techniques[[#This Row],[Expected Detection Rules]],1,Techniques[[#This Row],[Detection Rules]]/Techniques[[#This Row],[Expected Detection Rules]]) -> 0.25 | P6: =IF(Techniques[[#This Row],[Expected Detection Rules]]<=0,"disabled",IF(Techniques[[#This Row],[Data Sources Available]]>0, IF(Techniques[[#This Row],[Detection Rules]]>0,"detect","no detect"),IF(Techniques[[#This Row],[Detection Rules]]>0,"inconsistent","no sources"))) -> detect | S6: =IF(Techniques[[#This Row],[Expected Detection Rules]]<0,"expected detection rules negative!",IF(Techniques[[#This Row],[Detection Rules]]>Techniques[[#This Row],[Expected Detection Rules]],"more detection rules than expected!",IF(AND(IF(ISNUMBER(Techniques[[#This Row],[Detection Rules for Technique]]),Techniques[[#This Row],[Detection Rules for Technique]]>0,FALSE),IF(ISNUMBER(Techniques[[#This Row],[No. of Sub Techniques]]),Techniques[[#This Row],[No. of Sub Techniques]]>0,FALSE)),IF(Techniques[[#This Row],[Detection Rules for Technique]] > IF(ISNUMBER(Techniques[[#This Row],[Detection Rules Modifier]]),Techniques[[#This Row],[Detection Rules Modifier]],0), "modifier should be increased for the technique", ""),""))) -> modifier should be increased for the technique | T6: Linux, Windows, macOS | U6: Adversaries may attempt to dump credentials to obtain account login and credential material, normally in the form of a hash or a clear text password. Credentials can be obtained from OS caches, memory, or structures.(Citation: Brining MimiKatz to Unix) Credentials can then be used to perform [Lateral Movement](https://attack.mitre.org/tactics/TA0008) and access restricted information. Several of the tools mentioned in associated sub-techniques may be used by both adversaries and professional security testers. Additional custom tools likely exist as well. | V6: ### Windows Monitor for unexpected processes interacting with lsass.exe.(Citation: Medium Detecting Attempts to Steal Passwords from Memory) Common credential dumpers such as [Mimikatz](https://attack.mitre.org/software/S0002) access the LSA Subsystem Service (LSASS) process by opening the process, locating the LSA secrets key, and decrypting the sections in memory where credential details are stored. Credential dumpers may also use methods for reflective [Process Injection](https://attack.mitre.org/techniques/T1055) to reduce potential indicators of malicious activity. Hash dumpers open the Security Accounts Manager (SAM) on the local file system (%SystemRoot%/system32/config/SAM) or create a dump of the Registry SAM key to access stored account password hashes. Some hash dumpers will open the local file system as a device and parse to the SAM table to avoid file access defenses. Others will make an in-memory copy of the SAM table before reading hashes. Detection of compromised [Valid Accounts](https://attack.mitre.org/techniques/T1078) in-use by adversaries may help as well. On Windows 8.1 and Windows Server 2012 R2, monitor Windows Logs for LSASS.exe creation to verify that LSASS started as a protected process. Monitor processes and command-line arguments for program execution that may be indicative of credential dumping. Remote access tools may contain built-in features or incorporate existing tools like [Mimikatz](https://attack.mitre.org/software/S0002). [PowerShell](https://attack.mitre.org/techniques/T1059/001) scripts also exist that contain credential dumping functionality, such as PowerSploit's Invoke-Mimikatz module, (Citation: Powersploit) which may require additional logging features to be configured in the operating system to collect necessary information for analysis. Monitor domain controller logs for replication requests and other unscheduled activity possibly associated with DCSync. (Citation: Microsoft DRSR Dec 2017) (Citation: Microsoft GetNCCChanges) (Citation: Samba DRSUAPI) Note: Domain controllers may not log replication requests originating from the default domain controller account. (Citation: Harmj0y DCSync Sept 2015). Also monitor for network protocols (Citation: Microsoft DRSR Dec 2017) (Citation: Microsoft NRPC Dec 2017) and other replication requests (Citation: Microsoft SAMR) from IPs not associated with known domain controllers. (Citation: AdSecurity DCSync Sept 2015) ### Linux To obtain the passwords and hashes stored in memory, processes must open a maps file in the `/proc` filesystem for the process being analyzed. This file is stored under the path `/proc/<pid>/maps`, where the `<pid>` directory is the unique pid of the program being interrogated for such authentication data. The AuditD monitoring tool, which ships stock in many Linux distributions, can be used to watch for hostile processes opening this file in the proc file system, alerting on the pid, process name, and arguments of such programs. | W6: FALSE
A7: T1003 | B7: T1003.001 | C7: LSASS Memory (T1003.001) | D7: Credential Access | E7: Command: Command Execution, File: File Creation, Logon Session: Logon Session Creation, Process: OS API Execution, Process: Process Access, Process: Process Creation, Windows Registry: Windows Registry Key Modification | F7: =LEN(E7)-LEN(SUBSTITUTE(E7,",",""))+1 -> 7 | G7: {=SUM(IF(ISERROR(FIND(Sources[Data Source],Techniques[[#This Row],[Data Sources]])),0,1)*IF(Sources[Available]="yes",1,0))} -> 1 | H7: {=IF(Techniques[[#This Row],[Technique]]=Techniques[[#This Row],[ID]],SUM(IF(Techniques[[#This Row],[ID]]=Techniques[Technique],1,0))-1,"")} | I7: {=IF(SUM(IF($C7=Detections[],IF(Detections[Is Active]="yes",1,0),0))>0,SUM(IF($C7=Detections[],IF(Detections[Is Active]="yes",1,0),0)),"")} | J7: {=IF(IF(ISNUMBER(Techniques[[#This Row],[No. of Sub Techniques]]), Techniques[[#This Row],[No. of Sub Techniques]]>0,FALSE),SUM(IF(Techniques[[#This Row],[Technique]]=Techniques[Technique],Techniques[Detection Rules for Technique],0))-IF(ISNUMBER(Techniques[[#This Row],[Detection Rules for Technique]]),Techniques[[#This Row],[Detection Rules for Technique]],0),"")} | K7: =IF(AND(ISNUMBER(Techniques[[#This Row],[No. of Sub Techniques]]),Techniques[[#This Row],[No. of Sub Techniques]]>1),Techniques[No. of Sub Techniques],1) -> 1 | M7: {=Techniques[[#This Row],[Min. Detection Rules]]+IF(IF(ISNUMBER(Techniques[[#This Row],[No. of Sub Techniques]]),Techniques[[#This Row],[No. of Sub Techniques]]>0,FALSE),SUM(IF(Techniques[[#This Row],[Technique]]=Techniques[Technique],Techniques[Detection Rules Modifier],0)),Techniques[[#This Row],[Detection Rules Modifier]])} -> 1 | N7: =IF(ISNUMBER(Techniques[[#This Row],[Detection Rules for Technique]]),Techniques[[#This Row],[Detection Rules for Technique]],0)+IF(ISNUMBER(Techniques[[#This Row],[Detection Rules for SubTech]]),Techniques[[#This Row],[Detection Rules for SubTech]],0) -> 0 | O7: =IF(Techniques[[#This Row],[Detection Rules]]>=Techniques[[#This Row],[Expected Detection Rules]],1,Techniques[[#This Row],[Detection Rules]]/Techniques[[#This Row],[Expected Detection Rules]]) -> 0 | P7: =IF(Techniques[[#This Row],[Expected Detection Rules]]<=0,"disabled",IF(Techniques[[#This Row],[Data Sources Available]]>0, IF(Techniques[[#This Row],[Detection Rules]]>0,"detect","no detect"),IF(Techniques[[#This Row],[Detection Rules]]>0,"inconsistent","no sources"))) -> no detect | S7: =IF(Techniques[[#This Row],[Expected Detection Rules]]<0,"expected detection rules negative!",IF(Techniques[[#This Row],[Detection Rules]]>Techniques[[#This Row],[Expected Detection Rules]],"more detection rules than expected!",IF(AND(IF(ISNUMBER(Techniques[[#This Row],[Detection Rules for Technique]]),Techniques[[#This Row],[Detection Rules for Technique]]>0,FALSE),IF(ISNUMBER(Techniques[[#This Row],[No. of Sub Techniques]]),Techniques[[#This Row],[No. of Sub Techniques]]>0,FALSE)),IF(Techniques[[#This Row],[Detection Rules for Technique]] > IF(ISNUMBER(Techniques[[#This Row],[Detection Rules Modifier]]),Techniques[[#This Row],[Detection Rules Modifier]],0), "modifier should be increased for the technique", ""),""))) | T7: Windows | U7: Adversaries may attempt to access credential material stored in the process memory of the Local Security Authority Subsystem Service (LSASS). After a user logs on, the system generates and stores a variety of credential materials in LSASS process memory. These credential materials can be harvested by an administrative user or SYSTEM and used to conduct [Lateral Movement](https://attack.mitre.org/tactics/TA0008) using [Use Alternate Authentication Material](https://attack.mitre.org/techniques/T1550). As well as in-memory techniques, the LSASS process memory can be dumped from the target host and analyzed on a local system. For example, on the target host use procdump: * <code>procdump -ma lsass.exe lsass_dump</code> Locally, mimikatz can be run using: * <code>sekurlsa::Minidump lsassdump.dmp</code> * <code>sekurlsa::logonPasswords</code> Built-in Windows tools such as `comsvcs.dll` can also be used: * <code>rundll32.exe C:\Windows\System32\comsvcs.dll MiniDump PID lsass.dmp full</code>(Citation: Volexity Exchange Marauder March 2021)(Citation: Symantec Attacks Against Government Sector) Similar to [Image File Execution Options Injection](https://attack.mitre.org/techniques/T1546/012), the silent process exit mechanism can be abused to create a memory dump of `lsass.exe` through Windows Error Reporting (`WerFault.exe`).(Citation: Deep Instinct LSASS) Windows Security Support Provider (SSP) DLLs are loaded into LSASS process at system start. Once loaded into the LSA, SSP DLLs have access to encrypted and plaintext passwords that are stored in Windows, such as any logged-on user's Domain password or smart card PINs. The SSP configuration is stored in two Registry keys: <code>HKLM\SYSTEM\CurrentControlSet\Control\Lsa\Security Packages</code> and <code>HKLM\SYSTEM\CurrentControlSet\Control\Lsa\OSConfig\Security Packages</code>. An adversary may modify these Registry keys to add new SSPs, which will be loaded the next time the system boots, or when the AddSecurityPackage Windows API function is called.(Citation: Graeber 2014) The following SSPs can be used to access credentials: * Msv: Interactive logons, batch logons, and service logons are done through the MSV authentication package. * Wdigest: The Digest Authentication protocol is designed for use with Hypertext Transfer Protocol (HTTP) and Simple Authentication Security Layer (SASL) exchanges.(Citation: TechNet Blogs Credential Protection) * Kerberos: Preferred for mutual client-server domain authentication in Windows 2000 and later. * CredSSP: Provides SSO and Network Level Authentication for Remote Desktop Services.(Citation: TechNet Blogs Credential Protection) | V7: Monitor for unexpected processes interacting with LSASS.exe.(Citation: Medium Detecting Attempts to Steal Passwords from Memory) Common credential dumpers such as Mimikatz access LSASS.exe by opening the process, locating the LSA secrets key, and decrypting the sections in memory where credential details are stored. Credential dumpers may also use methods for reflective [Process Injection](https://attack.mitre.org/techniques/T1055) to reduce potential indicators of malicious activity. On Windows 8.1 and Windows Server 2012 R2, monitor Windows Logs for LSASS.exe creation to verify that LSASS started as a protected process. Monitor processes and command-line arguments for program execution that may be indicative of credential dumping. Remote access tools may contain built-in features or incorporate existing tools like Mimikatz. PowerShell scripts also exist that contain credential dumping functionality, such as PowerSploit's Invoke-Mimikatz module,(Citation: Powersploit) which may require additional logging features to be configured in the operating system to collect necessary information for analysis. | W7: TRUE | X7: T1003
A8: T1003 | B8: T1003.002 | C8: Security Account Manager (T1003.002) | D8: Credential Access | E8: Command: Command Execution, File: File Access, File: File Creation, Windows Registry: Windows Registry Key Access | F8: =LEN(E8)-LEN(SUBSTITUTE(E8,",",""))+1 -> 4 | G8: {=SUM(IF(ISERROR(FIND(Sources[Data Source],Techniques[[#This Row],[Data Sources]])),0,1)*IF(Sources[Available]="yes",1,0))} -> 1 | H8: {=IF(Techniques[[#This Row],[Technique]]=Techniques[[#This Row],[ID]],SUM(IF(Techniques[[#This Row],[ID]]=Techniques[Technique],1,0))-1,"")} | I8: {=IF(SUM(IF($C8=Detections[],IF(Detections[Is Active]="yes",1,0),0))>0,SUM(IF($C8=Detections[],IF(Detections[Is Active]="yes",1,0),0)),"")} | J8: {=IF(IF(ISNUMBER(Techniques[[#This Row],[No. of Sub Techniques]]), Techniques[[#This Row],[No. of Sub Techniques]]>0,FALSE),SUM(IF(Techniques[[#This Row],[Technique]]=Techniques[Technique],Techniques[Detection Rules for Technique],0))-IF(ISNUMBER(Techniques[[#This Row],[Detection Rules for Technique]]),Techniques[[#This Row],[Detection Rules for Technique]],0),"")} | K8: =IF(AND(ISNUMBER(Techniques[[#This Row],[No. of Sub Techniques]]),Techniques[[#This Row],[No. of Sub Techniques]]>1),Techniques[No. of Sub Techniques],1) -> 1 | M8: {=Techniques[[#This Row],[Min. Detection Rules]]+IF(IF(ISNUMBER(Techniques[[#This Row],[No. of Sub Techniques]]),Techniques[[#This Row],[No. of Sub Techniques]]>0,FALSE),SUM(IF(Techniques[[#This Row],[Technique]]=Techniques[Technique],Techniques[Detection Rules Modifier],0)),Techniques[[#This Row],[Detection Rules Modifier]])} -> 1 | N8: =IF(ISNUMBER(Techniques[[#This Row],[Detection Rules for Technique]]),Techniques[[#This Row],[Detection Rules for Technique]],0)+IF(ISNUMBER(Techniques[[#This Row],[Detection Rules for SubTech]]),Techniques[[#This Row],[Detection Rules for SubTech]],0) -> 0 | O8: =IF(Techniques[[#This Row],[Detection Rules]]>=Techniques[[#This Row],[Expected Detection Rules]],1,Techniques[[#This Row],[Detection Rules]]/Techniques[[#This Row],[Expected Detection Rules]]) -> 0 | P8: =IF(Techniques[[#This Row],[Expected Detection Rules]]<=0,"disabled",IF(Techniques[[#This Row],[Data Sources Available]]>0, IF(Techniques[[#This Row],[Detection Rules]]>0,"detect","no detect"),IF(Techniques[[#This Row],[Detection Rules]]>0,"inconsistent","no sources"))) -> no detect | S8: =IF(Techniques[[#This Row],[Expected Detection Rules]]<0,"expected detection rules negative!",IF(Techniques[[#This Row],[Detection Rules]]>Techniques[[#This Row],[Expected Detection Rules]],"more detection rules than expected!",IF(AND(IF(ISNUMBER(Techniques[[#This Row],[Detection Rules for Technique]]),Techniques[[#This Row],[Detection Rules for Technique]]>0,FALSE),IF(ISNUMBER(Techniques[[#This Row],[No. of Sub Techniques]]),Techniques[[#This Row],[No. of Sub Techniques]]>0,FALSE)),IF(Techniques[[#This Row],[Detection Rules for Technique]] > IF(ISNUMBER(Techniques[[#This Row],[Detection Rules Modifier]]),Techniques[[#This Row],[Detection Rules Modifier]],0), "modifier should be increased for the technique", ""),""))) | T8: Windows | U8: Adversaries may attempt to extract credential material from the Security Account Manager (SAM) database either through in-memory techniques or through the Windows Registry where the SAM database is stored. The SAM is a database file that contains local accounts for the host, typically those found with the <code>net user</code> command. Enumerating the SAM database requires SYSTEM level access. A number of tools can be used to retrieve the SAM file through in-memory techniques: * pwdumpx.exe * [gsecdump](https://attack.mitre.org/software/S0008) * [Mimikatz](https://attack.mitre.org/software/S0002) * secretsdump.py Alternatively, the SAM can be extracted from the Registry with Reg: * <code>reg save HKLM\sam sam</code> * <code>reg save HKLM\system system</code> Creddump7 can then be used to process the SAM database locally to retrieve hashes.(Citation: GitHub Creddump7) Notes: * RID 500 account is the local, built-in administrator. * RID 501 is the guest account. * User accounts start with a RID of 1,000+. | V8: Hash dumpers open the Security Accounts Manager (SAM) on the local file system (<code>%SystemRoot%/system32/config/SAM</code>) or create a dump of the Registry SAM key to access stored account password hashes. Some hash dumpers will open the local file system as a device and parse to the SAM table to avoid file access defenses. Others will make an in-memory copy of the SAM table before reading hashes. Detection of compromised [Valid Accounts](https://attack.mitre.org/techniques/T1078) in-use by adversaries may help as well. | W8: TRUE | X8: T1003
A9: T1003 | B9: T1003.003 | C9: NTDS (T1003.003) | D9: Credential Access | E9: Command: Command Execution, File: File Access | F9: =LEN(E9)-LEN(SUBSTITUTE(E9,",",""))+1 -> 2 | G9: {=SUM(IF(ISERROR(FIND(Sources[Data Source],Techniques[[#This Row],[Data Sources]])),0,1)*IF(Sources[Available]="yes",1,0))} -> 1 | H9: {=IF(Techniques[[#This Row],[Technique]]=Techniques[[#This Row],[ID]],SUM(IF(Techniques[[#This Row],[ID]]=Techniques[Technique],1,0))-1,"")} | I9: {=IF(SUM(IF($C9=Detections[],IF(Detections[Is Active]="yes",1,0),0))>0,SUM(IF($C9=Detections[],IF(Detections[Is Active]="yes",1,0),0)),"")} -> 1 | J9: {=IF(IF(ISNUMBER(Techniques[[#This Row],[No. of Sub Techniques]]), Techniques[[#This Row],[No. of Sub Techniques]]>0,FALSE),SUM(IF(Techniques[[#This Row],[Technique]]=Techniques[Technique],Techniques[Detection Rules for Technique],0))-IF(ISNUMBER(Techniques[[#This Row],[Detection Rules for Technique]]),Techniques[[#This Row],[Detection Rules for Technique]],0),"")} | K9: =IF(AND(ISNUMBER(Techniques[[#This Row],[No. of Sub Techniques]]),Techniques[[#This Row],[No. of Sub Techniques]]>1),Techniques[No. of Sub Techniques],1) -> 1 | M9: {=Techniques[[#This Row],[Min. Detection Rules]]+IF(IF(ISNUMBER(Techniques[[#This Row],[No. of Sub Techniques]]),Techniques[[#This Row],[No. of Sub Techniques]]>0,FALSE),SUM(IF(Techniques[[#This Row],[Technique]]=Techniques[Technique],Techniques[Detection Rules Modifier],0)),Techniques[[#This Row],[Detection Rules Modifier]])} -> 1 | N9: =IF(ISNUMBER(Techniques[[#This Row],[Detection Rules for Technique]]),Techniques[[#This Row],[Detection Rules for Technique]],0)+IF(ISNUMBER(Techniques[[#This Row],[Detection Rules for SubTech]]),Techniques[[#This Row],[Detection Rules for SubTech]],0) -> 1 | O9: =IF(Techniques[[#This Row],[Detection Rules]]>=Techniques[[#This Row],[Expected Detection Rules]],1,Techniques[[#This Row],[Detection Rules]]/Techniques[[#This Row],[Expected Detection Rules]]) -> 1 | P9: =IF(Techniques[[#This Row],[Expected Detection Rules]]<=0,"disabled",IF(Techniques[[#This Row],[Data Sources Available]]>0, IF(Techniques[[#This Row],[Detection Rules]]>0,"detect","no detect"),IF(Techniques[[#This Row],[Detection Rules]]>0,"inconsistent","no sources"))) -> detect | S9: =IF(Techniques[[#This Row],[Expected Detection Rules]]<0,"expected detection rules negative!",IF(Techniques[[#This Row],[Detection Rules]]>Techniques[[#This Row],[Expected Detection Rules]],"more detection rules than expected!",IF(AND(IF(ISNUMBER(Techniques[[#This Row],[Detection Rules for Technique]]),Techniques[[#This Row],[Detection Rules for Technique]]>0,FALSE),IF(ISNUMBER(Techniques[[#This Row],[No. of Sub Techniques]]),Techniques[[#This Row],[No. of Sub Techniques]]>0,FALSE)),IF(Techniques[[#This Row],[Detection Rules for Technique]] > IF(ISNUMBER(Techniques[[#This Row],[Detection Rules Modifier]]),Techniques[[#This Row],[Detection Rules Modifier]],0), "modifier should be increased for the technique", ""),""))) | T9: Windows | U9: Adversaries may attempt to access or create a copy of the Active Directory domain database in order to steal credential information, as well as obtain other information about domain members such as devices, users, and access rights. By default, the NTDS file (NTDS.dit) is located in <code>%SystemRoot%\NTDS\Ntds.dit</code> of a domain controller.(Citation: Wikipedia Active Directory) In addition to looking for NTDS files on active Domain Controllers, adversaries may search for backups that contain the same or similar information.(Citation: Metcalf 2015) The following tools and techniques can be used to enumerate the NTDS file and the contents of the entire Active Directory hashes. * Volume Shadow Copy * secretsdump.py * Using the in-built Windows tool, ntdsutil.exe * Invoke-NinjaCopy | V9: Monitor processes and command-line arguments for program execution that may be indicative of credential dumping, especially attempts to access or copy the NTDS.dit. | W9: TRUE | X9: T1003
A10: T1003 | B10: T1003.004 | C10: LSA Secrets (T1003.004) | D10: Credential Access | E10: Command: Command Execution, Windows Registry: Windows Registry Key Access | F10: =LEN(E10)-LEN(SUBSTITUTE(E10,",",""))+1 -> 2 | G10: {=SUM(IF(ISERROR(FIND(Sources[Data Source],Techniques[[#This Row],[Data Sources]])),0,1)*IF(Sources[Available]="yes",1,0))} -> 1 | H10: {=IF(Techniques[[#This Row],[Technique]]=Techniques[[#This Row],[ID]],SUM(IF(Techniques[[#This Row],[ID]]=Techniques[Technique],1,0))-1,"")} | I10: {=IF(SUM(IF($C10=Detections[],IF(Detections[Is Active]="yes",1,0),0))>0,SUM(IF($C10=Detections[],IF(Detections[Is Active]="yes",1,0),0)),"")} | J10: {=IF(IF(ISNUMBER(Techniques[[#This Row],[No. of Sub Techniques]]), Techniques[[#This Row],[No. of Sub Techniques]]>0,FALSE),SUM(IF(Techniques[[#This Row],[Technique]]=Techniques[Technique],Techniques[Detection Rules for Technique],0))-IF(ISNUMBER(Techniques[[#This Row],[Detection Rules for Technique]]),Techniques[[#This Row],[Detection Rules for Technique]],0),"")} | K10: =IF(AND(ISNUMBER(Techniques[[#This Row],[No. of Sub Techniques]]),Techniques[[#This Row],[No. of Sub Techniques]]>1),Techniques[No. of Sub Techniques],1) -> 1 | M10: {=Techniques[[#This Row],[Min. Detection Rules]]+IF(IF(ISNUMBER(Techniques[[#This Row],[No. of Sub Techniques]]),Techniques[[#This Row],[No. of Sub Techniques]]>0,FALSE),SUM(IF(Techniques[[#This Row],[Technique]]=Techniques[Technique],Techniques[Detection Rules Modifier],0)),Techniques[[#This Row],[Detection Rules Modifier]])} -> 1 | N10: =IF(ISNUMBER(Techniques[[#This Row],[Detection Rules for Technique]]),Techniques[[#This Row],[Detection Rules for Technique]],0)+IF(ISNUMBER(Techniques[[#This Row],[Detection Rules for SubTech]]),Techniques[[#This Row],[Detection Rules for SubTech]],0) -> 0 | O10: =IF(Techniques[[#This Row],[Detection Rules]]>=Techniques[[#This Row],[Expected Detection Rules]],1,Techniques[[#This Row],[Detection Rules]]/Techniques[[#This Row],[Expected Detection Rules]]) -> 0 | P10: =IF(Techniques[[#This Row],[Expected Detection Rules]]<=0,"disabled",IF(Techniques[[#This Row],[Data Sources Available]]>0, IF(Techniques[[#This Row],[Detection Rules]]>0,"detect","no detect"),IF(Techniques[[#This Row],[Detection Rules]]>0,"inconsistent","no sources"))) -> no detect | S10: =IF(Techniques[[#This Row],[Expected Detection Rules]]<0,"expected detection rules negative!",IF(Techniques[[#This Row],[Detection Rules]]>Techniques[[#This Row],[Expected Detection Rules]],"more detection rules than expected!",IF(AND(IF(ISNUMBER(Techniques[[#This Row],[Detection Rules for Technique]]),Techniques[[#This Row],[Detection Rules for Technique]]>0,FALSE),IF(ISNUMBER(Techniques[[#This Row],[No. of Sub Techniques]]),Techniques[[#This Row],[No. of Sub Techniques]]>0,FALSE)),IF(Techniques[[#This Row],[Detection Rules for Technique]] > IF(ISNUMBER(Techniques[[#This Row],[Detection Rules Modifier]]),Techniques[[#This Row],[Detection Rules Modifier]],0), "modifier should be increased for the technique", ""),""))) | T10: Windows | U10: Adversaries with SYSTEM access to a host may attempt to access Local Security Authority (LSA) secrets, which can contain a variety of different credential materials, such as credentials for service accounts.(Citation: Passcape LSA Secrets)(Citation: Microsoft AD Admin Tier Model)(Citation: Tilbury Windows Credentials) LSA secrets are stored in the registry at <code>HKEY_LOCAL_MACHINE\SECURITY\Policy\Secrets</code>. LSA secrets can also be dumped from memory.(Citation: ired Dumping LSA Secrets) [Reg](https://attack.mitre.org/software/S0075) can be used to extract from the Registry. [Mimikatz](https://attack.mitre.org/software/S0002) can be used to extract secrets from memory.(Citation: ired Dumping LSA Secrets) | V10: Monitor processes and command-line arguments for program execution that may be indicative of credential dumping. Remote access tools may contain built-in features or incorporate existing tools like Mimikatz. PowerShell scripts also exist that contain credential dumping functionality, such as PowerSploit's Invoke-Mimikatz module,(Citation: Powersploit) which may require additional logging features to be configured in the operating system to collect necessary information for analysis. | W10: TRUE | X10: T1003
A11: T1003 | B11: T1003.005 | C11: Cached Domain Credentials (T1003.005) | D11: Credential Access | E11: Command: Command Execution | F11: =LEN(E11)-LEN(SUBSTITUTE(E11,",",""))+1 -> 1 | G11: {=SUM(IF(ISERROR(FIND(Sources[Data Source],Techniques[[#This Row],[Data Sources]])),0,1)*IF(Sources[Available]="yes",1,0))} -> 1 | H11: {=IF(Techniques[[#This Row],[Technique]]=Techniques[[#This Row],[ID]],SUM(IF(Techniques[[#This Row],[ID]]=Techniques[Technique],1,0))-1,"")} | I11: {=IF(SUM(IF($C11=Detections[],IF(Detections[Is Active]="yes",1,0),0))>0,SUM(IF($C11=Detections[],IF(Detections[Is Active]="yes",1,0),0)),"")} | J11: {=IF(IF(ISNUMBER(Techniques[[#This Row],[No. of Sub Techniques]]), Techniques[[#This Row],[No. of Sub Techniques]]>0,FALSE),SUM(IF(Techniques[[#This Row],[Technique]]=Techniques[Technique],Techniques[Detection Rules for Technique],0))-IF(ISNUMBER(Techniques[[#This Row],[Detection Rules for Technique]]),Techniques[[#This Row],[Detection Rules for Technique]],0),"")} | K11: =IF(AND(ISNUMBER(Techniques[[#This Row],[No. of Sub Techniques]]),Techniques[[#This Row],[No. of Sub Techniques]]>1),Techniques[No. of Sub Techniques],1) -> 1 | M11: {=Techniques[[#This Row],[Min. Detection Rules]]+IF(IF(ISNUMBER(Techniques[[#This Row],[No. of Sub Techniques]]),Techniques[[#This Row],[No. of Sub Techniques]]>0,FALSE),SUM(IF(Techniques[[#This Row],[Technique]]=Techniques[Technique],Techniques[Detection Rules Modifier],0)),Techniques[[#This Row],[Detection Rules Modifier]])} -> 1 | N11: =IF(ISNUMBER(Techniques[[#This Row],[Detection Rules for Technique]]),Techniques[[#This Row],[Detection Rules for Technique]],0)+IF(ISNUMBER(Techniques[[#This Row],[Detection Rules for SubTech]]),Techniques[[#This Row],[Detection Rules for SubTech]],0) -> 0 | O11: =IF(Techniques[[#This Row],[Detection Rules]]>=Techniques[[#This Row],[Expected Detection Rules]],1,Techniques[[#This Row],[Detection Rules]]/Techniques[[#This Row],[Expected Detection Rules]]) -> 0 | P11: =IF(Techniques[[#This Row],[Expected Detection Rules]]<=0,"disabled",IF(Techniques[[#This Row],[Data Sources Available]]>0, IF(Techniques[[#This Row],[Detection Rules]]>0,"detect","no detect"),IF(Techniques[[#This Row],[Detection Rules]]>0,"inconsistent","no sources"))) -> no detect | S11: =IF(Techniques[[#This Row],[Expected Detection Rules]]<0,"expected detection rules negative!",IF(Techniques[[#This Row],[Detection Rules]]>Techniques[[#This Row],[Expected Detection Rules]],"more detection rules than expected!",IF(AND(IF(ISNUMBER(Techniques[[#This Row],[Detection Rules for Technique]]),Techniques[[#This Row],[Detection Rules for Technique]]>0,FALSE),IF(ISNUMBER(Techniques[[#This Row],[No. of Sub Techniques]]),Techniques[[#This Row],[No. of Sub Techniques]]>0,FALSE)),IF(Techniques[[#This Row],[Detection Rules for Technique]] > IF(ISNUMBER(Techniques[[#This Row],[Detection Rules Modifier]]),Techniques[[#This Row],[Detection Rules Modifier]],0), "modifier should be increased for the technique", ""),""))) | T11: Linux, Windows | U11: Adversaries may attempt to access cached domain credentials used to allow authentication to occur in the event a domain controller is unavailable.(Citation: Microsoft - Cached Creds) On Windows Vista and newer, the hash format is DCC2 (Domain Cached Credentials version 2) hash, also known as MS-Cache v2 hash.(Citation: PassLib mscache) The number of default cached credentials varies and can be altered per system. This hash does not allow pass-the-hash style attacks, and instead requires [Password Cracking](https://attack.mitre.org/techniques/T1110/002) to recover the plaintext password.(Citation: ired mscache) On Linux systems, Active Directory credentials can be accessed through caches maintained by software like System Security Services Daemon (SSSD) or Quest Authentication Services (formerly VAS). Cached credential hashes are typically located at `/var/lib/sss/db/cache.[domain].ldb` for SSSD or `/var/opt/quest/vas/authcache/vas_auth.vdb` for Quest. Adversaries can use utilities, such as `tdbdump`, on these database files to dump the cached hashes and use [Password Cracking](https://attack.mitre.org/techniques/T1110/002) to obtain the plaintext password.(Citation: Brining MimiKatz to Unix) With SYSTEM or sudo access, the tools/utilities such as [Mimikatz](https://attack.mitre.org/software/S0002), [Reg](https://attack.mitre.org/software/S0075), and secretsdump.py for Windows or Linikatz for Linux can be used to extract the cached credentials.(Citation: Brining MimiKatz to Unix) Note: Cached credentials for Windows Vista are derived using PBKDF2.(Citation: PassLib mscache) | V11: Monitor processes and command-line arguments for program execution that may be indicative of credential dumping. Remote access tools may contain built-in features or incorporate existing tools like Mimikatz. PowerShell scripts also exist that contain credential dumping functionality, such as PowerSploit's Invoke-Mimikatz module,(Citation: Powersploit) which may require additional logging features to be configured in the operating system to collect necessary information for analysis. Detection of compromised [Valid Accounts](https://attack.mitre.org/techniques/T1078) in-use by adversaries may help as well. | W11: TRUE | X11: T1003
A12: T1003 | B12: T1003.006 | C12: DCSync (T1003.006) | D12: Credential Access | E12: Active Directory: Active Directory Object Access, Network Traffic: Network Traffic Content, Network Traffic: Network Traffic Flow | F12: =LEN(E12)-LEN(SUBSTITUTE(E12,",",""))+1 -> 3 | G12: {=SUM(IF(ISERROR(FIND(Sources[Data Source],Techniques[[#This Row],[Data Sources]])),0,1)*IF(Sources[Available]="yes",1,0))} -> 3 | H12: {=IF(Techniques[[#This Row],[Technique]]=Techniques[[#This Row],[ID]],SUM(IF(Techniques[[#This Row],[ID]]=Techniques[Technique],1,0))-1,"")} | I12: {=IF(SUM(IF($C12=Detections[],IF(Detections[Is Active]="yes",1,0),0))>0,SUM(IF($C12=Detections[],IF(Detections[Is Active]="yes",1,0),0)),"")} | J12: {=IF(IF(ISNUMBER(Techniques[[#This Row],[No. of Sub Techniques]]), Techniques[[#This Row],[No. of Sub Techniques]]>0,FALSE),SUM(IF(Techniques[[#This Row],[Technique]]=Techniques[Technique],Techniques[Detection Rules for Technique],0))-IF(ISNUMBER(Techniques[[#This Row],[Detection Rules for Technique]]),Techniques[[#This Row],[Detection Rules for Technique]],0),"")} | K12: =IF(AND(ISNUMBER(Techniques[[#This Row],[No. of Sub Techniques]]),Techniques[[#This Row],[No. of Sub Techniques]]>1),Techniques[No. of Sub Techniques],1) -> 1 | M12: {=Techniques[[#This Row],[Min. Detection Rules]]+IF(IF(ISNUMBER(Techniques[[#This Row],[No. of Sub Techniques]]),Techniques[[#This Row],[No. of Sub Techniques]]>0,FALSE),SUM(IF(Techniques[[#This Row],[Technique]]=Techniques[Technique],Techniques[Detection Rules Modifier],0)),Techniques[[#This Row],[Detection Rules Modifier]])} -> 1 | N12: =IF(ISNUMBER(Techniques[[#This Row],[Detection Rules for Technique]]),Techniques[[#This Row],[Detection Rules for Technique]],0)+IF(ISNUMBER(Techniques[[#This Row],[Detection Rules for SubTech]]),Techniques[[#This Row],[Detection Rules for SubTech]],0) -> 0 | O12: =IF(Techniques[[#This Row],[Detection Rules]]>=Techniques[[#This Row],[Expected Detection Rules]],1,Techniques[[#This Row],[Detection Rules]]/Techniques[[#This Row],[Expected Detection Rules]]) -> 0 | P12: =IF(Techniques[[#This Row],[Expected Detection Rules]]<=0,"disabled",IF(Techniques[[#This Row],[Data Sources Available]]>0, IF(Techniques[[#This Row],[Detection Rules]]>0,"detect","no detect"),IF(Techniques[[#This Row],[Detection Rules]]>0,"inconsistent","no sources"))) -> no detect | S12: =IF(Techniques[[#This Row],[Expected Detection Rules]]<0,"expected detection rules negative!",IF(Techniques[[#This Row],[Detection Rules]]>Techniques[[#This Row],[Expected Detection Rules]],"more detection rules than expected!",IF(AND(IF(ISNUMBER(Techniques[[#This Row],[Detection Rules for Technique]]),Techniques[[#This Row],[Detection Rules for Technique]]>0,FALSE),IF(ISNUMBER(Techniques[[#This Row],[No. of Sub Techniques]]),Techniques[[#This Row],[No. of Sub Techniques]]>0,FALSE)),IF(Techniques[[#This Row],[Detection Rules for Technique]] > IF(ISNUMBER(Techniques[[#This Row],[Detection Rules Modifier]]),Techniques[[#This Row],[Detection Rules Modifier]],0), "modifier should be increased for the technique", ""),""))) | T12: Windows | U12: Adversaries may attempt to access credentials and other sensitive information by abusing a Windows Domain Controller's application programming interface (API)(Citation: Microsoft DRSR Dec 2017) (Citation: Microsoft GetNCCChanges) (Citation: Samba DRSUAPI) (Citation: Wine API samlib.dll) to simulate the replication process from a remote domain controller using a technique called DCSync. Members of the Administrators, Domain Admins, and Enterprise Admin groups or computer accounts on the domain controller are able to run DCSync to pull password data(Citation: ADSecurity Mimikatz DCSync) from Active Directory, which may include current and historical hashes of potentially useful accounts such as KRBTGT and Administrators. The hashes can then in turn be used to create a [Golden Ticket](https://attack.mitre.org/techniques/T1558/001) for use in [Pass the Ticket](https://attack.mitre.org/techniques/T1550/003)(Citation: Harmj0y Mimikatz and DCSync) or change an account's password as noted in [Account Manipulation](https://attack.mitre.org/techniques/T1098).(Citation: InsiderThreat ChangeNTLM July 2017) DCSync functionality has been included in the "lsadump" module in [Mimikatz](https://attack.mitre.org/software/S0002).(Citation: GitHub Mimikatz lsadump Module) Lsadump also includes NetSync, which performs DCSync over a legacy replication protocol.(Citation: Microsoft NRPC Dec 2017) | V12: Monitor domain controller logs for replication requests and other unscheduled activity possibly associated with DCSync.(Citation: Microsoft DRSR Dec 2017) (Citation: Microsoft GetNCCChanges) (Citation: Samba DRSUAPI) Also monitor for network protocols(Citation: Microsoft DRSR Dec 2017) (Citation: Microsoft NRPC Dec 2017) and other replication requests(Citation: Microsoft SAMR) from IPs not associated with known domain controllers.(Citation: AdSecurity DCSync Sept 2015) Note: Domain controllers may not log replication requests originating from the default domain controller account.(Citation: Harmj0y DCSync Sept 2015) | W12: TRUE | X12: T1003
A13: T1003 | B13: T1003.007 | C13: Proc Filesystem (T1003.007) | D13: Credential Access | E13: Command: Command Execution, File: File Access | F13: =LEN(E13)-LEN(SUBSTITUTE(E13,",",""))+1 -> 2 | G13: {=SUM(IF(ISERROR(FIND(Sources[Data Source],Techniques[[#This Row],[Data Sources]])),0,1)*IF(Sources[Available]="yes",1,0))} -> 1 | H13: {=IF(Techniques[[#This Row],[Technique]]=Techniques[[#This Row],[ID]],SUM(IF(Techniques[[#This Row],[ID]]=Techniques[Technique],1,0))-1,"")} | I13: {=IF(SUM(IF($C13=Detections[],IF(Detections[Is Active]="yes",1,0),0))>0,SUM(IF($C13=Detections[],IF(Detections[Is Active]="yes",1,0),0)),"")} | J13: {=IF(IF(ISNUMBER(Techniques[[#This Row],[No. of Sub Techniques]]), Techniques[[#This Row],[No. of Sub Techniques]]>0,FALSE),SUM(IF(Techniques[[#This Row],[Technique]]=Techniques[Technique],Techniques[Detection Rules for Technique],0))-IF(ISNUMBER(Techniques[[#This Row],[Detection Rules for Technique]]),Techniques[[#This Row],[Detection Rules for Technique]],0),"")} | K13: =IF(AND(ISNUMBER(Techniques[[#This Row],[No. of Sub Techniques]]),Techniques[[#This Row],[No. of Sub Techniques]]>1),Techniques[No. of Sub Techniques],1) -> 1 | M13: {=Techniques[[#This Row],[Min. Detection Rules]]+IF(IF(ISNUMBER(Techniques[[#This Row],[No. of Sub Techniques]]),Techniques[[#This Row],[No. of Sub Techniques]]>0,FALSE),SUM(IF(Techniques[[#This Row],[Technique]]=Techniques[Technique],Techniques[Detection Rules Modifier],0)),Techniques[[#This Row],[Detection Rules Modifier]])} -> 1 | N13: =IF(ISNUMBER(Techniques[[#This Row],[Detection Rules for Technique]]),Techniques[[#This Row],[Detection Rules for Technique]],0)+IF(ISNUMBER(Techniques[[#This Row],[Detection Rules for SubTech]]),Techniques[[#This Row],[Detection Rules for SubTech]],0) -> 0 | O13: =IF(Techniques[[#This Row],[Detection Rules]]>=Techniques[[#This Row],[Expected Detection Rules]],1,Techniques[[#This Row],[Detection Rules]]/Techniques[[#This Row],[Expected Detection Rules]]) -> 0 | P13: =IF(Techniques[[#This Row],[Expected Detection Rules]]<=0,"disabled",IF(Techniques[[#This Row],[Data Sources Available]]>0, IF(Techniques[[#This Row],[Detection Rules]]>0,"detect","no detect"),IF(Techniques[[#This Row],[Detection Rules]]>0,"inconsistent","no sources"))) -> no detect | S13: =IF(Techniques[[#This Row],[Expected Detection Rules]]<0,"expected detection rules negative!",IF(Techniques[[#This Row],[Detection Rules]]>Techniques[[#This Row],[Expected Detection Rules]],"more detection rules than expected!",IF(AND(IF(ISNUMBER(Techniques[[#This Row],[Detection Rules for Technique]]),Techniques[[#This Row],[Detection Rules for Technique]]>0,FALSE),IF(ISNUMBER(Techniques[[#This Row],[No. of Sub Techniques]]),Techniques[[#This Row],[No. of Sub Techniques]]>0,FALSE)),IF(Techniques[[#This Row],[Detection Rules for Technique]] > IF(ISNUMBER(Techniques[[#This Row],[Detection Rules Modifier]]),Techniques[[#This Row],[Detection Rules Modifier]],0), "modifier should be increased for the technique", ""),""))) | T13: Linux | U13: Adversaries may gather credentials from the proc filesystem or `/proc`. The proc filesystem is a pseudo-filesystem used as an interface to kernel data structures for Linux based systems managing virtual memory. For each process, the `/proc/<PID>/maps` file shows how memory is mapped within the process’s virtual address space. And `/proc/<PID>/mem`, exposed for debugging purposes, provides access to the process’s virtual address space.(Citation: Picus Labs Proc cump 2022)(Citation: baeldung Linux proc map 2022) When executing with root privileges, adversaries can search these memory locations for all processes on a system that contain patterns indicative of credentials. Adversaries may use regex patterns, such as <code>grep -E "^[0-9a-f-]* r" /proc/"$pid"/maps | cut -d' ' -f 1</code>, to look for fixed strings in memory structures or cached hashes.(Citation: atomic-red proc file system) When running without privileged access, processes can still view their own virtual memory locations. Some services or programs may save credentials in clear text inside the process’s memory.(Citation: MimiPenguin GitHub May 2017)(Citation: Polop Linux PrivEsc Gitbook) If running as or with the permissions of a web browser, a process can search the `/maps` & `/mem` locations for common website credential patterns (that can also be used to find adjacent memory within the same structure) in which hashes or cleartext credentials may be located. | V13: To obtain the passwords and hashes stored in memory, processes must open a maps file in the `/proc` filesystem for the process being analyzed. This file is stored under the path `/proc/PID/maps`, where the `PID` directory is the unique pid of the program being interrogated for such authentication data. The AuditD monitoring tool, which ships stock in many Linux distributions, can be used to watch for hostile processes opening this file in the proc file system, alerting on the pid, process name, and arguments of such programs. | W13: TRUE | X13: T1003
A14: T1003 | B14: T1003.008 | C14: /etc/passwd and /etc/shadow (T1003.008) | D14: Credential Access | E14: Command: Command Execution, File: File Access | F14: =LEN(E14)-LEN(SUBSTITUTE(E14,",",""))+1 -> 2 | G14: {=SUM(IF(ISERROR(FIND(Sources[Data Source],Techniques[[#This Row],[Data Sources]])),0,1)*IF(Sources[Available]="yes",1,0))} -> 1 | H14: {=IF(Techniques[[#This Row],[Technique]]=Techniques[[#This Row],[ID]],SUM(IF(Techniques[[#This Row],[ID]]=Techniques[Technique],1,0))-1,"")} | I14: {=IF(SUM(IF($C14=Detections[],IF(Detections[Is Active]="yes",1,0),0))>0,SUM(IF($C14=Detections[],IF(Detections[Is Active]="yes",1,0),0)),"")} | J14: {=IF(IF(ISNUMBER(Techniques[[#This Row],[No. of Sub Techniques]]), Techniques[[#This Row],[No. of Sub Techniques]]>0,FALSE),SUM(IF(Techniques[[#This Row],[Technique]]=Techniques[Technique],Techniques[Detection Rules for Technique],0))-IF(ISNUMBER(Techniques[[#This Row],[Detection Rules for Technique]]),Techniques[[#This Row],[Detection Rules for Technique]],0),"")} | K14: =IF(AND(ISNUMBER(Techniques[[#This Row],[No. of Sub Techniques]]),Techniques[[#This Row],[No. of Sub Techniques]]>1),Techniques[No. of Sub Techniques],1) -> 1 | M14: {=Techniques[[#This Row],[Min. Detection Rules]]+IF(IF(ISNUMBER(Techniques[[#This Row],[No. of Sub Techniques]]),Techniques[[#This Row],[No. of Sub Techniques]]>0,FALSE),SUM(IF(Techniques[[#This Row],[Technique]]=Techniques[Technique],Techniques[Detection Rules Modifier],0)),Techniques[[#This Row],[Detection Rules Modifier]])} -> 1 | N14: =IF(ISNUMBER(Techniques[[#This Row],[Detection Rules for Technique]]),Techniques[[#This Row],[Detection Rules for Technique]],0)+IF(ISNUMBER(Techniques[[#This Row],[Detection Rules for SubTech]]),Techniques[[#This Row],[Detection Rules for SubTech]],0) -> 0 | O14: =IF(Techniques[[#This Row],[Detection Rules]]>=Techniques[[#This Row],[Expected Detection Rules]],1,Techniques[[#This Row],[Detection Rules]]/Techniques[[#This Row],[Expected Detection Rules]]) -> 0 | P14: =IF(Techniques[[#This Row],[Expected Detection Rules]]<=0,"disabled",IF(Techniques[[#This Row],[Data Sources Available]]>0, IF(Techniques[[#This Row],[Detection Rules]]>0,"detect","no detect"),IF(Techniques[[#This Row],[Detection Rules]]>0,"inconsistent","no sources"))) -> no detect | S14: =IF(Techniques[[#This Row],[Expected Detection Rules]]<0,"expected detection rules negative!",IF(Techniques[[#This Row],[Detection Rules]]>Techniques[[#This Row],[Expected Detection Rules]],"more detection rules than expected!",IF(AND(IF(ISNUMBER(Techniques[[#This Row],[Detection Rules for Technique]]),Techniques[[#This Row],[Detection Rules for Technique]]>0,FALSE),IF(ISNUMBER(Techniques[[#This Row],[No. of Sub Techniques]]),Techniques[[#This Row],[No. of Sub Techniques]]>0,FALSE)),IF(Techniques[[#This Row],[Detection Rules for Technique]] > IF(ISNUMBER(Techniques[[#This Row],[Detection Rules Modifier]]),Techniques[[#This Row],[Detection Rules Modifier]],0), "modifier should be increased for the technique", ""),""))) | T14: Linux | U14: Adversaries may attempt to dump the contents of <code>/etc/passwd</code> and <code>/etc/shadow</code> to enable offline password cracking. Most modern Linux operating systems use a combination of <code>/etc/passwd</code> and <code>/etc/shadow</code> to store user account information including password hashes in <code>/etc/shadow</code>. By default, <code>/etc/shadow</code> is only readable by the root user.(Citation: Linux Password and Shadow File Formats) The Linux utility, unshadow, can be used to combine the two files in a format suited for password cracking utilities such as John the Ripper:(Citation: nixCraft - John the Ripper) <code># /usr/bin/unshadow /etc/passwd /etc/shadow > /tmp/crack.password.db</code> | V14: The AuditD monitoring tool, which ships stock in many Linux distributions, can be used to watch for hostile processes attempting to access <code>/etc/passwd</code> and <code>/etc/shadow</code>, alerting on the pid, process name, and arguments of such programs. | W14: TRUE | X14: T1003
A15: T1005 | B15: T1005 | C15: Data from Local System (T1005) | D15: Collection | E15: Command: Command Execution, File: File Access, Process: OS API Execution, Process: Process Creation, Script: Script Execution | F15: =LEN(E15)-LEN(SUBSTITUTE(E15,",",""))+1 -> 5 | G15: {=SUM(IF(ISERROR(FIND(Sources[Data Source],Techniques[[#This Row],[Data Sources]])),0,1)*IF(Sources[Available]="yes",1,0))} -> 1 | H15: {=IF(Techniques[[#This Row],[Technique]]=Techniques[[#This Row],[ID]],SUM(IF(Techniques[[#This Row],[ID]]=Techniques[Technique],1,0))-1,"")} -> 0 | I15: {=IF(SUM(IF($C15=Detections[],IF(Detections[Is Active]="yes",1,0),0))>0,SUM(IF($C15=Detections[],IF(Detections[Is Active]="yes",1,0),0)),"")} | J15: {=IF(IF(ISNUMBER(Techniques[[#This Row],[No. of Sub Techniques]]), Techniques[[#This Row],[No. of Sub Techniques]]>0,FALSE),SUM(IF(Techniques[[#This Row],[Technique]]=Techniques[Technique],Techniques[Detection Rules for Technique],0))-IF(ISNUMBER(Techniques[[#This Row],[Detection Rules for Technique]]),Techniques[[#This Row],[Detection Rules for Technique]],0),"")} | K15: =IF(AND(ISNUMBER(Techniques[[#This Row],[No. of Sub Techniques]]),Techniques[[#This Row],[No. of Sub Techniques]]>1),Techniques[No. of Sub Techniques],1) -> 1 | M15: {=Techniques[[#This Row],[Min. Detection Rules]]+IF(IF(ISNUMBER(Techniques[[#This Row],[No. of Sub Techniques]]),Techniques[[#This Row],[No. of Sub Techniques]]>0,FALSE),SUM(IF(Techniques[[#This Row],[Technique]]=Techniques[Technique],Techniques[Detection Rules Modifier],0)),Techniques[[#This Row],[Detection Rules Modifier]])} -> 1 | N15: =IF(ISNUMBER(Techniques[[#This Row],[Detection Rules for Technique]]),Techniques[[#This Row],[Detection Rules for Technique]],0)+IF(ISNUMBER(Techniques[[#This Row],[Detection Rules for SubTech]]),Techniques[[#This Row],[Detection Rules for SubTech]],0) -> 0 | O15: =IF(Techniques[[#This Row],[Detection Rules]]>=Techniques[[#This Row],[Expected Detection Rules]],1,Techniques[[#This Row],[Detection Rules]]/Techniques[[#This Row],[Expected Detection Rules]]) -> 0 | P15: =IF(Techniques[[#This Row],[Expected Detection Rules]]<=0,"disabled",IF(Techniques[[#This Row],[Data Sources Available]]>0, IF(Techniques[[#This Row],[Detection Rules]]>0,"detect","no detect"),IF(Techniques[[#This Row],[Detection Rules]]>0,"inconsistent","no sources"))) -> no detect | S15: =IF(Techniques[[#This Row],[Expected Detection Rules]]<0,"expected detection rules negative!",IF(Techniques[[#This Row],[Detection Rules]]>Techniques[[#This Row],[Expected Detection Rules]],"more detection rules than expected!",IF(AND(IF(ISNUMBER(Techniques[[#This Row],[Detection Rules for Technique]]),Techniques[[#This Row],[Detection Rules for Technique]]>0,FALSE),IF(ISNUMBER(Techniques[[#This Row],[No. of Sub Techniques]]),Techniques[[#This Row],[No. of Sub Techniques]]>0,FALSE)),IF(Techniques[[#This Row],[Detection Rules for Technique]] > IF(ISNUMBER(Techniques[[#This Row],[Detection Rules Modifier]]),Techniques[[#This Row],[Detection Rules Modifier]],0), "modifier should be increased for the technique", ""),""))) | T15: Linux, Network, Windows, macOS | U15: Adversaries may search local system sources, such as file systems and configuration files or local databases, to find files of interest and sensitive data prior to Exfiltration. Adversaries may do this using a [Command and Scripting Interpreter](https://attack.mitre.org/techniques/T1059), such as [cmd](https://attack.mitre.org/software/S0106) as well as a [Network Device CLI](https://attack.mitre.org/techniques/T1059/008), which have functionality to interact with the file system to gather information.(Citation: show_run_config_cmd_cisco) Adversaries may also use [Automated Collection](https://attack.mitre.org/techniques/T1119) on the local system. | V15: Monitor processes and command-line arguments for actions that could be taken to collect files from a system. Remote access tools with built-in features may interact directly with the Windows API to gather data. Further, [Network Device CLI](https://attack.mitre.org/techniques/T1059/008) commands may also be used to collect files such as configuration files with built-in features native to the network device platform.(Citation: Mandiant APT41 Global Intrusion )(Citation: US-CERT-TA18-106A) Monitor CLI activity for unexpected or unauthorized use commands being run by non-standard users from non-standard locations. Data may also be acquired through Windows system management tools such as [Windows Management Instrumentation](https://attack.mitre.org/techniques/T1047) and [PowerShell](https://attack.mitre.org/techniques/T1059/001). For network infrastructure devices, collect AAA logging to monitor `show` commands that view configuration files. | W15: FALSE
A16: T1006 | B16: T1006 | C16: Direct Volume Access (T1006) | D16: Defense Evasion | E16: Command: Command Execution, Drive: Drive Access, File: File Creation | F16: =LEN(E16)-LEN(SUBSTITUTE(E16,",",""))+1 -> 3 | G16: {=SUM(IF(ISERROR(FIND(Sources[Data Source],Techniques[[#This Row],[Data Sources]])),0,1)*IF(Sources[Available]="yes",1,0))} -> 2 | H16: {=IF(Techniques[[#This Row],[Technique]]=Techniques[[#This Row],[ID]],SUM(IF(Techniques[[#This Row],[ID]]=Techniques[Technique],1,0))-1,"")} -> 0 | I16: {=IF(SUM(IF($C16=Detections[],IF(Detections[Is Active]="yes",1,0),0))>0,SUM(IF($C16=Detections[],IF(Detections[Is Active]="yes",1,0),0)),"")} | J16: {=IF(IF(ISNUMBER(Techniques[[#This Row],[No. of Sub Techniques]]), Techniques[[#This Row],[No. of Sub Techniques]]>0,FALSE),SUM(IF(Techniques[[#This Row],[Technique]]=Techniques[Technique],Techniques[Detection Rules for Technique],0))-IF(ISNUMBER(Techniques[[#This Row],[Detection Rules for Technique]]),Techniques[[#This Row],[Detection Rules for Technique]],0),"")} | K16: =IF(AND(ISNUMBER(Techniques[[#This Row],[No. of Sub Techniques]]),Techniques[[#This Row],[No. of Sub Techniques]]>1),Techniques[No. of Sub Techniques],1) -> 1 | M16: {=Techniques[[#This Row],[Min. Detection Rules]]+IF(IF(ISNUMBER(Techniques[[#This Row],[No. of Sub Techniques]]),Techniques[[#This Row],[No. of Sub Techniques]]>0,FALSE),SUM(IF(Techniques[[#This Row],[Technique]]=Techniques[Technique],Techniques[Detection Rules Modifier],0)),Techniques[[#This Row],[Detection Rules Modifier]])} -> 1 | N16: =IF(ISNUMBER(Techniques[[#This Row],[Detection Rules for Technique]]),Techniques[[#This Row],[Detection Rules for Technique]],0)+IF(ISNUMBER(Techniques[[#This Row],[Detection Rules for SubTech]]),Techniques[[#This Row],[Detection Rules for SubTech]],0) -> 0 | O16: =IF(Techniques[[#This Row],[Detection Rules]]>=Techniques[[#This Row],[Expected Detection Rules]],1,Techniques[[#This Row],[Detection Rules]]/Techniques[[#This Row],[Expected Detection Rules]]) -> 0 | P16: =IF(Techniques[[#This Row],[Expected Detection Rules]]<=0,"disabled",IF(Techniques[[#This Row],[Data Sources Available]]>0, IF(Techniques[[#This Row],[Detection Rules]]>0,"detect","no detect"),IF(Techniques[[#This Row],[Detection Rules]]>0,"inconsistent","no sources"))) -> no detect | S16: =IF(Techniques[[#This Row],[Expected Detection Rules]]<0,"expected detection rules negative!",IF(Techniques[[#This Row],[Detection Rules]]>Techniques[[#This Row],[Expected Detection Rules]],"more detection rules than expected!",IF(AND(IF(ISNUMBER(Techniques[[#This Row],[Detection Rules for Technique]]),Techniques[[#This Row],[Detection Rules for Technique]]>0,FALSE),IF(ISNUMBER(Techniques[[#This Row],[No. of Sub Techniques]]),Techniques[[#This Row],[No. of Sub Techniques]]>0,FALSE)),IF(Techniques[[#This Row],[Detection Rules for Technique]] > IF(ISNUMBER(Techniques[[#This Row],[Detection Rules Modifier]]),Techniques[[#This Row],[Detection Rules Modifier]],0), "modifier should be increased for the technique", ""),""))) | T16: Network, Windows | U16: Adversaries may directly access a volume to bypass file access controls and file system monitoring. Windows allows programs to have direct access to logical volumes. Programs with direct access may read and write files directly from the drive by analyzing file system data structures. This technique may bypass Windows file access controls as well as file system monitoring tools. (Citation: Hakobyan 2009) Utilities, such as `NinjaCopy`, exist to perform these actions in PowerShell.(Citation: Github PowerSploit Ninjacopy) Adversaries may also use built-in or third-party utilities (such as `vssadmin`, `wbadmin`, and [esentutl](https://attack.mitre.org/software/S0404)) to create shadow copies or backups of data from system volumes.(Citation: LOLBAS Esentutl) | V16: Monitor handle opens on drive volumes that are made by processes to determine when they may directly access logical drives. (Citation: Github PowerSploit Ninjacopy) Monitor processes and command-line arguments for actions that could be taken to copy files from the logical drive and evade common file system protections. Since this technique may also be used through [PowerShell](https://attack.mitre.org/techniques/T1059/001), additional logging of PowerShell scripts is recommended. | W16: FALSE
A17: T1007 | B17: T1007 | C17: System Service Discovery (T1007) | D17: Discovery | E17: Command: Command Execution, Process: OS API Execution, Process: Process Creation | F17: =LEN(E17)-LEN(SUBSTITUTE(E17,",",""))+1 -> 3 | G17: {=SUM(IF(ISERROR(FIND(Sources[Data Source],Techniques[[#This Row],[Data Sources]])),0,1)*IF(Sources[Available]="yes",1,0))} -> 1 | H17: {=IF(Techniques[[#This Row],[Technique]]=Techniques[[#This Row],[ID]],SUM(IF(Techniques[[#This Row],[ID]]=Techniques[Technique],1,0))-1,"")} -> 0 | I17: {=IF(SUM(IF($C17=Detections[],IF(Detections[Is Active]="yes",1,0),0))>0,SUM(IF($C17=Detections[],IF(Detections[Is Active]="yes",1,0),0)),"")} | J17: {=IF(IF(ISNUMBER(Techniques[[#This Row],[No. of Sub Techniques]]), Techniques[[#This Row],[No. of Sub Techniques]]>0,FALSE),SUM(IF(Techniques[[#This Row],[Technique]]=Techniques[Technique],Techniques[Detection Rules for Technique],0))-IF(ISNUMBER(Techniques[[#This Row],[Detection Rules for Technique]]),Techniques[[#This Row],[Detection Rules for Technique]],0),"")} | K17: =IF(AND(ISNUMBER(Techniques[[#This Row],[No. of Sub Techniques]]),Techniques[[#This Row],[No. of Sub Techniques]]>1),Techniques[No. of Sub Techniques],1) -> 1 | M17: {=Techniques[[#This Row],[Min. Detection Rules]]+IF(IF(ISNUMBER(Techniques[[#This Row],[No. of Sub Techniques]]),Techniques[[#This Row],[No. of Sub Techniques]]>0,FALSE),SUM(IF(Techniques[[#This Row],[Technique]]=Techniques[Technique],Techniques[Detection Rules Modifier],0)),Techniques[[#This Row],[Detection Rules Modifier]])} -> 1 | N17: =IF(ISNUMBER(Techniques[[#This Row],[Detection Rules for Technique]]),Techniques[[#This Row],[Detection Rules for Technique]],0)+IF(ISNUMBER(Techniques[[#This Row],[Detection Rules for SubTech]]),Techniques[[#This Row],[Detection Rules for SubTech]],0) -> 0 | O17: =IF(Techniques[[#This Row],[Detection Rules]]>=Techniques[[#This Row],[Expected Detection Rules]],1,Techniques[[#This Row],[Detection Rules]]/Techniques[[#This Row],[Expected Detection Rules]]) -> 0 | P17: =IF(Techniques[[#This Row],[Expected Detection Rules]]<=0,"disabled",IF(Techniques[[#This Row],[Data Sources Available]]>0, IF(Techniques[[#This Row],[Detection Rules]]>0,"detect","no detect"),IF(Techniques[[#This Row],[Detection Rules]]>0,"inconsistent","no sources"))) -> no detect | S17: =IF(Techniques[[#This Row],[Expected Detection Rules]]<0,"expected detection rules negative!",IF(Techniques[[#This Row],[Detection Rules]]>Techniques[[#This Row],[Expected Detection Rules]],"more detection rules than expected!",IF(AND(IF(ISNUMBER(Techniques[[#This Row],[Detection Rules for Technique]]),Techniques[[#This Row],[Detection Rules for Technique]]>0,FALSE),IF(ISNUMBER(Techniques[[#This Row],[No. of Sub Techniques]]),Techniques[[#This Row],[No. of Sub Techniques]]>0,FALSE)),IF(Techniques[[#This Row],[Detection Rules for Technique]] > IF(ISNUMBER(Techniques[[#This Row],[Detection Rules Modifier]]),Techniques[[#This Row],[Detection Rules Modifier]],0), "modifier should be increased for the technique", ""),""))) | T17: Linux, Windows, macOS | U17: Adversaries may try to gather information about registered local system services. Adversaries may obtain information about services using tools as well as OS utility commands such as <code>sc query</code>, <code>tasklist /svc</code>, <code>systemctl --type=service</code>, and <code>net start</code>. Adversaries may use the information from [System Service Discovery](https://attack.mitre.org/techniques/T1007) during automated discovery to shape follow-on behaviors, including whether or not the adversary fully infects the target and/or attempts specific actions. | V17: System and network discovery techniques normally occur throughout an operation as an adversary learns the environment. Data and events should not be viewed in isolation, but as part of a chain of behavior that could lead to other activities, such as Lateral Movement, based on the information obtained. Monitor processes and command-line arguments for actions that could be taken to gather system information related to services. Remote access tools with built-in features may interact directly with the Windows API to gather information. Information may also be acquired through Windows system management tools such as [Windows Management Instrumentation](https://attack.mitre.org/techniques/T1047) and [PowerShell](https://attack.mitre.org/techniques/T1059/001). | W17: FALSE
A18: T1008 | B18: T1008 | C18: Fallback Channels (T1008) | D18: Command and Control | E18: Network Traffic: Network Connection Creation, Network Traffic: Network Traffic Flow | F18: =LEN(E18)-LEN(SUBSTITUTE(E18,",",""))+1 -> 2 | G18: {=SUM(IF(ISERROR(FIND(Sources[Data Source],Techniques[[#This Row],[Data Sources]])),0,1)*IF(Sources[Available]="yes",1,0))} -> 2 | H18: {=IF(Techniques[[#This Row],[Technique]]=Techniques[[#This Row],[ID]],SUM(IF(Techniques[[#This Row],[ID]]=Techniques[Technique],1,0))-1,"")} -> 0 | I18: {=IF(SUM(IF($C18=Detections[],IF(Detections[Is Active]="yes",1,0),0))>0,SUM(IF($C18=Detections[],IF(Detections[Is Active]="yes",1,0),0)),"")} | J18: {=IF(IF(ISNUMBER(Techniques[[#This Row],[No. of Sub Techniques]]), Techniques[[#This Row],[No. of Sub Techniques]]>0,FALSE),SUM(IF(Techniques[[#This Row],[Technique]]=Techniques[Technique],Techniques[Detection Rules for Technique],0))-IF(ISNUMBER(Techniques[[#This Row],[Detection Rules for Technique]]),Techniques[[#This Row],[Detection Rules for Technique]],0),"")} | K18: =IF(AND(ISNUMBER(Techniques[[#This Row],[No. of Sub Techniques]]),Techniques[[#This Row],[No. of Sub Techniques]]>1),Techniques[No. of Sub Techniques],1) -> 1 | M18: {=Techniques[[#This Row],[Min. Detection Rules]]+IF(IF(ISNUMBER(Techniques[[#This Row],[No. of Sub Techniques]]),Techniques[[#This Row],[No. of Sub Techniques]]>0,FALSE),SUM(IF(Techniques[[#This Row],[Technique]]=Techniques[Technique],Techniques[Detection Rules Modifier],0)),Techniques[[#This Row],[Detection Rules Modifier]])} -> 1 | N18: =IF(ISNUMBER(Techniques[[#This Row],[Detection Rules for Technique]]),Techniques[[#This Row],[Detection Rules for Technique]],0)+IF(ISNUMBER(Techniques[[#This Row],[Detection Rules for SubTech]]),Techniques[[#This Row],[Detection Rules for SubTech]],0) -> 0 | O18: =IF(Techniques[[#This Row],[Detection Rules]]>=Techniques[[#This Row],[Expected Detection Rules]],1,Techniques[[#This Row],[Detection Rules]]/Techniques[[#This Row],[Expected Detection Rules]]) -> 0 | P18: =IF(Techniques[[#This Row],[Expected Detection Rules]]<=0,"disabled",IF(Techniques[[#This Row],[Data Sources Available]]>0, IF(Techniques[[#This Row],[Detection Rules]]>0,"detect","no detect"),IF(Techniques[[#This Row],[Detection Rules]]>0,"inconsistent","no sources"))) -> no detect | S18: =IF(Techniques[[#This Row],[Expected Detection Rules]]<0,"expected detection rules negative!",IF(Techniques[[#This Row],[Detection Rules]]>Techniques[[#This Row],[Expected Detection Rules]],"more detection rules than expected!",IF(AND(IF(ISNUMBER(Techniques[[#This Row],[Detection Rules for Technique]]),Techniques[[#This Row],[Detection Rules for Technique]]>0,FALSE),IF(ISNUMBER(Techniques[[#This Row],[No. of Sub Techniques]]),Techniques[[#This Row],[No. of Sub Techniques]]>0,FALSE)),IF(Techniques[[#This Row],[Detection Rules for Technique]] > IF(ISNUMBER(Techniques[[#This Row],[Detection Rules Modifier]]),Techniques[[#This Row],[Detection Rules Modifier]],0), "modifier should be increased for the technique", ""),""))) | T18: Linux, Windows, macOS | U18: Adversaries may use fallback or alternate communication channels if the primary channel is compromised or inaccessible in order to maintain reliable command and control and to avoid data transfer thresholds. | V18: Analyze network data for uncommon data flows (e.g., a client sending significantly more data than it receives from a server). Processes utilizing the network that do not normally have network communication or have never been seen before are suspicious. Analyze packet contents to detect communications that do not follow the expected protocol behavior for the port that is being used. (Citation: University of Birmingham C2) | W18: FALSE
A19: T1010 | B19: T1010 | C19: Application Window Discovery (T1010) | D19: Discovery | E19: Command: Command Execution, Process: OS API Execution, Process: Process Creation | F19: =LEN(E19)-LEN(SUBSTITUTE(E19,",",""))+1 -> 3 | G19: {=SUM(IF(ISERROR(FIND(Sources[Data Source],Techniques[[#This Row],[Data Sources]])),0,1)*IF(Sources[Available]="yes",1,0))} -> 1 | H19: {=IF(Techniques[[#This Row],[Technique]]=Techniques[[#This Row],[ID]],SUM(IF(Techniques[[#This Row],[ID]]=Techniques[Technique],1,0))-1,"")} -> 0 | I19: {=IF(SUM(IF($C19=Detections[],IF(Detections[Is Active]="yes",1,0),0))>0,SUM(IF($C19=Detections[],IF(Detections[Is Active]="yes",1,0),0)),"")} -> 1 | J19: {=IF(IF(ISNUMBER(Techniques[[#This Row],[No. of Sub Techniques]]), Techniques[[#This Row],[No. of Sub Techniques]]>0,FALSE),SUM(IF(Techniques[[#This Row],[Technique]]=Techniques[Technique],Techniques[Detection Rules for Technique],0))-IF(ISNUMBER(Techniques[[#This Row],[Detection Rules for Technique]]),Techniques[[#This Row],[Detection Rules for Technique]],0),"")} | K19: =IF(AND(ISNUMBER(Techniques[[#This Row],[No. of Sub Techniques]]),Techniques[[#This Row],[No. of Sub Techniques]]>1),Techniques[No. of Sub Techniques],1) -> 1 | M19: {=Techniques[[#This Row],[Min. Detection Rules]]+IF(IF(ISNUMBER(Techniques[[#This Row],[No. of Sub Techniques]]),Techniques[[#This Row],[No. of Sub Techniques]]>0,FALSE),SUM(IF(Techniques[[#This Row],[Technique]]=Techniques[Technique],Techniques[Detection Rules Modifier],0)),Techniques[[#This Row],[Detection Rules Modifier]])} -> 1 | N19: =IF(ISNUMBER(Techniques[[#This Row],[Detection Rules for Technique]]),Techniques[[#This Row],[Detection Rules for Technique]],0)+IF(ISNUMBER(Techniques[[#This Row],[Detection Rules for SubTech]]),Techniques[[#This Row],[Detection Rules for SubTech]],0) -> 1 | O19: =IF(Techniques[[#This Row],[Detection Rules]]>=Techniques[[#This Row],[Expected Detection Rules]],1,Techniques[[#This Row],[Detection Rules]]/Techniques[[#This Row],[Expected Detection Rules]]) -> 1 | P19: =IF(Techniques[[#This Row],[Expected Detection Rules]]<=0,"disabled",IF(Techniques[[#This Row],[Data Sources Available]]>0, IF(Techniques[[#This Row],[Detection Rules]]>0,"detect","no detect"),IF(Techniques[[#This Row],[Detection Rules]]>0,"inconsistent","no sources"))) -> detect | S19: =IF(Techniques[[#This Row],[Expected Detection Rules]]<0,"expected detection rules negative!",IF(Techniques[[#This Row],[Detection Rules]]>Techniques[[#This Row],[Expected Detection Rules]],"more detection rules than expected!",IF(AND(IF(ISNUMBER(Techniques[[#This Row],[Detection Rules for Technique]]),Techniques[[#This Row],[Detection Rules for Technique]]>0,FALSE),IF(ISNUMBER(Techniques[[#This Row],[No. of Sub Techniques]]),Techniques[[#This Row],[No. of Sub Techniques]]>0,FALSE)),IF(Techniques[[#This Row],[Detection Rules for Technique]] > IF(ISNUMBER(Techniques[[#This Row],[Detection Rules Modifier]]),Techniques[[#This Row],[Detection Rules Modifier]],0), "modifier should be increased for the technique", ""),""))) | T19: Linux, Windows, macOS | U19: Adversaries may attempt to get a listing of open application windows. Window listings could convey information about how the system is used.(Citation: Prevailion DarkWatchman 2021) For example, information about application windows could be used identify potential data to collect as well as identifying security tooling ([Security Software Discovery](https://attack.mitre.org/techniques/T1518/001)) to evade.(Citation: ESET Grandoreiro April 2020) Adversaries typically abuse system features for this type of enumeration. For example, they may gather information through native system features such as [Command and Scripting Interpreter](https://attack.mitre.org/techniques/T1059) commands and [Native API](https://attack.mitre.org/techniques/T1106) functions. | V19: System and network discovery techniques normally occur throughout an operation as an adversary learns the environment. Data and events should not be viewed in isolation, but as part of a chain of behavior that could lead to other activities based on the information obtained. Monitor processes and command-line arguments for actions that could be taken to gather system and network information. Remote access tools with built-in features may interact directly with the Windows API to gather information. Information may also be acquired through Windows system management tools such as [Windows Management Instrumentation](https://attack.mitre.org/techniques/T1047) and [PowerShell](https://attack.mitre.org/techniques/T1059/001). | W19: FALSE
A20: T1011 | B20: T1011 | C20: Exfiltration Over Other Network Medium (T1011) | D20: Exfiltration | E20: Command: Command Execution, File: File Access, Network Traffic: Network Connection Creation, Network Traffic: Network Traffic Content, Network Traffic: Network Traffic Flow | F20: =LEN(E20)-LEN(SUBSTITUTE(E20,",",""))+1 -> 5 | G20: {=SUM(IF(ISERROR(FIND(Sources[Data Source],Techniques[[#This Row],[Data Sources]])),0,1)*IF(Sources[Available]="yes",1,0))} -> 4 | H20: {=IF(Techniques[[#This Row],[Technique]]=Techniques[[#This Row],[ID]],SUM(IF(Techniques[[#This Row],[ID]]=Techniques[Technique],1,0))-1,"")} -> 1 | I20: {=IF(SUM(IF($C20=Detections[],IF(Detections[Is Active]="yes",1,0),0))>0,SUM(IF($C20=Detections[],IF(Detections[Is Active]="yes",1,0),0)),"")} | J20: {=IF(IF(ISNUMBER(Techniques[[#This Row],[No. of Sub Techniques]]), Techniques[[#This Row],[No. of Sub Techniques]]>0,FALSE),SUM(IF(Techniques[[#This Row],[Technique]]=Techniques[Technique],Techniques[Detection Rules for Technique],0))-IF(ISNUMBER(Techniques[[#This Row],[Detection Rules for Technique]]),Techniques[[#This Row],[Detection Rules for Technique]],0),"")} -> 0 | K20: =IF(AND(ISNUMBER(Techniques[[#This Row],[No. of Sub Techniques]]),Techniques[[#This Row],[No. of Sub Techniques]]>1),Techniques[No. of Sub Techniques],1) -> 1 | M20: {=Techniques[[#This Row],[Min. Detection Rules]]+IF(IF(ISNUMBER(Techniques[[#This Row],[No. of Sub Techniques]]),Techniques[[#This Row],[No. of Sub Techniques]]>0,FALSE),SUM(IF(Techniques[[#This Row],[Technique]]=Techniques[Technique],Techniques[Detection Rules Modifier],0)),Techniques[[#This Row],[Detection Rules Modifier]])} -> 1 | N20: =IF(ISNUMBER(Techniques[[#This Row],[Detection Rules for Technique]]),Techniques[[#This Row],[Detection Rules for Technique]],0)+IF(ISNUMBER(Techniques[[#This Row],[Detection Rules for SubTech]]),Techniques[[#This Row],[Detection Rules for SubTech]],0) -> 0 | O20: =IF(Techniques[[#This Row],[Detection Rules]]>=Techniques[[#This Row],[Expected Detection Rules]],1,Techniques[[#This Row],[Detection Rules]]/Techniques[[#This Row],[Expected Detection Rules]]) -> 0 | P20: =IF(Techniques[[#This Row],[Expected Detection Rules]]<=0,"disabled",IF(Techniques[[#This Row],[Data Sources Available]]>0, IF(Techniques[[#This Row],[Detection Rules]]>0,"detect","no detect"),IF(Techniques[[#This Row],[Detection Rules]]>0,"inconsistent","no sources"))) -> no detect | S20: =IF(Techniques[[#This Row],[Expected Detection Rules]]<0,"expected detection rules negative!",IF(Techniques[[#This Row],[Detection Rules]]>Techniques[[#This Row],[Expected Detection Rules]],"more detection rules than expected!",IF(AND(IF(ISNUMBER(Techniques[[#This Row],[Detection Rules for Technique]]),Techniques[[#This Row],[Detection Rules for Technique]]>0,FALSE),IF(ISNUMBER(Techniques[[#This Row],[No. of Sub Techniques]]),Techniques[[#This Row],[No. of Sub Techniques]]>0,FALSE)),IF(Techniques[[#This Row],[Detection Rules for Technique]] > IF(ISNUMBER(Techniques[[#This Row],[Detection Rules Modifier]]),Techniques[[#This Row],[Detection Rules Modifier]],0), "modifier should be increased for the technique", ""),""))) | T20: Linux, Windows, macOS | U20: Adversaries may attempt to exfiltrate data over a different network medium than the command and control channel. If the command and control network is a wired Internet connection, the exfiltration may occur, for example, over a WiFi connection, modem, cellular data connection, Bluetooth, or another radio frequency (RF) channel. Adversaries may choose to do this if they have sufficient access or proximity, and the connection might not be secured or defended as well as the primary Internet-connected channel because it is not routed through the same enterprise network. | V20: Monitor for processes utilizing the network that do not normally have network communication or have never been seen before. Processes that normally require user-driven events to access the network (for example, a web browser opening with a mouse click or key press) but access the network without such may be malicious. Monitor for and investigate changes to host adapter settings, such as addition and/or replication of communication interfaces. | W20: FALSE
A21: T1011 | B21: T1011.001 | C21: Exfiltration Over Bluetooth (T1011.001) | D21: Exfiltration | E21: Command: Command Execution, File: File Access, Network Traffic: Network Connection Creation, Network Traffic: Network Traffic Content, Network Traffic: Network Traffic Flow | F21: =LEN(E21)-LEN(SUBSTITUTE(E21,",",""))+1 -> 5 | G21: {=SUM(IF(ISERROR(FIND(Sources[Data Source],Techniques[[#This Row],[Data Sources]])),0,1)*IF(Sources[Available]="yes",1,0))} -> 4 | H21: {=IF(Techniques[[#This Row],[Technique]]=Techniques[[#This Row],[ID]],SUM(IF(Techniques[[#This Row],[ID]]=Techniques[Technique],1,0))-1,"")} | I21: {=IF(SUM(IF($C21=Detections[],IF(Detections[Is Active]="yes",1,0),0))>0,SUM(IF($C21=Detections[],IF(Detections[Is Active]="yes",1,0),0)),"")} | J21: {=IF(IF(ISNUMBER(Techniques[[#This Row],[No. of Sub Techniques]]), Techniques[[#This Row],[No. of Sub Techniques]]>0,FALSE),SUM(IF(Techniques[[#This Row],[Technique]]=Techniques[Technique],Techniques[Detection Rules for Technique],0))-IF(ISNUMBER(Techniques[[#This Row],[Detection Rules for Technique]]),Techniques[[#This Row],[Detection Rules for Technique]],0),"")} | K21: =IF(AND(ISNUMBER(Techniques[[#This Row],[No. of Sub Techniques]]),Techniques[[#This Row],[No. of Sub Techniques]]>1),Techniques[No. of Sub Techniques],1) -> 1 | M21: {=Techniques[[#This Row],[Min. Detection Rules]]+IF(IF(ISNUMBER(Techniques[[#This Row],[No. of Sub Techniques]]),Techniques[[#This Row],[No. of Sub Techniques]]>0,FALSE),SUM(IF(Techniques[[#This Row],[Technique]]=Techniques[Technique],Techniques[Detection Rules Modifier],0)),Techniques[[#This Row],[Detection Rules Modifier]])} -> 1 | N21: =IF(ISNUMBER(Techniques[[#This Row],[Detection Rules for Technique]]),Techniques[[#This Row],[Detection Rules for Technique]],0)+IF(ISNUMBER(Techniques[[#This Row],[Detection Rules for SubTech]]),Techniques[[#This Row],[Detection Rules for SubTech]],0) -> 0 | O21: =IF(Techniques[[#This Row],[Detection Rules]]>=Techniques[[#This Row],[Expected Detection Rules]],1,Techniques[[#This Row],[Detection Rules]]/Techniques[[#This Row],[Expected Detection Rules]]) -> 0 | P21: =IF(Techniques[[#This Row],[Expected Detection Rules]]<=0,"disabled",IF(Techniques[[#This Row],[Data Sources Available]]>0, IF(Techniques[[#This Row],[Detection Rules]]>0,"detect","no detect"),IF(Techniques[[#This Row],[Detection Rules]]>0,"inconsistent","no sources"))) -> no detect | S21: =IF(Techniques[[#This Row],[Expected Detection Rules]]<0,"expected detection rules negative!",IF(Techniques[[#This Row],[Detection Rules]]>Techniques[[#This Row],[Expected Detection Rules]],"more detection rules than expected!",IF(AND(IF(ISNUMBER(Techniques[[#This Row],[Detection Rules for Technique]]),Techniques[[#This Row],[Detection Rules for Technique]]>0,FALSE),IF(ISNUMBER(Techniques[[#This Row],[No. of Sub Techniques]]),Techniques[[#This Row],[No. of Sub Techniques]]>0,FALSE)),IF(Techniques[[#This Row],[Detection Rules for Technique]] > IF(ISNUMBER(Techniques[[#This Row],[Detection Rules Modifier]]),Techniques[[#This Row],[Detection Rules Modifier]],0), "modifier should be increased for the technique", ""),""))) | T21: Linux, Windows, macOS | U21: Adversaries may attempt to exfiltrate data over Bluetooth rather than the command and control channel. If the command and control network is a wired Internet connection, an adversary may opt to exfiltrate data using a Bluetooth communication channel. Adversaries may choose to do this if they have sufficient access and proximity. Bluetooth connections might not be secured or defended as well as the primary Internet-connected channel because it is not routed through the same enterprise network. | V21: Monitor for processes utilizing the network that do not normally have network communication or have never been seen before. Processes that normally require user-driven events to access the network (for example, a web browser opening with a mouse click or key press) but access the network without such may be malicious. Monitor for and investigate changes to host adapter settings, such as addition and/or replication of communication interfaces. | W21: TRUE | X21: T1011
A22: T1012 | B22: T1012 | C22: Query Registry (T1012) | D22: Discovery | E22: Command: Command Execution, Process: OS API Execution, Process: Process Creation, Windows Registry: Windows Registry Key Access | F22: =LEN(E22)-LEN(SUBSTITUTE(E22,",",""))+1 -> 4 | G22: {=SUM(IF(ISERROR(FIND(Sources[Data Source],Techniques[[#This Row],[Data Sources]])),0,1)*IF(Sources[Available]="yes",1,0))} -> 1 | H22: {=IF(Techniques[[#This Row],[Technique]]=Techniques[[#This Row],[ID]],SUM(IF(Techniques[[#This Row],[ID]]=Techniques[Technique],1,0))-1,"")} -> 0 | I22: {=IF(SUM(IF($C22=Detections[],IF(Detections[Is Active]="yes",1,0),0))>0,SUM(IF($C22=Detections[],IF(Detections[Is Active]="yes",1,0),0)),"")} | J22: {=IF(IF(ISNUMBER(Techniques[[#This Row],[No. of Sub Techniques]]), Techniques[[#This Row],[No. of Sub Techniques]]>0,FALSE),SUM(IF(Techniques[[#This Row],[Technique]]=Techniques[Technique],Techniques[Detection Rules for Technique],0))-IF(ISNUMBER(Techniques[[#This Row],[Detection Rules for Technique]]),Techniques[[#This Row],[Detection Rules for Technique]],0),"")} | K22: =IF(AND(ISNUMBER(Techniques[[#This Row],[No. of Sub Techniques]]),Techniques[[#This Row],[No. of Sub Techniques]]>1),Techniques[No. of Sub Techniques],1) -> 1 | M22: {=Techniques[[#This Row],[Min. Detection Rules]]+IF(IF(ISNUMBER(Techniques[[#This Row],[No. of Sub Techniques]]),Techniques[[#This Row],[No. of Sub Techniques]]>0,FALSE),SUM(IF(Techniques[[#This Row],[Technique]]=Techniques[Technique],Techniques[Detection Rules Modifier],0)),Techniques[[#This Row],[Detection Rules Modifier]])} -> 1 | N22: =IF(ISNUMBER(Techniques[[#This Row],[Detection Rules for Technique]]),Techniques[[#This Row],[Detection Rules for Technique]],0)+IF(ISNUMBER(Techniques[[#This Row],[Detection Rules for SubTech]]),Techniques[[#This Row],[Detection Rules for SubTech]],0) -> 0 | O22: =IF(Techniques[[#This Row],[Detection Rules]]>=Techniques[[#This Row],[Expected Detection Rules]],1,Techniques[[#This Row],[Detection Rules]]/Techniques[[#This Row],[Expected Detection Rules]]) -> 0 | P22: =IF(Techniques[[#This Row],[Expected Detection Rules]]<=0,"disabled",IF(Techniques[[#This Row],[Data Sources Available]]>0, IF(Techniques[[#This Row],[Detection Rules]]>0,"detect","no detect"),IF(Techniques[[#This Row],[Detection Rules]]>0,"inconsistent","no sources"))) -> no detect | S22: =IF(Techniques[[#This Row],[Expected Detection Rules]]<0,"expected detection rules negative!",IF(Techniques[[#This Row],[Detection Rules]]>Techniques[[#This Row],[Expected Detection Rules]],"more detection rules than expected!",IF(AND(IF(ISNUMBER(Techniques[[#This Row],[Detection Rules for Technique]]),Techniques[[#This Row],[Detection Rules for Technique]]>0,FALSE),IF(ISNUMBER(Techniques[[#This Row],[No. of Sub Techniques]]),Techniques[[#This Row],[No. of Sub Techniques]]>0,FALSE)),IF(Techniques[[#This Row],[Detection Rules for Technique]] > IF(ISNUMBER(Techniques[[#This Row],[Detection Rules Modifier]]),Techniques[[#This Row],[Detection Rules Modifier]],0), "modifier should be increased for the technique", ""),""))) | T22: Windows | U22: Adversaries may interact with the Windows Registry to gather information about the system, configuration, and installed software. The Registry contains a significant amount of information about the operating system, configuration, software, and security.(Citation: Wikipedia Windows Registry) Information can easily be queried using the [Reg](https://attack.mitre.org/software/S0075) utility, though other means to access the Registry exist. Some of the information may help adversaries to further their operation within a network. Adversaries may use the information from [Query Registry](https://attack.mitre.org/techniques/T1012) during automated discovery to shape follow-on behaviors, including whether or not the adversary fully infects the target and/or attempts specific actions. | V22: System and network discovery techniques normally occur throughout an operation as an adversary learns the environment. Data and events should not be viewed in isolation, but as part of a chain of behavior that could lead to other activities, such as Lateral Movement, based on the information obtained. Interaction with the Windows Registry may come from the command line using utilities such as [Reg](https://attack.mitre.org/software/S0075) or through running malware that may interact with the Registry through an API. Command-line invocation of utilities used to query the Registry may be detected through process and command-line monitoring. Remote access tools with built-in features may interact directly with the Windows API to gather information. Information may also be acquired through Windows system management tools such as [Windows Management Instrumentation](https://attack.mitre.org/techniques/T1047) and [PowerShell](https://attack.mitre.org/techniques/T1059/001). | W22: FALSE
A23: T1014 | B23: T1014 | C23: Rootkit (T1014) | D23: Defense Evasion | E23: Drive: Drive Modification, File: File Modification, Firmware: Firmware Modification | F23: =LEN(E23)-LEN(SUBSTITUTE(E23,",",""))+1 -> 3 | G23: {=SUM(IF(ISERROR(FIND(Sources[Data Source],Techniques[[#This Row],[Data Sources]])),0,1)*IF(Sources[Available]="yes",1,0))} -> 1 | H23: {=IF(Techniques[[#This Row],[Technique]]=Techniques[[#This Row],[ID]],SUM(IF(Techniques[[#This Row],[ID]]=Techniques[Technique],1,0))-1,"")} -> 0 | I23: {=IF(SUM(IF($C23=Detections[],IF(Detections[Is Active]="yes",1,0),0))>0,SUM(IF($C23=Detections[],IF(Detections[Is Active]="yes",1,0),0)),"")} -> 2 | J23: {=IF(IF(ISNUMBER(Techniques[[#This Row],[No. of Sub Techniques]]), Techniques[[#This Row],[No. of Sub Techniques]]>0,FALSE),SUM(IF(Techniques[[#This Row],[Technique]]=Techniques[Technique],Techniques[Detection Rules for Technique],0))-IF(ISNUMBER(Techniques[[#This Row],[Detection Rules for Technique]]),Techniques[[#This Row],[Detection Rules for Technique]],0),"")} | K23: =IF(AND(ISNUMBER(Techniques[[#This Row],[No. of Sub Techniques]]),Techniques[[#This Row],[No. of Sub Techniques]]>1),Techniques[No. of Sub Techniques],1) -> 1 | M23: {=Techniques[[#This Row],[Min. Detection Rules]]+IF(IF(ISNUMBER(Techniques[[#This Row],[No. of Sub Techniques]]),Techniques[[#This Row],[No. of Sub Techniques]]>0,FALSE),SUM(IF(Techniques[[#This Row],[Technique]]=Techniques[Technique],Techniques[Detection Rules Modifier],0)),Techniques[[#This Row],[Detection Rules Modifier]])} -> 1 | N23: =IF(ISNUMBER(Techniques[[#This Row],[Detection Rules for Technique]]),Techniques[[#This Row],[Detection Rules for Technique]],0)+IF(ISNUMBER(Techniques[[#This Row],[Detection Rules for SubTech]]),Techniques[[#This Row],[Detection Rules for SubTech]],0) -> 2 | O23: =IF(Techniques[[#This Row],[Detection Rules]]>=Techniques[[#This Row],[Expected Detection Rules]],1,Techniques[[#This Row],[Detection Rules]]/Techniques[[#This Row],[Expected Detection Rules]]) -> 1 | P23: =IF(Techniques[[#This Row],[Expected Detection Rules]]<=0,"disabled",IF(Techniques[[#This Row],[Data Sources Available]]>0, IF(Techniques[[#This Row],[Detection Rules]]>0,"detect","no detect"),IF(Techniques[[#This Row],[Detection Rules]]>0,"inconsistent","no sources"))) -> detect | S23: =IF(Techniques[[#This Row],[Expected Detection Rules]]<0,"expected detection rules negative!",IF(Techniques[[#This Row],[Detection Rules]]>Techniques[[#This Row],[Expected Detection Rules]],"more detection rules than expected!",IF(AND(IF(ISNUMBER(Techniques[[#This Row],[Detection Rules for Technique]]),Techniques[[#This Row],[Detection Rules for Technique]]>0,FALSE),IF(ISNUMBER(Techniques[[#This Row],[No. of Sub Techniques]]),Techniques[[#This Row],[No. of Sub Techniques]]>0,FALSE)),IF(Techniques[[#This Row],[Detection Rules for Technique]] > IF(ISNUMBER(Techniques[[#This Row],[Detection Rules Modifier]]),Techniques[[#This Row],[Detection Rules Modifier]],0), "modifier should be increased for the technique", ""),""))) -> more detection rules than expected! | T23: Linux, Windows, macOS | U23: Adversaries may use rootkits to hide the presence of programs, files, network connections, services, drivers, and other system components. Rootkits are programs that hide the existence of malware by intercepting/hooking and modifying operating system API calls that supply system information. (Citation: Symantec Windows Rootkits) Rootkits or rootkit enabling functionality may reside at the user or kernel level in the operating system or lower, to include a hypervisor, Master Boot Record, or [System Firmware](https://attack.mitre.org/techniques/T1542/001). (Citation: Wikipedia Rootkit) Rootkits have been seen for Windows, Linux, and Mac OS X systems. (Citation: CrowdStrike Linux Rootkit) (Citation: BlackHat Mac OSX Rootkit) | V23: Some rootkit protections may be built into anti-virus or operating system software. There are dedicated rootkit detection tools that look for specific types of rootkit behavior. Monitor for the existence of unrecognized DLLs, devices, services, and changes to the MBR. (Citation: Wikipedia Rootkit) | W23: FALSE
A24: T1016 | B24: T1016 | C24: System Network Configuration Discovery (T1016) | D24: Discovery | E24: Command: Command Execution, Process: OS API Execution, Process: Process Creation, Script: Script Execution | F24: =LEN(E24)-LEN(SUBSTITUTE(E24,",",""))+1 -> 4 | G24: {=SUM(IF(ISERROR(FIND(Sources[Data Source],Techniques[[#This Row],[Data Sources]])),0,1)*IF(Sources[Available]="yes",1,0))} -> 1 | H24: {=IF(Techniques[[#This Row],[Technique]]=Techniques[[#This Row],[ID]],SUM(IF(Techniques[[#This Row],[ID]]=Techniques[Technique],1,0))-1,"")} -> 2 | I24: {=IF(SUM(IF($C24=Detections[],IF(Detections[Is Active]="yes",1,0),0))>0,SUM(IF($C24=Detections[],IF(Detections[Is Active]="yes",1,0),0)),"")} | J24: {=IF(IF(ISNUMBER(Techniques[[#This Row],[No. of Sub Techniques]]), Techniques[[#This Row],[No. of Sub Techniques]]>0,FALSE),SUM(IF(Techniques[[#This Row],[Technique]]=Techniques[Technique],Techniques[Detection Rules for Technique],0))-IF(ISNUMBER(Techniques[[#This Row],[Detection Rules for Technique]]),Techniques[[#This Row],[Detection Rules for Technique]],0),"")} -> 1 | K24: =IF(AND(ISNUMBER(Techniques[[#This Row],[No. of Sub Techniques]]),Techniques[[#This Row],[No. of Sub Techniques]]>1),Techniques[No. of Sub Techniques],1) -> 2 | M24: {=Techniques[[#This Row],[Min. Detection Rules]]+IF(IF(ISNUMBER(Techniques[[#This Row],[No. of Sub Techniques]]),Techniques[[#This Row],[No. of Sub Techniques]]>0,FALSE),SUM(IF(Techniques[[#This Row],[Technique]]=Techniques[Technique],Techniques[Detection Rules Modifier],0)),Techniques[[#This Row],[Detection Rules Modifier]])} -> 2 | N24: =IF(ISNUMBER(Techniques[[#This Row],[Detection Rules for Technique]]),Techniques[[#This Row],[Detection Rules for Technique]],0)+IF(ISNUMBER(Techniques[[#This Row],[Detection Rules for SubTech]]),Techniques[[#This Row],[Detection Rules for SubTech]],0) -> 1 | O24: =IF(Techniques[[#This Row],[Detection Rules]]>=Techniques[[#This Row],[Expected Detection Rules]],1,Techniques[[#This Row],[Detection Rules]]/Techniques[[#This Row],[Expected Detection Rules]]) -> 0.5 | P24: =IF(Techniques[[#This Row],[Expected Detection Rules]]<=0,"disabled",IF(Techniques[[#This Row],[Data Sources Available]]>0, IF(Techniques[[#This Row],[Detection Rules]]>0,"detect","no detect"),IF(Techniques[[#This Row],[Detection Rules]]>0,"inconsistent","no sources"))) -> detect | S24: =IF(Techniques[[#This Row],[Expected Detection Rules]]<0,"expected detection rules negative!",IF(Techniques[[#This Row],[Detection Rules]]>Techniques[[#This Row],[Expected Detection Rules]],"more detection rules than expected!",IF(AND(IF(ISNUMBER(Techniques[[#This Row],[Detection Rules for Technique]]),Techniques[[#This Row],[Detection Rules for Technique]]>0,FALSE),IF(ISNUMBER(Techniques[[#This Row],[No. of Sub Techniques]]),Techniques[[#This Row],[No. of Sub Techniques]]>0,FALSE)),IF(Techniques[[#This Row],[Detection Rules for Technique]] > IF(ISNUMBER(Techniques[[#This Row],[Detection Rules Modifier]]),Techniques[[#This Row],[Detection Rules Modifier]],0), "modifier should be increased for the technique", ""),""))) | T24: Linux, Network, Windows, macOS | U24: Adversaries may look for details about the network configuration and settings, such as IP and/or MAC addresses, of systems they access or through information discovery of remote systems. Several operating system administration utilities exist that can be used to gather this information. Examples include [Arp](https://attack.mitre.org/software/S0099), [ipconfig](https://attack.mitre.org/software/S0100)/[ifconfig](https://attack.mitre.org/software/S0101), [nbtstat](https://attack.mitre.org/software/S0102), and [route](https://attack.mitre.org/software/S0103). Adversaries may also leverage a [Network Device CLI](https://attack.mitre.org/techniques/T1059/008) on network devices to gather information about configurations and settings, such as IP addresses of configured interfaces and static/dynamic routes (e.g. <code>show ip route</code>, <code>show ip interface</code>).(Citation: US-CERT-TA18-106A)(Citation: Mandiant APT41 Global Intrusion ) Adversaries may use the information from [System Network Configuration Discovery](https://attack.mitre.org/techniques/T1016) during automated discovery to shape follow-on behaviors, including determining certain access within the target network and what actions to do next. | V24: System and network discovery techniques normally occur throughout an operation as an adversary learns the environment. Data and events should not be viewed in isolation, but as part of a chain of behavior that could lead to other activities, such as Lateral Movement, based on the information obtained. Monitor processes and command-line arguments for actions that could be taken to gather system and network information. Remote access tools with built-in features may interact directly with the Windows API to gather information. Further, {{LinkById|T1059.008} commands may also be used to gather system and network information with built-in features native to the network device platform. Monitor CLI activity for unexpected or unauthorized use commands being run by non-standard users from non-standard locations. Information may also be acquired through Windows system management tools such as [Windows Management Instrumentation](https://attack.mitre.org/techniques/T1047) and [PowerShell](https://attack.mitre.org/techniques/T1059/001). | W24: FALSE
A25: T1016 | B25: T1016.001 | C25: Internet Connection Discovery (T1016.001) | D25: Discovery | E25: Command: Command Execution, Process: Process Creation | F25: =LEN(E25)-LEN(SUBSTITUTE(E25,",",""))+1 -> 2 | G25: {=SUM(IF(ISERROR(FIND(Sources[Data Source],Techniques[[#This Row],[Data Sources]])),0,1)*IF(Sources[Available]="yes",1,0))} -> 1 | H25: {=IF(Techniques[[#This Row],[Technique]]=Techniques[[#This Row],[ID]],SUM(IF(Techniques[[#This Row],[ID]]=Techniques[Technique],1,0))-1,"")} | I25: {=IF(SUM(IF($C25=Detections[],IF(Detections[Is Active]="yes",1,0),0))>0,SUM(IF($C25=Detections[],IF(Detections[Is Active]="yes",1,0),0)),"")} -> 1 | J25: {=IF(IF(ISNUMBER(Techniques[[#This Row],[No. of Sub Techniques]]), Techniques[[#This Row],[No. of Sub Techniques]]>0,FALSE),SUM(IF(Techniques[[#This Row],[Technique]]=Techniques[Technique],Techniques[Detection Rules for Technique],0))-IF(ISNUMBER(Techniques[[#This Row],[Detection Rules for Technique]]),Techniques[[#This Row],[Detection Rules for Technique]],0),"")} | K25: =IF(AND(ISNUMBER(Techniques[[#This Row],[No. of Sub Techniques]]),Techniques[[#This Row],[No. of Sub Techniques]]>1),Techniques[No. of Sub Techniques],1) -> 1 | M25: {=Techniques[[#This Row],[Min. Detection Rules]]+IF(IF(ISNUMBER(Techniques[[#This Row],[No. of Sub Techniques]]),Techniques[[#This Row],[No. of Sub Techniques]]>0,FALSE),SUM(IF(Techniques[[#This Row],[Technique]]=Techniques[Technique],Techniques[Detection Rules Modifier],0)),Techniques[[#This Row],[Detection Rules Modifier]])} -> 1 | N25: =IF(ISNUMBER(Techniques[[#This Row],[Detection Rules for Technique]]),Techniques[[#This Row],[Detection Rules for Technique]],0)+IF(ISNUMBER(Techniques[[#This Row],[Detection Rules for SubTech]]),Techniques[[#This Row],[Detection Rules for SubTech]],0) -> 1 | O25: =IF(Techniques[[#This Row],[Detection Rules]]>=Techniques[[#This Row],[Expected Detection Rules]],1,Techniques[[#This Row],[Detection Rules]]/Techniques[[#This Row],[Expected Detection Rules]]) -> 1 | P25: =IF(Techniques[[#This Row],[Expected Detection Rules]]<=0,"disabled",IF(Techniques[[#This Row],[Data Sources Available]]>0, IF(Techniques[[#This Row],[Detection Rules]]>0,"detect","no detect"),IF(Techniques[[#This Row],[Detection Rules]]>0,"inconsistent","no sources"))) -> detect | S25: =IF(Techniques[[#This Row],[Expected Detection Rules]]<0,"expected detection rules negative!",IF(Techniques[[#This Row],[Detection Rules]]>Techniques[[#This Row],[Expected Detection Rules]],"more detection rules than expected!",IF(AND(IF(ISNUMBER(Techniques[[#This Row],[Detection Rules for Technique]]),Techniques[[#This Row],[Detection Rules for Technique]]>0,FALSE),IF(ISNUMBER(Techniques[[#This Row],[No. of Sub Techniques]]),Techniques[[#This Row],[No. of Sub Techniques]]>0,FALSE)),IF(Techniques[[#This Row],[Detection Rules for Technique]] > IF(ISNUMBER(Techniques[[#This Row],[Detection Rules Modifier]]),Techniques[[#This Row],[Detection Rules Modifier]],0), "modifier should be increased for the technique", ""),""))) | T25: Linux, Windows, macOS | U25: Adversaries may check for Internet connectivity on compromised systems. This may be performed during automated discovery and can be accomplished in numerous ways such as using [Ping](https://attack.mitre.org/software/S0097), <code>tracert</code>, and GET requests to websites. Adversaries may use the results and responses from these requests to determine if the system is capable of communicating with their C2 servers before attempting to connect to them. The results may also be used to identify routes, redirectors, and proxy servers. | V25: System and network discovery techniques normally occur throughout an operation as an adversary learns the environment. Data and events should not be viewed in isolation, but as part of a chain of behavior that could lead to other activities, such as Command and Control, based on the information obtained. Monitor processes and command-line arguments for actions that could be taken to check Internet connectivity. | W25: TRUE | X25: T1016
A26: T1016 | B26: T1016.002 | C26: Wi-Fi Discovery (T1016.002) | D26: Discovery | E26: Command: Command Execution, Process: OS API Execution | F26: =LEN(E26)-LEN(SUBSTITUTE(E26,",",""))+1 -> 2 | G26: {=SUM(IF(ISERROR(FIND(Sources[Data Source],Techniques[[#This Row],[Data Sources]])),0,1)*IF(Sources[Available]="yes",1,0))} -> 1 | H26: {=IF(Techniques[[#This Row],[Technique]]=Techniques[[#This Row],[ID]],SUM(IF(Techniques[[#This Row],[ID]]=Techniques[Technique],1,0))-1,"")} | I26: {=IF(SUM(IF($C26=Detections[],IF(Detections[Is Active]="yes",1,0),0))>0,SUM(IF($C26=Detections[],IF(Detections[Is Active]="yes",1,0),0)),"")} | J26: {=IF(IF(ISNUMBER(Techniques[[#This Row],[No. of Sub Techniques]]), Techniques[[#This Row],[No. of Sub Techniques]]>0,FALSE),SUM(IF(Techniques[[#This Row],[Technique]]=Techniques[Technique],Techniques[Detection Rules for Technique],0))-IF(ISNUMBER(Techniques[[#This Row],[Detection Rules for Technique]]),Techniques[[#This Row],[Detection Rules for Technique]],0),"")} | K26: =IF(AND(ISNUMBER(Techniques[[#This Row],[No. of Sub Techniques]]),Techniques[[#This Row],[No. of Sub Techniques]]>1),Techniques[No. of Sub Techniques],1) -> 1 | M26: {=Techniques[[#This Row],[Min. Detection Rules]]+IF(IF(ISNUMBER(Techniques[[#This Row],[No. of Sub Techniques]]),Techniques[[#This Row],[No. of Sub Techniques]]>0,FALSE),SUM(IF(Techniques[[#This Row],[Technique]]=Techniques[Technique],Techniques[Detection Rules Modifier],0)),Techniques[[#This Row],[Detection Rules Modifier]])} -> 1 | N26: =IF(ISNUMBER(Techniques[[#This Row],[Detection Rules for Technique]]),Techniques[[#This Row],[Detection Rules for Technique]],0)+IF(ISNUMBER(Techniques[[#This Row],[Detection Rules for SubTech]]),Techniques[[#This Row],[Detection Rules for SubTech]],0) -> 0 | O26: =IF(Techniques[[#This Row],[Detection Rules]]>=Techniques[[#This Row],[Expected Detection Rules]],1,Techniques[[#This Row],[Detection Rules]]/Techniques[[#This Row],[Expected Detection Rules]]) -> 0 | P26: =IF(Techniques[[#This Row],[Expected Detection Rules]]<=0,"disabled",IF(Techniques[[#This Row],[Data Sources Available]]>0, IF(Techniques[[#This Row],[Detection Rules]]>0,"detect","no detect"),IF(Techniques[[#This Row],[Detection Rules]]>0,"inconsistent","no sources"))) -> no detect | S26: =IF(Techniques[[#This Row],[Expected Detection Rules]]<0,"expected detection rules negative!",IF(Techniques[[#This Row],[Detection Rules]]>Techniques[[#This Row],[Expected Detection Rules]],"more detection rules than expected!",IF(AND(IF(ISNUMBER(Techniques[[#This Row],[Detection Rules for Technique]]),Techniques[[#This Row],[Detection Rules for Technique]]>0,FALSE),IF(ISNUMBER(Techniques[[#This Row],[No. of Sub Techniques]]),Techniques[[#This Row],[No. of Sub Techniques]]>0,FALSE)),IF(Techniques[[#This Row],[Detection Rules for Technique]] > IF(ISNUMBER(Techniques[[#This Row],[Detection Rules Modifier]]),Techniques[[#This Row],[Detection Rules Modifier]],0), "modifier should be increased for the technique", ""),""))) | T26: Linux, Windows, macOS | U26: Adversaries may search for information about Wi-Fi networks, such as network names and passwords, on compromised systems. Adversaries may use Wi-Fi information as part of [Account Discovery](https://attack.mitre.org/techniques/T1087), [Remote System Discovery](https://attack.mitre.org/techniques/T1018), and other discovery or [Credential Access](https://attack.mitre.org/tactics/TA0006) activity to support both ongoing and future campaigns. Adversaries may collect various types of information about Wi-Fi networks from hosts. For example, on Windows names and passwords of all Wi-Fi networks a device has previously connected to may be available through `netsh wlan show profiles` to enumerate Wi-Fi names and then `netsh wlan show profile “Wi-Fi name” key=clear` to show a Wi-Fi network’s corresponding password.(Citation: BleepingComputer Agent Tesla steal wifi passwords)(Citation: Malware Bytes New AgentTesla variant steals WiFi credentials)(Citation: Check Point APT35 CharmPower January 2022) Additionally, names and other details of locally reachable Wi-Fi networks can be discovered using calls to `wlanAPI.dll` [Native API](https://attack.mitre.org/techniques/T1106) functions.(Citation: Binary Defense Emotes Wi-Fi Spreader) On Linux, names and passwords of all Wi-Fi-networks a device has previously connected to may be available in files under ` /etc/NetworkManager/system-connections/`.(Citation: Wi-Fi Password of All Connected Networks in Windows/Linux) On macOS, the password of a known Wi-Fi may be identified with ` security find-generic-password -wa wifiname` (requires admin username/password).(Citation: Find Wi-Fi Password on Mac) | V26: This type of attack technique cannot be easily mitigated with preventive controls since it is based on the abuse of system features. | W26: TRUE | X26: T1016
A27: T1018 | B27: T1018 | C27: Remote System Discovery (T1018) | D27: Discovery | E27: Command: Command Execution, File: File Access, Network Traffic: Network Connection Creation, Process: Process Creation | F27: =LEN(E27)-LEN(SUBSTITUTE(E27,",",""))+1 -> 4 | G27: {=SUM(IF(ISERROR(FIND(Sources[Data Source],Techniques[[#This Row],[Data Sources]])),0,1)*IF(Sources[Available]="yes",1,0))} -> 2 | H27: {=IF(Techniques[[#This Row],[Technique]]=Techniques[[#This Row],[ID]],SUM(IF(Techniques[[#This Row],[ID]]=Techniques[Technique],1,0))-1,"")} -> 0 | I27: {=IF(SUM(IF($C27=Detections[],IF(Detections[Is Active]="yes",1,0),0))>0,SUM(IF($C27=Detections[],IF(Detections[Is Active]="yes",1,0),0)),"")} | J27: {=IF(IF(ISNUMBER(Techniques[[#This Row],[No. of Sub Techniques]]), Techniques[[#This Row],[No. of Sub Techniques]]>0,FALSE),SUM(IF(Techniques[[#This Row],[Technique]]=Techniques[Technique],Techniques[Detection Rules for Technique],0))-IF(ISNUMBER(Techniques[[#This Row],[Detection Rules for Technique]]),Techniques[[#This Row],[Detection Rules for Technique]],0),"")} | K27: =IF(AND(ISNUMBER(Techniques[[#This Row],[No. of Sub Techniques]]),Techniques[[#This Row],[No. of Sub Techniques]]>1),Techniques[No. of Sub Techniques],1) -> 1 | M27: {=Techniques[[#This Row],[Min. Detection Rules]]+IF(IF(ISNUMBER(Techniques[[#This Row],[No. of Sub Techniques]]),Techniques[[#This Row],[No. of Sub Techniques]]>0,FALSE),SUM(IF(Techniques[[#This Row],[Technique]]=Techniques[Technique],Techniques[Detection Rules Modifier],0)),Techniques[[#This Row],[Detection Rules Modifier]])} -> 1 | N27: =IF(ISNUMBER(Techniques[[#This Row],[Detection Rules for Technique]]),Techniques[[#This Row],[Detection Rules for Technique]],0)+IF(ISNUMBER(Techniques[[#This Row],[Detection Rules for SubTech]]),Techniques[[#This Row],[Detection Rules for SubTech]],0) -> 0 | O27: =IF(Techniques[[#This Row],[Detection Rules]]>=Techniques[[#This Row],[Expected Detection Rules]],1,Techniques[[#This Row],[Detection Rules]]/Techniques[[#This Row],[Expected Detection Rules]]) -> 0 | P27: =IF(Techniques[[#This Row],[Expected Detection Rules]]<=0,"disabled",IF(Techniques[[#This Row],[Data Sources Available]]>0, IF(Techniques[[#This Row],[Detection Rules]]>0,"detect","no detect"),IF(Techniques[[#This Row],[Detection Rules]]>0,"inconsistent","no sources"))) -> no detect | S27: =IF(Techniques[[#This Row],[Expected Detection Rules]]<0,"expected detection rules negative!",IF(Techniques[[#This Row],[Detection Rules]]>Techniques[[#This Row],[Expected Detection Rules]],"more detection rules than expected!",IF(AND(IF(ISNUMBER(Techniques[[#This Row],[Detection Rules for Technique]]),Techniques[[#This Row],[Detection Rules for Technique]]>0,FALSE),IF(ISNUMBER(Techniques[[#This Row],[No. of Sub Techniques]]),Techniques[[#This Row],[No. of Sub Techniques]]>0,FALSE)),IF(Techniques[[#This Row],[Detection Rules for Technique]] > IF(ISNUMBER(Techniques[[#This Row],[Detection Rules Modifier]]),Techniques[[#This Row],[Detection Rules Modifier]],0), "modifier should be increased for the technique", ""),""))) | T27: Linux, Network, Windows, macOS | U27: Adversaries may attempt to get a listing of other systems by IP address, hostname, or other logical identifier on a network that may be used for Lateral Movement from the current system. Functionality could exist within remote access tools to enable this, but utilities available on the operating system could also be used such as [Ping](https://attack.mitre.org/software/S0097) or <code>net view</code> using [Net](https://attack.mitre.org/software/S0039). Adversaries may also analyze data from local host files (ex: <code>C:\Windows\System32\Drivers\etc\hosts</code> or <code>/etc/hosts</code>) or other passive means (such as local [Arp](https://attack.mitre.org/software/S0099) cache entries) in order to discover the presence of remote systems in an environment. Adversaries may also target discovery of network infrastructure as well as leverage [Network Device CLI](https://attack.mitre.org/techniques/T1059/008) commands on network devices to gather detailed information about systems within a network (e.g. <code>show cdp neighbors</code>, <code>show arp</code>).(Citation: US-CERT-TA18-106A)(Citation: CISA AR21-126A FIVEHANDS May 2021) | V27: System and network discovery techniques normally occur throughout an operation as an adversary learns the environment. Data and events should not be viewed in isolation, but as part of a chain of behavior that could lead to other activities, such as Lateral Movement, based on the information obtained. Normal, benign system and network events related to legitimate remote system discovery may be uncommon, depending on the environment and how they are used. Monitor processes and command-line arguments for actions that could be taken to gather system and network information. Remote access tools with built-in features may interact directly with the Windows API to gather information. Information may also be acquired through Windows system management tools such as [Windows Management Instrumentation](https://attack.mitre.org/techniques/T1047) and [PowerShell](https://attack.mitre.org/techniques/T1059/001). Monitor for processes that can be used to discover remote systems, such as <code>ping.exe</code> and <code>tracert.exe</code>, especially when executed in quick succession.(Citation: Elastic - Koadiac Detection with EQL) | W27: FALSE
A28: T1020 | B28: T1020 | C28: Automated Exfiltration (T1020) | D28: Exfiltration | E28: Command: Command Execution, File: File Access, Network Traffic: Network Connection Creation, Network Traffic: Network Traffic Content, Network Traffic: Network Traffic Flow, Script: Script Execution | F28: =LEN(E28)-LEN(SUBSTITUTE(E28,",",""))+1 -> 6 | G28: {=SUM(IF(ISERROR(FIND(Sources[Data Source],Techniques[[#This Row],[Data Sources]])),0,1)*IF(Sources[Available]="yes",1,0))} -> 4 | H28: {=IF(Techniques[[#This Row],[Technique]]=Techniques[[#This Row],[ID]],SUM(IF(Techniques[[#This Row],[ID]]=Techniques[Technique],1,0))-1,"")} -> 1 | I28: {=IF(SUM(IF($C28=Detections[],IF(Detections[Is Active]="yes",1,0),0))>0,SUM(IF($C28=Detections[],IF(Detections[Is Active]="yes",1,0),0)),"")} | J28: {=IF(IF(ISNUMBER(Techniques[[#This Row],[No. of Sub Techniques]]), Techniques[[#This Row],[No. of Sub Techniques]]>0,FALSE),SUM(IF(Techniques[[#This Row],[Technique]]=Techniques[Technique],Techniques[Detection Rules for Technique],0))-IF(ISNUMBER(Techniques[[#This Row],[Detection Rules for Technique]]),Techniques[[#This Row],[Detection Rules for Technique]],0),"")} -> 1 | K28: =IF(AND(ISNUMBER(Techniques[[#This Row],[No. of Sub Techniques]]),Techniques[[#This Row],[No. of Sub Techniques]]>1),Techniques[No. of Sub Techniques],1) -> 1 | M28: {=Techniques[[#This Row],[Min. Detection Rules]]+IF(IF(ISNUMBER(Techniques[[#This Row],[No. of Sub Techniques]]),Techniques[[#This Row],[No. of Sub Techniques]]>0,FALSE),SUM(IF(Techniques[[#This Row],[Technique]]=Techniques[Technique],Techniques[Detection Rules Modifier],0)),Techniques[[#This Row],[Detection Rules Modifier]])} -> 1 | N28: =IF(ISNUMBER(Techniques[[#This Row],[Detection Rules for Technique]]),Techniques[[#This Row],[Detection Rules for Technique]],0)+IF(ISNUMBER(Techniques[[#This Row],[Detection Rules for SubTech]]),Techniques[[#This Row],[Detection Rules for SubTech]],0) -> 1 | O28: =IF(Techniques[[#This Row],[Detection Rules]]>=Techniques[[#This Row],[Expected Detection Rules]],1,Techniques[[#This Row],[Detection Rules]]/Techniques[[#This Row],[Expected Detection Rules]]) -> 1 | P28: =IF(Techniques[[#This Row],[Expected Detection Rules]]<=0,"disabled",IF(Techniques[[#This Row],[Data Sources Available]]>0, IF(Techniques[[#This Row],[Detection Rules]]>0,"detect","no detect"),IF(Techniques[[#This Row],[Detection Rules]]>0,"inconsistent","no sources"))) -> detect | S28: =IF(Techniques[[#This Row],[Expected Detection Rules]]<0,"expected detection rules negative!",IF(Techniques[[#This Row],[Detection Rules]]>Techniques[[#This Row],[Expected Detection Rules]],"more detection rules than expected!",IF(AND(IF(ISNUMBER(Techniques[[#This Row],[Detection Rules for Technique]]),Techniques[[#This Row],[Detection Rules for Technique]]>0,FALSE),IF(ISNUMBER(Techniques[[#This Row],[No. of Sub Techniques]]),Techniques[[#This Row],[No. of Sub Techniques]]>0,FALSE)),IF(Techniques[[#This Row],[Detection Rules for Technique]] > IF(ISNUMBER(Techniques[[#This Row],[Detection Rules Modifier]]),Techniques[[#This Row],[Detection Rules Modifier]],0), "modifier should be increased for the technique", ""),""))) | T28: Linux, Network, Windows, macOS | U28: Adversaries may exfiltrate data, such as sensitive documents, through the use of automated processing after being gathered during Collection.(Citation: ESET Gamaredon June 2020) When automated exfiltration is used, other exfiltration techniques likely apply as well to transfer the information out of the network, such as [Exfiltration Over C2 Channel](https://attack.mitre.org/techniques/T1041) and [Exfiltration Over Alternative Protocol](https://attack.mitre.org/techniques/T1048). | V28: Monitor process file access patterns and network behavior. Unrecognized processes or scripts that appear to be traversing file systems and sending network traffic may be suspicious. | W28: FALSE
A29: T1020 | B29: T1020.001 | C29: Traffic Duplication (T1020.001) | D29: Exfiltration | E29: Network Traffic: Network Connection Creation, Network Traffic: Network Traffic Flow | F29: =LEN(E29)-LEN(SUBSTITUTE(E29,",",""))+1 -> 2 | G29: {=SUM(IF(ISERROR(FIND(Sources[Data Source],Techniques[[#This Row],[Data Sources]])),0,1)*IF(Sources[Available]="yes",1,0))} -> 2 | H29: {=IF(Techniques[[#This Row],[Technique]]=Techniques[[#This Row],[ID]],SUM(IF(Techniques[[#This Row],[ID]]=Techniques[Technique],1,0))-1,"")} | I29: {=IF(SUM(IF($C29=Detections[],IF(Detections[Is Active]="yes",1,0),0))>0,SUM(IF($C29=Detections[],IF(Detections[Is Active]="yes",1,0),0)),"")} -> 1 | J29: {=IF(IF(ISNUMBER(Techniques[[#This Row],[No. of Sub Techniques]]), Techniques[[#This Row],[No. of Sub Techniques]]>0,FALSE),SUM(IF(Techniques[[#This Row],[Technique]]=Techniques[Technique],Techniques[Detection Rules for Technique],0))-IF(ISNUMBER(Techniques[[#This Row],[Detection Rules for Technique]]),Techniques[[#This Row],[Detection Rules for Technique]],0),"")} | K29: =IF(AND(ISNUMBER(Techniques[[#This Row],[No. of Sub Techniques]]),Techniques[[#This Row],[No. of Sub Techniques]]>1),Techniques[No. of Sub Techniques],1) -> 1 | M29: {=Techniques[[#This Row],[Min. Detection Rules]]+IF(IF(ISNUMBER(Techniques[[#This Row],[No. of Sub Techniques]]),Techniques[[#This Row],[No. of Sub Techniques]]>0,FALSE),SUM(IF(Techniques[[#This Row],[Technique]]=Techniques[Technique],Techniques[Detection Rules Modifier],0)),Techniques[[#This Row],[Detection Rules Modifier]])} -> 1 | N29: =IF(ISNUMBER(Techniques[[#This Row],[Detection Rules for Technique]]),Techniques[[#This Row],[Detection Rules for Technique]],0)+IF(ISNUMBER(Techniques[[#This Row],[Detection Rules for SubTech]]),Techniques[[#This Row],[Detection Rules for SubTech]],0) -> 1 | O29: =IF(Techniques[[#This Row],[Detection Rules]]>=Techniques[[#This Row],[Expected Detection Rules]],1,Techniques[[#This Row],[Detection Rules]]/Techniques[[#This Row],[Expected Detection Rules]]) -> 1 | P29: =IF(Techniques[[#This Row],[Expected Detection Rules]]<=0,"disabled",IF(Techniques[[#This Row],[Data Sources Available]]>0, IF(Techniques[[#This Row],[Detection Rules]]>0,"detect","no detect"),IF(Techniques[[#This Row],[Detection Rules]]>0,"inconsistent","no sources"))) -> detect | S29: =IF(Techniques[[#This Row],[Expected Detection Rules]]<0,"expected detection rules negative!",IF(Techniques[[#This Row],[Detection Rules]]>Techniques[[#This Row],[Expected Detection Rules]],"more detection rules than expected!",IF(AND(IF(ISNUMBER(Techniques[[#This Row],[Detection Rules for Technique]]),Techniques[[#This Row],[Detection Rules for Technique]]>0,FALSE),IF(ISNUMBER(Techniques[[#This Row],[No. of Sub Techniques]]),Techniques[[#This Row],[No. of Sub Techniques]]>0,FALSE)),IF(Techniques[[#This Row],[Detection Rules for Technique]] > IF(ISNUMBER(Techniques[[#This Row],[Detection Rules Modifier]]),Techniques[[#This Row],[Detection Rules Modifier]],0), "modifier should be increased for the technique", ""),""))) | T29: IaaS, Network | U29: Adversaries may leverage traffic mirroring in order to automate data exfiltration over compromised infrastructure. Traffic mirroring is a native feature for some devices, often used for network analysis. For example, devices may be configured to forward network traffic to one or more destinations for analysis by a network analyzer or other monitoring device. (Citation: Cisco Traffic Mirroring)(Citation: Juniper Traffic Mirroring) Adversaries may abuse traffic mirroring to mirror or redirect network traffic through other infrastructure they control. Malicious modifications to network devices to enable traffic redirection may be possible through [ROMMONkit](https://attack.mitre.org/techniques/T1542/004) or [Patch System Image](https://attack.mitre.org/techniques/T1601/001).(Citation: US-CERT-TA18-106A)(Citation: Cisco Blog Legacy Device Attacks) Many cloud-based environments also support traffic mirroring. For example, AWS Traffic Mirroring, GCP Packet Mirroring, and Azure vTap allow users to define specified instances to collect traffic from and specified targets to send collected traffic to.(Citation: AWS Traffic Mirroring)(Citation: GCP Packet Mirroring)(Citation: Azure Virtual Network TAP) Adversaries may use traffic duplication in conjunction with [Network Sniffing](https://attack.mitre.org/techniques/T1040), [Input Capture](https://attack.mitre.org/techniques/T1056), or [Adversary-in-the-Middle](https://attack.mitre.org/techniques/T1557) depending on the goals and objectives of the adversary. | V29: Monitor network traffic for uncommon data flows (e.g. unusual network communications, suspicious communications that have never been seen before, communications sending fixed size data packets at regular intervals). Analyze packet contents to detect communications that do not follow the expected protocol behavior for the port that is being used. | W29: TRUE | X29: T1020
A30: T1021 | B30: T1021 | C30: Remote Services (T1021) | D30: Lateral Movement | E30: Command: Command Execution, Logon Session: Logon Session Creation, Module: Module Load, Network Share: Network Share Access, Network Traffic: Network Connection Creation, Network Traffic: Network Traffic Flow, Process: Process Creation, WMI: WMI Creation | F30: =LEN(E30)-LEN(SUBSTITUTE(E30,",",""))+1 -> 8 | G30: {=SUM(IF(ISERROR(FIND(Sources[Data Source],Techniques[[#This Row],[Data Sources]])),0,1)*IF(Sources[Available]="yes",1,0))} -> 3 | H30: {=IF(Techniques[[#This Row],[Technique]]=Techniques[[#This Row],[ID]],SUM(IF(Techniques[[#This Row],[ID]]=Techniques[Technique],1,0))-1,"")} -> 8 | I30: {=IF(SUM(IF($C30=Detections[],IF(Detections[Is Active]="yes",1,0),0))>0,SUM(IF($C30=Detections[],IF(Detections[Is Active]="yes",1,0),0)),"")} | J30: {=IF(IF(ISNUMBER(Techniques[[#This Row],[No. of Sub Techniques]]), Techniques[[#This Row],[No. of Sub Techniques]]>0,FALSE),SUM(IF(Techniques[[#This Row],[Technique]]=Techniques[Technique],Techniques[Detection Rules for Technique],0))-IF(ISNUMBER(Techniques[[#This Row],[Detection Rules for Technique]]),Techniques[[#This Row],[Detection Rules for Technique]],0),"")} -> 0 | K30: =IF(AND(ISNUMBER(Techniques[[#This Row],[No. of Sub Techniques]]),Techniques[[#This Row],[No. of Sub Techniques]]>1),Techniques[No. of Sub Techniques],1) -> 8 | M30: {=Techniques[[#This Row],[Min. Detection Rules]]+IF(IF(ISNUMBER(Techniques[[#This Row],[No. of Sub Techniques]]),Techniques[[#This Row],[No. of Sub Techniques]]>0,FALSE),SUM(IF(Techniques[[#This Row],[Technique]]=Techniques[Technique],Techniques[Detection Rules Modifier],0)),Techniques[[#This Row],[Detection Rules Modifier]])} -> 8 | N30: =IF(ISNUMBER(Techniques[[#This Row],[Detection Rules for Technique]]),Techniques[[#This Row],[Detection Rules for Technique]],0)+IF(ISNUMBER(Techniques[[#This Row],[Detection Rules for SubTech]]),Techniques[[#This Row],[Detection Rules for SubTech]],0) -> 0 | O30: =IF(Techniques[[#This Row],[Detection Rules]]>=Techniques[[#This Row],[Expected Detection Rules]],1,Techniques[[#This Row],[Detection Rules]]/Techniques[[#This Row],[Expected Detection Rules]]) -> 0 | P30: =IF(Techniques[[#This Row],[Expected Detection Rules]]<=0,"disabled",IF(Techniques[[#This Row],[Data Sources Available]]>0, IF(Techniques[[#This Row],[Detection Rules]]>0,"detect","no detect"),IF(Techniques[[#This Row],[Detection Rules]]>0,"inconsistent","no sources"))) -> no detect | S30: =IF(Techniques[[#This Row],[Expected Detection Rules]]<0,"expected detection rules negative!",IF(Techniques[[#This Row],[Detection Rules]]>Techniques[[#This Row],[Expected Detection Rules]],"more detection rules than expected!",IF(AND(IF(ISNUMBER(Techniques[[#This Row],[Detection Rules for Technique]]),Techniques[[#This Row],[Detection Rules for Technique]]>0,FALSE),IF(ISNUMBER(Techniques[[#This Row],[No. of Sub Techniques]]),Techniques[[#This Row],[No. of Sub Techniques]]>0,FALSE)),IF(Techniques[[#This Row],[Detection Rules for Technique]] > IF(ISNUMBER(Techniques[[#This Row],[Detection Rules Modifier]]),Techniques[[#This Row],[Detection Rules Modifier]],0), "modifier should be increased for the technique", ""),""))) | T30: IaaS, Linux, Windows, macOS | U30: Adversaries may use [Valid Accounts](https://attack.mitre.org/techniques/T1078) to log into a service that accepts remote connections, such as telnet, SSH, and VNC. The adversary may then perform actions as the logged-on user. In an enterprise environment, servers and workstations can be organized into domains. Domains provide centralized identity management, allowing users to login using one set of credentials across the entire network. If an adversary is able to obtain a set of valid domain credentials, they could login to many different machines using remote access protocols such as secure shell (SSH) or remote desktop protocol (RDP).(Citation: SSH Secure Shell)(Citation: TechNet Remote Desktop Services) They could also login to accessible SaaS or IaaS services, such as those that federate their identities to the domain. Legitimate applications (such as [Software Deployment Tools](https://attack.mitre.org/techniques/T1072) and other administrative programs) may utilize [Remote Services](https://attack.mitre.org/techniques/T1021) to access remote hosts. For example, Apple Remote Desktop (ARD) on macOS is native software used for remote management. ARD leverages a blend of protocols, including [VNC](https://attack.mitre.org/techniques/T1021/005) to send the screen and control buffers and [SSH](https://attack.mitre.org/techniques/T1021/004) for secure file transfer.(Citation: Remote Management MDM macOS)(Citation: Kickstart Apple Remote Desktop commands)(Citation: Apple Remote Desktop Admin Guide 3.3) Adversaries can abuse applications such as ARD to gain remote code execution and perform lateral movement. In versions of macOS prior to 10.14, an adversary can escalate an SSH session to an ARD session which enables an adversary to accept TCC (Transparency, Consent, and Control) prompts without user interaction and gain access to data.(Citation: FireEye 2019 Apple Remote Desktop)(Citation: Lockboxx ARD 2019)(Citation: Kickstart Apple Remote Desktop commands) | V30: Correlate use of login activity related to remote services with unusual behavior or other malicious or suspicious activity. Adversaries will likely need to learn about an environment and the relationships between systems through Discovery techniques prior to attempting Lateral Movement. Use of applications such as ARD may be legitimate depending on the environment and how it’s used. Other factors, such as access patterns and activity that occurs after a remote login, may indicate suspicious or malicious behavior using these applications. Monitor for user accounts logged into systems they would not normally access or access patterns to multiple systems over a relatively short period of time. In macOS, you can review logs for "screensharingd" and "Authentication" event messages. Monitor network connections regarding remote management (ports tcp:3283 and tcp:5900) and for remote login (port tcp:22).(Citation: Lockboxx ARD 2019)(Citation: Apple Unified Log Analysis Remote Login and Screen Sharing) | W30: FALSE
A31: T1021 | B31: T1021.001 | C31: Remote Desktop Protocol (T1021.001) | D31: Lateral Movement | E31: Logon Session: Logon Session Creation, Logon Session: Logon Session Metadata, Network Traffic: Network Connection Creation, Network Traffic: Network Traffic Flow, Process: Process Creation | F31: =LEN(E31)-LEN(SUBSTITUTE(E31,",",""))+1 -> 5 | G31: {=SUM(IF(ISERROR(FIND(Sources[Data Source],Techniques[[#This Row],[Data Sources]])),0,1)*IF(Sources[Available]="yes",1,0))} -> 2 | H31: {=IF(Techniques[[#This Row],[Technique]]=Techniques[[#This Row],[ID]],SUM(IF(Techniques[[#This Row],[ID]]=Techniques[Technique],1,0))-1,"")} | I31: {=IF(SUM(IF($C31=Detections[],IF(Detections[Is Active]="yes",1,0),0))>0,SUM(IF($C31=Detections[],IF(Detections[Is Active]="yes",1,0),0)),"")} | J31: {=IF(IF(ISNUMBER(Techniques[[#This Row],[No. of Sub Techniques]]), Techniques[[#This Row],[No. of Sub Techniques]]>0,FALSE),SUM(IF(Techniques[[#This Row],[Technique]]=Techniques[Technique],Techniques[Detection Rules for Technique],0))-IF(ISNUMBER(Techniques[[#This Row],[Detection Rules for Technique]]),Techniques[[#This Row],[Detection Rules for Technique]],0),"")} | K31: =IF(AND(ISNUMBER(Techniques[[#This Row],[No. of Sub Techniques]]),Techniques[[#This Row],[No. of Sub Techniques]]>1),Techniques[No. of Sub Techniques],1) -> 1 | M31: {=Techniques[[#This Row],[Min. Detection Rules]]+IF(IF(ISNUMBER(Techniques[[#This Row],[No. of Sub Techniques]]),Techniques[[#This Row],[No. of Sub Techniques]]>0,FALSE),SUM(IF(Techniques[[#This Row],[Technique]]=Techniques[Technique],Techniques[Detection Rules Modifier],0)),Techniques[[#This Row],[Detection Rules Modifier]])} -> 1 | N31: =IF(ISNUMBER(Techniques[[#This Row],[Detection Rules for Technique]]),Techniques[[#This Row],[Detection Rules for Technique]],0)+IF(ISNUMBER(Techniques[[#This Row],[Detection Rules for SubTech]]),Techniques[[#This Row],[Detection Rules for SubTech]],0) -> 0 | O31: =IF(Techniques[[#This Row],[Detection Rules]]>=Techniques[[#This Row],[Expected Detection Rules]],1,Techniques[[#This Row],[Detection Rules]]/Techniques[[#This Row],[Expected Detection Rules]]) -> 0 | P31: =IF(Techniques[[#This Row],[Expected Detection Rules]]<=0,"disabled",IF(Techniques[[#This Row],[Data Sources Available]]>0, IF(Techniques[[#This Row],[Detection Rules]]>0,"detect","no detect"),IF(Techniques[[#This Row],[Detection Rules]]>0,"inconsistent","no sources"))) -> no detect | S31: =IF(Techniques[[#This Row],[Expected Detection Rules]]<0,"expected detection rules negative!",IF(Techniques[[#This Row],[Detection Rules]]>Techniques[[#This Row],[Expected Detection Rules]],"more detection rules than expected!",IF(AND(IF(ISNUMBER(Techniques[[#This Row],[Detection Rules for Technique]]),Techniques[[#This Row],[Detection Rules for Technique]]>0,FALSE),IF(ISNUMBER(Techniques[[#This Row],[No. of Sub Techniques]]),Techniques[[#This Row],[No. of Sub Techniques]]>0,FALSE)),IF(Techniques[[#This Row],[Detection Rules for Technique]] > IF(ISNUMBER(Techniques[[#This Row],[Detection Rules Modifier]]),Techniques[[#This Row],[Detection Rules Modifier]],0), "modifier should be increased for the technique", ""),""))) | T31: Windows | U31: Adversaries may use [Valid Accounts](https://attack.mitre.org/techniques/T1078) to log into a computer using the Remote Desktop Protocol (RDP). The adversary may then perform actions as the logged-on user. Remote desktop is a common feature in operating systems. It allows a user to log into an interactive session with a system desktop graphical user interface on a remote system. Microsoft refers to its implementation of the Remote Desktop Protocol (RDP) as Remote Desktop Services (RDS).(Citation: TechNet Remote Desktop Services) Adversaries may connect to a remote system over RDP/RDS to expand access if the service is enabled and allows access to accounts with known credentials. Adversaries will likely use Credential Access techniques to acquire credentials to use with RDP. Adversaries may also use RDP in conjunction with the [Accessibility Features](https://attack.mitre.org/techniques/T1546/008) or [Terminal Services DLL](https://attack.mitre.org/techniques/T1505/005) for Persistence.(Citation: Alperovitch Malware) | V31: Use of RDP may be legitimate, depending on the network environment and how it is used. Other factors, such as access patterns and activity that occurs after a remote login, may indicate suspicious or malicious behavior with RDP. Monitor for user accounts logged into systems they would not normally access or access patterns to multiple systems over a relatively short period of time. | W31: TRUE | X31: T1021
A32: T1021 | B32: T1021.002 | C32: SMB/Windows Admin Shares (T1021.002) | D32: Lateral Movement | E32: Command: Command Execution, Logon Session: Logon Session Creation, Network Share: Network Share Access, Network Traffic: Network Connection Creation, Network Traffic: Network Traffic Flow, Process: Process Creation | F32: =LEN(E32)-LEN(SUBSTITUTE(E32,",",""))+1 -> 6 | G32: {=SUM(IF(ISERROR(FIND(Sources[Data Source],Techniques[[#This Row],[Data Sources]])),0,1)*IF(Sources[Available]="yes",1,0))} -> 3 | H32: {=IF(Techniques[[#This Row],[Technique]]=Techniques[[#This Row],[ID]],SUM(IF(Techniques[[#This Row],[ID]]=Techniques[Technique],1,0))-1,"")} | I32: {=IF(SUM(IF($C32=Detections[],IF(Detections[Is Active]="yes",1,0),0))>0,SUM(IF($C32=Detections[],IF(Detections[Is Active]="yes",1,0),0)),"")} | J32: {=IF(IF(ISNUMBER(Techniques[[#This Row],[No. of Sub Techniques]]), Techniques[[#This Row],[No. of Sub Techniques]]>0,FALSE),SUM(IF(Techniques[[#This Row],[Technique]]=Techniques[Technique],Techniques[Detection Rules for Technique],0))-IF(ISNUMBER(Techniques[[#This Row],[Detection Rules for Technique]]),Techniques[[#This Row],[Detection Rules for Technique]],0),"")} | K32: =IF(AND(ISNUMBER(Techniques[[#This Row],[No. of Sub Techniques]]),Techniques[[#This Row],[No. of Sub Techniques]]>1),Techniques[No. of Sub Techniques],1) -> 1 | M32: {=Techniques[[#This Row],[Min. Detection Rules]]+IF(IF(ISNUMBER(Techniques[[#This Row],[No. of Sub Techniques]]),Techniques[[#This Row],[No. of Sub Techniques]]>0,FALSE),SUM(IF(Techniques[[#This Row],[Technique]]=Techniques[Technique],Techniques[Detection Rules Modifier],0)),Techniques[[#This Row],[Detection Rules Modifier]])} -> 1 | N32: =IF(ISNUMBER(Techniques[[#This Row],[Detection Rules for Technique]]),Techniques[[#This Row],[Detection Rules for Technique]],0)+IF(ISNUMBER(Techniques[[#This Row],[Detection Rules for SubTech]]),Techniques[[#This Row],[Detection Rules for SubTech]],0) -> 0 | O32: =IF(Techniques[[#This Row],[Detection Rules]]>=Techniques[[#This Row],[Expected Detection Rules]],1,Techniques[[#This Row],[Detection Rules]]/Techniques[[#This Row],[Expected Detection Rules]]) -> 0 | P32: =IF(Techniques[[#This Row],[Expected Detection Rules]]<=0,"disabled",IF(Techniques[[#This Row],[Data Sources Available]]>0, IF(Techniques[[#This Row],[Detection Rules]]>0,"detect","no detect"),IF(Techniques[[#This Row],[Detection Rules]]>0,"inconsistent","no sources"))) -> no detect | S32: =IF(Techniques[[#This Row],[Expected Detection Rules]]<0,"expected detection rules negative!",IF(Techniques[[#This Row],[Detection Rules]]>Techniques[[#This Row],[Expected Detection Rules]],"more detection rules than expected!",IF(AND(IF(ISNUMBER(Techniques[[#This Row],[Detection Rules for Technique]]),Techniques[[#This Row],[Detection Rules for Technique]]>0,FALSE),IF(ISNUMBER(Techniques[[#This Row],[No. of Sub Techniques]]),Techniques[[#This Row],[No. of Sub Techniques]]>0,FALSE)),IF(Techniques[[#This Row],[Detection Rules for Technique]] > IF(ISNUMBER(Techniques[[#This Row],[Detection Rules Modifier]]),Techniques[[#This Row],[Detection Rules Modifier]],0), "modifier should be increased for the technique", ""),""))) | T32: Windows | U32: Adversaries may use [Valid Accounts](https://attack.mitre.org/techniques/T1078) to interact with a remote network share using Server Message Block (SMB). The adversary may then perform actions as the logged-on user. SMB is a file, printer, and serial port sharing protocol for Windows machines on the same network or domain. Adversaries may use SMB to interact with file shares, allowing them to move laterally throughout a network. Linux and macOS implementations of SMB typically use Samba. Windows systems have hidden network shares that are accessible only to administrators and provide the ability for remote file copy and other administrative functions. Example network shares include `C$`, `ADMIN$`, and `IPC$`. Adversaries may use this technique in conjunction with administrator-level [Valid Accounts](https://attack.mitre.org/techniques/T1078) to remotely access a networked system over SMB,(Citation: Wikipedia Server Message Block) to interact with systems using remote procedure calls (RPCs),(Citation: TechNet RPC) transfer files, and run transferred binaries through remote Execution. Example execution techniques that rely on authenticated sessions over SMB/RPC are [Scheduled Task/Job](https://attack.mitre.org/techniques/T1053), [Service Execution](https://attack.mitre.org/techniques/T1569/002), and [Windows Management Instrumentation](https://attack.mitre.org/techniques/T1047). Adversaries can also use NTLM hashes to access administrator shares on systems with [Pass the Hash](https://attack.mitre.org/techniques/T1550/002) and certain configuration and patch levels.(Citation: Microsoft Admin Shares) | V32: Ensure that proper logging of accounts used to log into systems is turned on and centrally collected. Windows logging is able to collect success/failure for accounts that may be used to move laterally and can be collected using tools such as Windows Event Forwarding. (Citation: Lateral Movement Payne)(Citation: Windows Event Forwarding Payne) Monitor remote login events and associated SMB activity for file transfers and remote process execution. Monitor the actions of remote users who connect to administrative shares. Monitor for use of tools and commands to connect to remote shares, such as [Net](https://attack.mitre.org/software/S0039), on the command-line interface and Discovery techniques that could be used to find remotely accessible systems.(Citation: Medium Detecting WMI Persistence) | W32: TRUE | X32: T1021
A33: T1021 | B33: T1021.003 | C33: Distributed Component Object Model (T1021.003) | D33: Lateral Movement | E33: Module: Module Load, Network Traffic: Network Connection Creation, Process: Process Creation | F33: =LEN(E33)-LEN(SUBSTITUTE(E33,",",""))+1 -> 3 | G33: {=SUM(IF(ISERROR(FIND(Sources[Data Source],Techniques[[#This Row],[Data Sources]])),0,1)*IF(Sources[Available]="yes",1,0))} -> 1 | H33: {=IF(Techniques[[#This Row],[Technique]]=Techniques[[#This Row],[ID]],SUM(IF(Techniques[[#This Row],[ID]]=Techniques[Technique],1,0))-1,"")} | I33: {=IF(SUM(IF($C33=Detections[],IF(Detections[Is Active]="yes",1,0),0))>0,SUM(IF($C33=Detections[],IF(Detections[Is Active]="yes",1,0),0)),"")} | J33: {=IF(IF(ISNUMBER(Techniques[[#This Row],[No. of Sub Techniques]]), Techniques[[#This Row],[No. of Sub Techniques]]>0,FALSE),SUM(IF(Techniques[[#This Row],[Technique]]=Techniques[Technique],Techniques[Detection Rules for Technique],0))-IF(ISNUMBER(Techniques[[#This Row],[Detection Rules for Technique]]),Techniques[[#This Row],[Detection Rules for Technique]],0),"")} | K33: =IF(AND(ISNUMBER(Techniques[[#This Row],[No. of Sub Techniques]]),Techniques[[#This Row],[No. of Sub Techniques]]>1),Techniques[No. of Sub Techniques],1) -> 1 | M33: {=Techniques[[#This Row],[Min. Detection Rules]]+IF(IF(ISNUMBER(Techniques[[#This Row],[No. of Sub Techniques]]),Techniques[[#This Row],[No. of Sub Techniques]]>0,FALSE),SUM(IF(Techniques[[#This Row],[Technique]]=Techniques[Technique],Techniques[Detection Rules Modifier],0)),Techniques[[#This Row],[Detection Rules Modifier]])} -> 1 | N33: =IF(ISNUMBER(Techniques[[#This Row],[Detection Rules for Technique]]),Techniques[[#This Row],[Detection Rules for Technique]],0)+IF(ISNUMBER(Techniques[[#This Row],[Detection Rules for SubTech]]),Techniques[[#This Row],[Detection Rules for SubTech]],0) -> 0 | O33: =IF(Techniques[[#This Row],[Detection Rules]]>=Techniques[[#This Row],[Expected Detection Rules]],1,Techniques[[#This Row],[Detection Rules]]/Techniques[[#This Row],[Expected Detection Rules]]) -> 0 | P33: =IF(Techniques[[#This Row],[Expected Detection Rules]]<=0,"disabled",IF(Techniques[[#This Row],[Data Sources Available]]>0, IF(Techniques[[#This Row],[Detection Rules]]>0,"detect","no detect"),IF(Techniques[[#This Row],[Detection Rules]]>0,"inconsistent","no sources"))) -> no detect | S33: =IF(Techniques[[#This Row],[Expected Detection Rules]]<0,"expected detection rules negative!",IF(Techniques[[#This Row],[Detection Rules]]>Techniques[[#This Row],[Expected Detection Rules]],"more detection rules than expected!",IF(AND(IF(ISNUMBER(Techniques[[#This Row],[Detection Rules for Technique]]),Techniques[[#This Row],[Detection Rules for Technique]]>0,FALSE),IF(ISNUMBER(Techniques[[#This Row],[No. of Sub Techniques]]),Techniques[[#This Row],[No. of Sub Techniques]]>0,FALSE)),IF(Techniques[[#This Row],[Detection Rules for Technique]] > IF(ISNUMBER(Techniques[[#This Row],[Detection Rules Modifier]]),Techniques[[#This Row],[Detection Rules Modifier]],0), "modifier should be increased for the technique", ""),""))) | T33: Windows | U33: Adversaries may use [Valid Accounts](https://attack.mitre.org/techniques/T1078) to interact with remote machines by taking advantage of Distributed Component Object Model (DCOM). The adversary may then perform actions as the logged-on user. The Windows Component Object Model (COM) is a component of the native Windows application programming interface (API) that enables interaction between software objects, or executable code that implements one or more interfaces. Through COM, a client object can call methods of server objects, which are typically Dynamic Link Libraries (DLL) or executables (EXE). Distributed COM (DCOM) is transparent middleware that extends the functionality of COM beyond a local computer using remote procedure call (RPC) technology.(Citation: Fireeye Hunting COM June 2019)(Citation: Microsoft COM) Permissions to interact with local and remote server COM objects are specified by access control lists (ACL) in the Registry.(Citation: Microsoft Process Wide Com Keys) By default, only Administrators may remotely activate and launch COM objects through DCOM.(Citation: Microsoft COM ACL) Through DCOM, adversaries operating in the context of an appropriately privileged user can remotely obtain arbitrary and even direct shellcode execution through Office applications(Citation: Enigma Outlook DCOM Lateral Movement Nov 2017) as well as other Windows objects that contain insecure methods.(Citation: Enigma MMC20 COM Jan 2017)(Citation: Enigma DCOM Lateral Movement Jan 2017) DCOM can also execute macros in existing documents(Citation: Enigma Excel DCOM Sept 2017) and may also invoke [Dynamic Data Exchange](https://attack.mitre.org/techniques/T1559/002) (DDE) execution directly through a COM created instance of a Microsoft Office application(Citation: Cyberreason DCOM DDE Lateral Movement Nov 2017), bypassing the need for a malicious document. DCOM can be used as a method of remotely interacting with [Windows Management Instrumentation](https://attack.mitre.org/techniques/T1047). (Citation: MSDN WMI) | V33: Monitor for COM objects loading DLLs and other modules not typically associated with the application.(Citation: Enigma Outlook DCOM Lateral Movement Nov 2017) Enumeration of COM objects, via [Query Registry](https://attack.mitre.org/techniques/T1012) or [PowerShell](https://attack.mitre.org/techniques/T1059/001), may also proceed malicious use.(Citation: Fireeye Hunting COM June 2019)(Citation: Enigma MMC20 COM Jan 2017) Monitor for spawning of processes associated with COM objects, especially those invoked by a user different than the one currently logged on. Monitor for any influxes or abnormal increases in DCOM related Distributed Computing Environment/Remote Procedure Call (DCE/RPC) traffic (typically over port 135). | W33: TRUE | X33: T1021
